Workbook
Name Print_Titles_0: Contemporary!$A$11:$IV$11
Name Print_Titles_0: Duo!$A$6:$IV$6
Name Print_Titles_0: 'Solo list'!$A$1
Name Print_Titles_0_0: Contemporary!$A$11:$IV$11
Name Print_Titles_0_0: Duo!$A$6:$IV$6
Name Print_Titles_0_0: 'Solo list'!$A$1
Name Print_Titles_0_0_0: Contemporary!$A$11:$IV$11
Name Print_Titles_0_0_0: Duo!$A$6:$IV$6
Name Print_Titles_0_0_0: 'Solo list'!$A$1
Name Print_Titles_0_0_0_0: Contemporary!$A$11:$IV$11
Name Print_Titles_0_0_0_0: Duo!$A$6:$IV$6
Name Print_Titles_0_0_0_0: 'Solo list'!$A$1
Name Print_Titles_0_0_0_0_0: Contemporary!$A$11:$IV$11
Name Print_Titles_0_0_0_0_0: Duo!$A$6:$IV$6
Name Print_Titles_0_0_0_0_0: 'Solo list'!$A$1
Name Print_Titles_0_0_0_0_0_0: Contemporary!$A$11:$IV$11
Name Print_Titles_0_0_0_0_0_0: Duo!$A$6:$IV$6
Name Print_Titles_0_0_0_0_0_0: 'Solo list'!$A$1
Name Print_Titles_0_0_0_0_0_0_0: Contemporary!$A$11:$IV$11
Name Print_Titles_0_0_0_0_0_0_0: Duo!$A$6:$IV$6
Name Print_Titles_0_0_0_0_0_0_0: 'Solo list'!$A$1
Name Print_Titles_0_0_0_0_0_0_0_0: Contemporary!$A$11:$IV$11
Name Print_Titles_0_0_0_0_0_0_0_0: Duo!$A$6:$IV$6
Name Print_Titles_0_0_0_0_0_0_0_0: 'Solo list'!$A$1
Name Print_Titles_0_0_0_0_0_0_0_0_0: Contemporary!$A$11:$IV$11
Name Print_Titles_0_0_0_0_0_0_0_0_0: Duo!$A$6:$IV$6
Name Print_Titles_0_0_0_0_0_0_0_0_0: 'Solo list'!$A$1
Name Print_Titles_0_0_0_0_0_0_0_0_0_0: Contemporary!$A$11:$IV$11
Name Print_Titles_0_0_0_0_0_0_0_0_0_0: Duo!$A$6:$IV$6
Name Print_Titles_0_0_0_0_0_0_0_0_0_0: 'Solo list'!$A$1
Name Print_Titles_0_0_0_0_0_0_0_0_0_0_0: Contemporary!$A$11:$IV$11
Name Print_Titles_0_0_0_0_0_0_0_0_0_0_0: Duo!$A$6:$IV$6
Name Print_Titles_0_0_0_0_0_0_0_0_0_0_0: 'Solo list'!$A$1
Name repertoire_csv: CSV!$A$1:$A$536
Name repertoirelist: Contemporary!$B$1:$W$324
Name Table1: #REF!

Sheet Contemporary
B1: WIP | C1: Key | D1: Title | E1: Artist | F1: Cover? | G1: Year | H1: Genre | I1: Genre 2 | K1: Tags | M1: Title | N1: Artist | O1: Release | P1: BPM | Q1: Energy | R1: Dance | S1: Loud | T1: Valence | U1: Length | V1: Acoustic | W1: Popularity
A3: =RAND() -> 0.81236922 | B3: WIP | C3: F#m | D3: 1973 | E3: James Blunt | G3: 2007 | H3: Rock | I3: Pop | J3: pop;alternative;love;dance | K3: =CONCATENATE(SUBSTITUTE(Spotify!J3,",",";"),";",J3) -> ;pop;alternative;love;dance | M3: =Spotify!B3 -> 1973 | N3: =Spotify!D3 -> James Blunt | O3: =Spotify!E3 -> 39330 | P3: =ROUND(Spotify!U3,0) -> 123 | Q3: =ROUND(Spotify!L3*100,0) -> 67 | R3: =ROUND(Spotify!K3*100,0) -> 72 | S3: =Spotify!N3 -> -7.928 | T3: =ROUND(Spotify!T3*100,0) -> 77 | U3: =ROUND(Spotify!F3/60000,1) -> 4.7 | V3: =ROUND(Spotify!Q3*100,0) -> 7 | W3: =Spotify!G3 -> 75
C4: G | D4: A Hard Day's Night | E4: Beatles | G4: 1964 | H4: Rock | J4: dance;jive;fast;groovy;love;oldies;retro | K4: =CONCATENATE(SUBSTITUTE(Spotify!J4,",",";"),";",J4) -> classic rock;psychedelic rock;dance;jive;fast;groovy;love;oldies;retro | M4: =Spotify!B4 -> A Hard Day's Night - Remastered 2015 | N4: =Spotify!D4 -> The Beatles | O4: =Spotify!E4 -> 36843 | P4: =ROUND(Spotify!U4,0) -> 139 | Q4: =ROUND(Spotify!L4*100,0) -> 82 | R4: =ROUND(Spotify!K4*100,0) -> 55 | S4: =Spotify!N4 -> -4.89 | T4: =ROUND(Spotify!T4*100,0) -> 76 | U4: =ROUND(Spotify!F4/60000,1) -> 2.5 | V4: =ROUND(Spotify!Q4*100,0) -> 5 | W4: =Spotify!G4 -> 54
A5: =RAND() -> 0.52698433 | B5: WIP | C5: A | D5: A Little Less Conversation | E5: Elvis Presley | G5: 1968 | H5: Rock | J5: dance;jive;fast;groovy;love;oldies;retro | K5: =CONCATENATE(SUBSTITUTE(Spotify!J5,",",";"),";",J5) -> rockabilly;rock and roll;dance;jive;fast;groovy;love;oldies;retro | M5: =Spotify!B5 -> A Little Less Conversation | N5: =Spotify!D5 -> Elvis Presley | O5: =Spotify!E5 -> 2007 | P5: =ROUND(Spotify!U5,0) -> 114 | Q5: =ROUND(Spotify!L5*100,0) -> 80 | R5: =ROUND(Spotify!K5*100,0) -> 58 | S5: =Spotify!N5 -> -8.03 | T5: =ROUND(Spotify!T5*100,0) -> 84 | U5: =ROUND(Spotify!F5/60000,1) -> 2 | V5: =ROUND(Spotify!Q5*100,0) -> 15 | W5: =Spotify!G5 -> 56
A6: =RAND() -> 0.038804632 | B6: WIP | C6: F | D6: A Little More | E6: Eric Hutchinson | G6: 2014 | H6: Rock | I6: Pop | J6: fast;dance;groovy;alternative | K6: =CONCATENATE(SUBSTITUTE(Spotify!J6,",",";"),";",J6) -> ;fast;dance;groovy;alternative | M6: =Spotify!B6 -> A Little More | N6: =Spotify!D6 -> Eric Hutchinson | O6: =Spotify!E6 -> 41737 | P6: =ROUND(Spotify!U6,0) -> 80 | Q6: =ROUND(Spotify!L6*100,0) -> 74 | R6: =ROUND(Spotify!K6*100,0) -> 64 | S6: =Spotify!N6 -> -5.084 | T6: =ROUND(Spotify!T6*100,0) -> 94 | U6: =ROUND(Spotify!F6/60000,1) -> 3.3 | V6: =ROUND(Spotify!Q6*100,0) -> 1 | W6: =Spotify!G6 -> 44
A7: =RAND() -> 0.33794738 | B7: WIP | C7: Dm | D7: A Man For All Seasons | E7: Robbie Williams | G7: 2003 | H7: Soundtrack | J7: dance;groovy | K7: =CONCATENATE(SUBSTITUTE(Spotify!J7,",",";"),";",J7) -> soundtrack;score;dance;groovy | M7: =Spotify!B7 -> Zimmer: A Man For All Seasons | N7: =Spotify!D7 -> Hans Zimmer;Robbie Williams | O7: =Spotify!E7 -> 37622 | P7: =ROUND(Spotify!U7,0) -> 124 | Q7: =ROUND(Spotify!L7*100,0) -> 74 | R7: =ROUND(Spotify!K7*100,0) -> 58 | S7: =Spotify!N7 -> -8.36 | T7: =ROUND(Spotify!T7*100,0) -> 82 | U7: =ROUND(Spotify!F7/60000,1) -> 4 | V7: =ROUND(Spotify!Q7*100,0) -> 1 | W7: =Spotify!G7 -> 42
A8: =RAND() -> 0.67198577 | D8: A Sky Full Of Stars | E8: Coldplay | G8: 2014 | H8: Rock | I8: Alternative | J8: alternative | K8: =CONCATENATE(SUBSTITUTE(Spotify!J8,",",";"),";",J8) -> ;alternative | M8: =Spotify!B8 -> A Sky Full of Stars | N8: =Spotify!D8 -> Coldplay | O8: =Spotify!E8 -> 41775 | P8: =ROUND(Spotify!U8,0) -> 125 | Q8: =ROUND(Spotify!L8*100,0) -> 68 | R8: =ROUND(Spotify!K8*100,0) -> 55 | S8: =Spotify!N8 -> -6.474 | T8: =ROUND(Spotify!T8*100,0) -> 16 | U8: =ROUND(Spotify!F8/60000,1) -> 4.5 | V8: =ROUND(Spotify!Q8*100,0) -> 1 | W8: =Spotify!G8 -> 88
A9: =RAND() -> 0.63150212 | C9: E | D9: A Thousand Miles | E9: Vanessa Carlton | G9: 2002 | H9: Pop | J9: dance;groovy;love;waltz | K9: =CONCATENATE(SUBSTITUTE(Spotify!J9,",",";"),";",J9) -> ;dance;groovy;love;waltz | M9: =Spotify!B9 -> A Thousand Miles | N9: =Spotify!D9 -> Vanessa Carlton | O9: =Spotify!E9 -> 37376 | P9: =ROUND(Spotify!U9,0) -> 95 | Q9: =ROUND(Spotify!L9*100,0) -> 83 | R9: =ROUND(Spotify!K9*100,0) -> 56 | S9: =Spotify!N9 -> -3.862 | T9: =ROUND(Spotify!T9*100,0) -> 27 | U9: =ROUND(Spotify!F9/60000,1) -> 4 | V9: =ROUND(Spotify!Q9*100,0) -> 32 | W9: =Spotify!G9 -> 83
A10: =RAND() -> 0.079094887 | C10: C | D10: A Thousand Years | E10: Christina Perri | G10: 2011 | H10: Soundtrack | J10: love;slow | K10: =CONCATENATE(SUBSTITUTE(Spotify!J10,",",";"),";",J10) -> soft pop;love;slow | M10: =Spotify!B10 -> a thousand years | N10: =Spotify!D10 -> Christina Perri | O10: =Spotify!E10 -> 40834 | P10: =ROUND(Spotify!U10,0) -> 139 | Q10: =ROUND(Spotify!L10*100,0) -> 41 | R10: =ROUND(Spotify!K10*100,0) -> 42 | S10: =Spotify!N10 -> -7.445 | T10: =ROUND(Spotify!T10*100,0) -> 16 | U10: =ROUND(Spotify!F10/60000,1) -> 4.8 | V10: =ROUND(Spotify!Q10*100,0) -> 31 | W10: =Spotify!G10 -> 86
A11: =RAND() -> 0.72631845 | C11: Gm | D11: Adventure Of A Lifetime | E11: Coldplay | G11: 2015 | H11: Pop | I11: Alternative | J11: dance;alternative | K11: =CONCATENATE(SUBSTITUTE(Spotify!J11,",",";"),";",J11) -> ;dance;alternative | M11: =Spotify!B11 -> Adventure of a Lifetime | N11: =Spotify!D11 -> Coldplay | O11: =Spotify!E11 -> 42342 | P11: =ROUND(Spotify!U11,0) -> 112 | Q11: =ROUND(Spotify!L11*100,0) -> 92 | R11: =ROUND(Spotify!K11*100,0) -> 64 | S11: =Spotify!N11 -> -3.887 | T11: =ROUND(Spotify!T11*100,0) -> 53 | U11: =ROUND(Spotify!F11/60000,1) -> 4.4 | V11: =ROUND(Spotify!Q11*100,0) -> 0 | W11: =Spotify!G11 -> 88
A12: =RAND() -> 0.03777012 | C12: G# | D12: Africa | E12: Toto | G12: 1982 | H12: Rock | I12: Soft Rock | J12: retro;oldies | K12: =CONCATENATE(SUBSTITUTE(Spotify!J12,",",";"),";",J12) -> yacht rock;soft rock;retro;oldies | M12: =Spotify!B12 -> Africa | N12: =Spotify!D12 -> TOTO | O12: =Spotify!E12 -> 30049 | P12: =ROUND(Spotify!U12,0) -> 93 | Q12: =ROUND(Spotify!L12*100,0) -> 37 | R12: =ROUND(Spotify!K12*100,0) -> 67 | S12: =Spotify!N12 -> -18.064 | T12: =ROUND(Spotify!T12*100,0) -> 73 | U12: =ROUND(Spotify!F12/60000,1) -> 4.9 | V12: =ROUND(Spotify!Q12*100,0) -> 26 | W12: =Spotify!G12 -> 90
A13: =RAND() -> 0.90859039 | B13: WIP | C13: E | D13: After Midnight | E13: J J Cale | G13: 1966 | H13: Rock | J13: acoustic;groovy;oldies;retro | K13: =CONCATENATE(SUBSTITUTE(Spotify!J13,",",";"),";",J13) -> blues;roots rock;blues rock;acoustic;groovy;oldies;retro | M13: =Spotify!B13 -> After Midnight | N13: =Spotify!D13 -> J.J. Cale | O13: =Spotify!E13 -> 1972 | P13: =ROUND(Spotify!U13,0) -> 96 | Q13: =ROUND(Spotify!L13*100,0) -> 31 | R13: =ROUND(Spotify!K13*100,0) -> 69 | S13: =Spotify!N13 -> -19.315 | T13: =ROUND(Spotify!T13*100,0) -> 52 | U13: =ROUND(Spotify!F13/60000,1) -> 2.4 | V13: =ROUND(Spotify!Q13*100,0) -> 17 | W13: =Spotify!G13 -> 62
B14: WIP | D14: Aicha | E14: Outlandish | G14: 2002 | H14: RnB | I14: Hip-hop | K14: =CONCATENATE(SUBSTITUTE(Spotify!J14,",",";"),";",J14) -> dansk pop; | M14: =Spotify!B14 -> Aicha | N14: =Spotify!D14 -> Outlandish | O14: =Spotify!E14 -> 37712 | P14: =ROUND(Spotify!U14,0) -> 87 | Q14: =ROUND(Spotify!L14*100,0) -> 64 | R14: =ROUND(Spotify!K14*100,0) -> 75 | S14: =Spotify!N14 -> -5.494 | T14: =ROUND(Spotify!T14*100,0) -> 61 | U14: =ROUND(Spotify!F14/60000,1) -> 4.6 | V14: =ROUND(Spotify!Q14*100,0) -> 21 | W14: =Spotify!G14 -> 58
A15: =RAND() -> 0.19557299 | D15: All About That Bass | E15: Meghan Trainor | G15: 2014 | H15: Doo-wop | J15: dance;jive;groovy | K15: =CONCATENATE(SUBSTITUTE(Spotify!J15,",",";"),";",J15) -> ;dance;jive;groovy | M15: =Spotify!B15 -> All About That Bass | N15: =Spotify!D15 -> Meghan Trainor | O15: =Spotify!E15 -> 42016 | P15: =ROUND(Spotify!U15,0) -> 134 | Q15: =ROUND(Spotify!L15*100,0) -> 89 | R15: =ROUND(Spotify!K15*100,0) -> 81 | S15: =Spotify!N15 -> -3.726 | T15: =ROUND(Spotify!T15*100,0) -> 96 | U15: =ROUND(Spotify!F15/60000,1) -> 3.2 | V15: =ROUND(Spotify!Q15*100,0) -> 6 | W15: =Spotify!G15 -> 71
A16: =RAND() -> 0.63895595 | B16: WIP | C16: C# | D16: All About You | E16: McFly | G16: 2005 | H16: Rock | I16: Pop | J16: love;pop | K16: =CONCATENATE(SUBSTITUTE(Spotify!J16,",",";"),";",J16) -> ;love;pop | M16: =Spotify!B16 -> All About You | N16: =Spotify!D16 -> McFly | O16: =Spotify!E16 -> 38353 | P16: =ROUND(Spotify!U16,0) -> 130 | Q16: =ROUND(Spotify!L16*100,0) -> 56 | R16: =ROUND(Spotify!K16*100,0) -> 54 | S16: =Spotify!N16 -> -5.313 | T16: =ROUND(Spotify!T16*100,0) -> 30 | U16: =ROUND(Spotify!F16/60000,1) -> 3.1 | V16: =ROUND(Spotify!Q16*100,0) -> 20 | W16: =Spotify!G16 -> 59
A17: =RAND() -> 0.17884601 | C17: D | D17: All I Have To Do Is Dream | E17: Everly Brothers | G17: 1958 | H17: Rock 'n' roll | J17: love;slow;oldies;retro;sweet | K17: =CONCATENATE(SUBSTITUTE(Spotify!J17,",",";"),";",J17) -> doo-wop;love;slow;oldies;retro;sweet | M17: =Spotify!B17 -> All I Have to Do Is Dream | N17: =Spotify!D17 -> The Everly Brothers | O17: =Spotify!E17 -> 23590 | P17: =ROUND(Spotify!U17,0) -> 96 | Q17: =ROUND(Spotify!L17*100,0) -> 46 | R17: =ROUND(Spotify!K17*100,0) -> 53 | S17: =Spotify!N17 -> -8.172 | T17: =ROUND(Spotify!T17*100,0) -> 53 | U17: =ROUND(Spotify!F17/60000,1) -> 2.4 | V17: =ROUND(Spotify!Q17*100,0) -> 84 | W17: =Spotify!G17 -> 70
A18: =RAND() -> 0.22293151 | C18: F | D18: All Star | E18: Smash Mouth | G18: 1999 | H18: Rock | I18: Alternative | J18: alternative | K18: =CONCATENATE(SUBSTITUTE(Spotify!J18,",",";"),";",J18) -> ;alternative | M18: =Spotify!B18 -> All Star | N18: =Spotify!D18 -> Smash Mouth | O18: =Spotify!E18 -> 36319 | P18: =ROUND(Spotify!U18,0) -> 104 | Q18: =ROUND(Spotify!L18*100,0) -> 87 | R18: =ROUND(Spotify!K18*100,0) -> 73 | S18: =Spotify!N18 -> -5.881 | T18: =ROUND(Spotify!T18*100,0) -> 78 | U18: =ROUND(Spotify!F18/60000,1) -> 3.3 | V18: =ROUND(Spotify!Q18*100,0) -> 4 | W18: =Spotify!G18 -> 82
A19: =RAND() -> 0.0021019655 | B19: WIP | C19: G | D19: Angel Of The Morning | E19: Juice Newton | G19: 1981 | H19: Country | J19: love;slow;oldies;retro | K19: =CONCATENATE(SUBSTITUTE(Spotify!J19,",",";"),";",J19) -> ;love;slow;oldies;retro | M19: =Spotify!B19 -> Angel Of The Morning | N19: =Spotify!D19 -> Juice Newton | O19: =Spotify!E19 -> 29587 | P19: =ROUND(Spotify!U19,0) -> 76 | Q19: =ROUND(Spotify!L19*100,0) -> 31 | R19: =ROUND(Spotify!K19*100,0) -> 45 | S19: =Spotify!N19 -> -9.309 | T19: =ROUND(Spotify!T19*100,0) -> 34 | U19: =ROUND(Spotify!F19/60000,1) -> 4.2 | V19: =ROUND(Spotify!Q19*100,0) -> 43 | W19: =Spotify!G19 -> 68
A20: =RAND() -> 0.50212663 | D20: Angels | E20: Robbie Williams | G20: 1997 | H20: Rock | I20: Pop / Gospel | J20: love;slow | K20: =CONCATENATE(SUBSTITUTE(Spotify!J20,",",";"),";",J20) -> ;love;slow | M20: =Spotify!B20 -> Angels | N20: =Spotify!D20 -> Robbie Williams | O20: =Spotify!E20 -> 35431 | P20: =ROUND(Spotify!U20,0) -> 150 | Q20: =ROUND(Spotify!L20*100,0) -> 59 | R20: =ROUND(Spotify!K20*100,0) -> 43 | S20: =Spotify!N20 -> -6.362 | T20: =ROUND(Spotify!T20*100,0) -> 26 | U20: =ROUND(Spotify!F20/60000,1) -> 4.4 | V20: =ROUND(Spotify!Q20*100,0) -> 16 | W20: =Spotify!G20 -> 65
A21: =RAND() -> 0.13420442 | C21: G | D21: Annie's Song | E21: John Denver | G21: 1974 | H21: Rock | I21: Folk / Country | J21: love;slow;oldies;retro;waltz | K21: =CONCATENATE(SUBSTITUTE(Spotify!J21,",",";"),";",J21) -> folk;love;slow;oldies;retro;waltz | M21: =Spotify!B21 -> Annie's Song | N21: =Spotify!D21 -> John Denver | O21: =Spotify!E21 -> 27195 | P21: =ROUND(Spotify!U21,0) -> 146 | Q21: =ROUND(Spotify!L21*100,0) -> 31 | R21: =ROUND(Spotify!K21*100,0) -> 30 | S21: =Spotify!N21 -> -10.879 | T21: =ROUND(Spotify!T21*100,0) -> 46 | U21: =ROUND(Spotify!F21/60000,1) -> 3 | V21: =ROUND(Spotify!Q21*100,0) -> 87 | W21: =Spotify!G21 -> 71
D22: Another Day In Paradise | E22: Phil Collins | G22: 1989 | H22: Rock | I22: Soft | J22: alternative;groovy | K22: =CONCATENATE(SUBSTITUTE(Spotify!J22,",",";"),";",J22) -> soft rock;alternative;groovy | M22: =Spotify!B22 -> Another Day in Paradise - 2016 Remaster | N22: =Spotify!D22 -> Phil Collins | O22: =Spotify!E22 -> 32832 | P22: =ROUND(Spotify!U22,0) -> 102 | Q22: =ROUND(Spotify!L22*100,0) -> 57 | R22: =ROUND(Spotify!K22*100,0) -> 78 | S22: =Spotify!N22 -> -7.32 | T22: =ROUND(Spotify!T22*100,0) -> 37 | U22: =ROUND(Spotify!F22/60000,1) -> 5.4 | V22: =ROUND(Spotify!Q22*100,0) -> 74 | W22: =Spotify!G22 -> 84
B23: WIP | C23: F | D23: Answer Me My Love | E23: Inger Marie | G23: 2011 | H23: Jazz | I23: Smooth | K23: =CONCATENATE(SUBSTITUTE(Spotify!J23,",",";"),";",J23) -> vocal jazz;smooth jazz;jazz pop; | M23: =Spotify!B23 -> Answer Me, My Love | N23: =Spotify!D23 -> Inger Marie Gundersen | O23: =Spotify!E23 -> 40847 | P23: =ROUND(Spotify!U23,0) -> 89 | Q23: =ROUND(Spotify!L23*100,0) -> 8 | R23: =ROUND(Spotify!K23*100,0) -> 63 | S23: =Spotify!N23 -> -27.517 | T23: =ROUND(Spotify!T23*100,0) -> 37 | U23: =ROUND(Spotify!F23/60000,1) -> 3.8 | V23: =ROUND(Spotify!Q23*100,0) -> 77 | W23: =Spotify!G23 -> 18
A24: =RAND() -> 0.69948315 | B24: WIP | C24: Cm | D24: Antonio's Song | E24: Till Brönner | F24: Michael Franks | G24: 1977 | H24: Jazz | I24: Smooth | J24: groovy;jazz;slow;oldies;retro | K24: =CONCATENATE(SUBSTITUTE(Spotify!J24,",",";"),";",J24) -> smooth jazz;jazz;groovy;jazz;slow;oldies;retro | M24: =Spotify!B24 -> Antonio's Song | N24: =Spotify!D24 -> Till Brönner | O24: =Spotify!E24 -> 38145 | P24: =ROUND(Spotify!U24,0) -> 114 | Q24: =ROUND(Spotify!L24*100,0) -> 39 | R24: =ROUND(Spotify!K24*100,0) -> 68 | S24: =Spotify!N24 -> -14.082 | T24: =ROUND(Spotify!T24*100,0) -> 65 | U24: =ROUND(Spotify!F24/60000,1) -> 5 | V24: =ROUND(Spotify!Q24*100,0) -> 46 | W24: =Spotify!G24 -> 27
A25: =RAND() -> 0.42480174 | B25: WIP | D25: Ave Maria | E25: Beyonce | G25: 2008 | H25: Pop | I25: RnB | J25: love;groovy | K25: =CONCATENATE(SUBSTITUTE(Spotify!J28,",",";"),";",J25) -> ;love;groovy | M25: =Spotify!B28 -> Believer | N25: =Spotify!D28 -> Imagine Dragons | O25: =Spotify!E28 -> 42909 | P25: =ROUND(Spotify!U28,0) -> 125 | Q25: =ROUND(Spotify!L28*100,0) -> 78 | R25: =ROUND(Spotify!K28*100,0) -> 78 | S25: =Spotify!N28 -> -4.374 | T25: =ROUND(Spotify!T28*100,0) -> 67 | U25: =ROUND(Spotify!F28/60000,1) -> 3.4 | V25: =ROUND(Spotify!Q28*100,0) -> 6 | W25: =Spotify!G28 -> 88
A26: =RAND() -> 0.26934975 | B26: WIP | C26: Bm | D26: Baby One More Time | E26: Britney Spears | G26: 1998 | H26: Pop | J26: love;groovy;dance | K26: =CONCATENATE(SUBSTITUTE(Spotify!J29,",",";"),";",J26) -> classical crossover;opera;love;groovy;dance | M26: =Spotify!B29 -> Bésame Mucho | N26: =Spotify!D29 -> Andrea Bocelli | O26: =Spotify!E29 -> 38718 | P26: =ROUND(Spotify!U29,0) -> 95 | Q26: =ROUND(Spotify!L29*100,0) -> 50 | R26: =ROUND(Spotify!K29*100,0) -> 52 | S26: =Spotify!N29 -> -8.521 | T26: =ROUND(Spotify!T29*100,0) -> 38 | U26: =ROUND(Spotify!F29/60000,1) -> 4 | V26: =ROUND(Spotify!Q29*100,0) -> 89 | W26: =Spotify!G29 -> 65
A27: =RAND() -> 0.20312101 | B27: WIP | C27: Em | D27: Beautiful Tango | E27: Hindi Zahra | G27: 2010 | H27: Soul | I27: Folk | J27: alternative;acoustic | K27: =CONCATENATE(SUBSTITUTE(Spotify!#REF!,",",";"),";",J27) -> #REF! | M27: =Spotify!#REF! -> #REF! | N27: =Spotify!#REF! -> #REF! | O27: =Spotify!#REF! -> #REF! | P27: =ROUND(Spotify!#REF!,0) -> #REF! | Q27: =ROUND(Spotify!#REF!*100,0) -> #REF! | R27: =ROUND(Spotify!#REF!*100,0) -> #REF! | S27: =Spotify!#REF! -> #REF! | T27: =ROUND(Spotify!#REF!*100,0) -> #REF! | U27: =ROUND(Spotify!#REF!/60000,1) -> #REF! | V27: =ROUND(Spotify!#REF!*100,0) -> #REF! | W27: =Spotify!#REF! -> #REF!
A28: =RAND() -> 0.21230257 | C28: Am | D28: Believer | E28: Imagine Dragons | G28: 2017 | H28: Rock | I28: Pop | J28: alternative | K28: =CONCATENATE(SUBSTITUTE(Spotify!J31,",",";"),";",J28) -> folk;folk rock;singer-songwriter;alternative | M28: =Spotify!B31 -> Big Yellow Taxi | N28: =Spotify!D31 -> Joni Mitchell | O28: =Spotify!E31 -> 43560 | P28: =ROUND(Spotify!U31,0) -> 86 | Q28: =ROUND(Spotify!L31*100,0) -> 47 | R28: =ROUND(Spotify!K31*100,0) -> 61 | S28: =Spotify!N31 -> -9.135 | T28: =ROUND(Spotify!T31*100,0) -> 97 | U28: =ROUND(Spotify!F31/60000,1) -> 2.2 | V28: =ROUND(Spotify!Q31*100,0) -> 59 | W28: =Spotify!G31 -> 46
A29: =RAND() -> 0.61707823 | C29: Am | D29: Besame Mucho | E29: Andrea Bocelli | F29: Consuelo Velazquez | G29: 1940 | H29: Latin | I29: Bolero | J29: love;slow;jazz;bossa;oldies;retro | K29: =CONCATENATE(SUBSTITUTE(Spotify!J32,",",";"),";",J29) -> ;love;slow;jazz;bossa;oldies;retro | M29: =Spotify!B32 -> Billie Jean | N29: =Spotify!D32 -> Michael Jackson | O29: =Spotify!E32 -> 39486 | P29: =ROUND(Spotify!U32,0) -> 117 | Q29: =ROUND(Spotify!L32*100,0) -> 65 | R29: =ROUND(Spotify!K32*100,0) -> 92 | S29: =Spotify!N32 -> -3.051 | T29: =ROUND(Spotify!T32*100,0) -> 85 | U29: =ROUND(Spotify!F32/60000,1) -> 4.9 | V29: =ROUND(Spotify!Q32*100,0) -> 2 | W29: =Spotify!G32 -> 82
A30: =RAND() -> 0.96996976 | B30: WIP | D30: Better When I'm Dancing | E30: Meghan Trainor | G30: 2015 | H30: Pop | J30: dance;fast | K30: =CONCATENATE(SUBSTITUTE(Spotify!J33,",",";"),";",J30) -> french jazz;dance;fast | M30: =Spotify!B33 -> Bistro Fada | N30: =Spotify!D33 -> Stephane Wrembel | O30: =Spotify!E33 -> 40676 | P30: =ROUND(Spotify!U33,0) -> 99 | Q30: =ROUND(Spotify!L33*100,0) -> 37 | R30: =ROUND(Spotify!K33*100,0) -> 76 | S30: =Spotify!N33 -> -10.908 | T30: =ROUND(Spotify!T33*100,0) -> 86 | U30: =ROUND(Spotify!F33/60000,1) -> 3 | V30: =ROUND(Spotify!Q33*100,0) -> 89 | W30: =Spotify!G33 -> 52
A31: =RAND() -> 0.039207695 | B31: WIP | D31: Big Yellow Taxi | E31: Joni Mitchell | G31: 1970 | H31: Rock | I31: Folk | J31: pop;acoustic;alternative;retro;oldies | K31: =CONCATENATE(SUBSTITUTE(Spotify!J35,",",";"),";",J31) -> ;pop;acoustic;alternative;retro;oldies | M31: =Spotify!B35 -> Black or White - Single Version | N31: =Spotify!D35 -> Michael Jackson | O31: =Spotify!E35 -> 37942 | P31: =ROUND(Spotify!U35,0) -> 115 | Q31: =ROUND(Spotify!L35*100,0) -> 93 | R31: =ROUND(Spotify!K35*100,0) -> 76 | S31: =Spotify!N35 -> -2.768 | T31: =ROUND(Spotify!T35*100,0) -> 96 | U31: =ROUND(Spotify!F35/60000,1) -> 3.3 | V31: =ROUND(Spotify!Q35*100,0) -> 11 | W31: =Spotify!G35 -> 68
D32: Billie Jean | E32: Michael Jackson | G32: 1982 | H32: Pop | K32: =CONCATENATE(SUBSTITUTE(Spotify!J36,",",";"),";",J32) -> classic rock;psychedelic rock; | M32: =Spotify!B36 -> Blackbird - Remastered 2009 | N32: =Spotify!D36 -> The Beatles | O32: =Spotify!E36 -> 25164 | P32: =ROUND(Spotify!U36,0) -> 94 | Q32: =ROUND(Spotify!L36*100,0) -> 13 | R32: =ROUND(Spotify!K36*100,0) -> 69 | S32: =Spotify!N36 -> -14.361 | T32: =ROUND(Spotify!T36*100,0) -> 37 | U32: =ROUND(Spotify!F36/60000,1) -> 2.3 | V32: =ROUND(Spotify!Q36*100,0) -> 75 | W32: =Spotify!G36 -> 80
A33: =RAND() -> 0.82305478 | B33: WIP | C33: Em | D33: Bistro Fada | E33: Stephane Wrembel | G33: 2011 | H33: Jazz | I33: Gypsy Jazz | J33: instrumental;waltz | K33: =CONCATENATE(SUBSTITUTE(Spotify!J38,",",";"),";",J33) -> folk;folk rock;instrumental;waltz | M33: =Spotify!B38 -> Blowin' in the Wind | N33: =Spotify!D38 -> Peter, Paul and Mary | O33: =Spotify!E38 -> 1963 | P33: =ROUND(Spotify!U38,0) -> 155 | Q33: =ROUND(Spotify!L38*100,0) -> 8 | R33: =ROUND(Spotify!K38*100,0) -> 38 | S33: =Spotify!N38 -> -17.77 | T33: =ROUND(Spotify!T38*100,0) -> 56 | U33: =ROUND(Spotify!F38/60000,1) -> 3 | V33: =ROUND(Spotify!Q38*100,0) -> 83 | W33: =Spotify!G38 -> 60
A34: =RAND() -> 0.83540049 | C34: C | D34: Bitter Sweet Symphony | E34: Verve | G34: 1997 | H34: Rock | I34: Alternative | J34: alternative | K34: =CONCATENATE(SUBSTITUTE(Spotify!J39,",",";"),";",J34) -> yacht rock;alternative | M34: =Spotify!B39 -> Brandy (You're a Fine Girl) | N34: =Spotify!D39 -> Looking Glass | O34: =Spotify!E39 -> 1972 | P34: =ROUND(Spotify!U39,0) -> 125 | Q34: =ROUND(Spotify!L39*100,0) -> 63 | R34: =ROUND(Spotify!K39*100,0) -> 72 | S34: =Spotify!N39 -> -11.369 | T34: =ROUND(Spotify!T39*100,0) -> 83 | U34: =ROUND(Spotify!F39/60000,1) -> 3.2 | V34: =ROUND(Spotify!Q39*100,0) -> 40 | W34: =Spotify!G39 -> 78
B35: WIP | D35: Black Or White | E35: Michael Jackson | G35: 1991 | H35: Pop | I35: RnB | K35: =CONCATENATE(SUBSTITUTE(Spotify!J40,",",";"),";",J35) -> samba;seresta;classical;chamber music;brazilian jazz;bossa nova;latin jazz;afro-cuban jazz;big band;jazz; | M35: =Spotify!B40 -> Brasileirinho | N35: =Spotify!D40 -> Waldir Azevedo;Yo-Yo Ma;Romero Lubambo;Cyro Baptista;Jose De Faria;José Da Silva;Helio Alves;Nilson Matta;Paquito D'Rivera | O35: =Spotify!E40 -> 2003 | P35: =ROUND(Spotify!U40,0) -> 105 | Q35: =ROUND(Spotify!L40*100,0) -> 52 | R35: =ROUND(Spotify!K40*100,0) -> 49 | S35: =Spotify!N40 -> -13.08 | T35: =ROUND(Spotify!T40*100,0) -> 92 | U35: =ROUND(Spotify!F40/60000,1) -> 3.4 | V35: =ROUND(Spotify!Q40*100,0) -> 35 | W35: =Spotify!G40 -> 33
A36: =RAND() -> 0.12828128 | B36: WIP | C36: G | D36: Blackbird | E36: Beatles | G36: 1968 | H36: Folk | J36: oldies;retro;acoustic;alternative;folk | K36: =CONCATENATE(SUBSTITUTE(Spotify!J41,",",";"),";",J36) -> ;oldies;retro;acoustic;alternative;folk | M36: =Spotify!B41 -> Breakfast At Tiffany's | N36: =Spotify!D41 -> Deep Blue Something | O36: =Spotify!E41 -> 34700 | P36: =ROUND(Spotify!U41,0) -> 110 | Q36: =ROUND(Spotify!L41*100,0) -> 83 | R36: =ROUND(Spotify!K41*100,0) -> 62 | S36: =Spotify!N41 -> -5.548 | T36: =ROUND(Spotify!T41*100,0) -> 54 | U36: =ROUND(Spotify!F41/60000,1) -> 4.3 | V36: =ROUND(Spotify!Q41*100,0) -> 11 | W36: =Spotify!G41 -> 73
A37: =RAND() -> 0.32569321 | C37: Cm | D37: Blinding Lights | E37: Weeknd | G37: 2019 | H37: RnB | I37: Soul | J37: groovy;dance;fast;love | K37: =CONCATENATE(SUBSTITUTE(Spotify!J42,",",";"),";",J37) -> ;groovy;dance;fast;love | M37: =Spotify!B42 -> Breathe (2 AM) | N37: =Spotify!D42 -> Anna Nalick | O37: =Spotify!E42 -> 2005 | P37: =ROUND(Spotify!U42,0) -> 170 | Q37: =ROUND(Spotify!L42*100,0) -> 45 | R37: =ROUND(Spotify!K42*100,0) -> 39 | S37: =Spotify!N42 -> -7.715 | T37: =ROUND(Spotify!T42*100,0) -> 29 | U37: =ROUND(Spotify!F42/60000,1) -> 4.7 | V37: =ROUND(Spotify!Q42*100,0) -> 42 | W37: =Spotify!G42 -> 66
A38: =RAND() -> 0.67179284 | C38: D | D38: Blowin' In The Wind | E38: Peter Paul and Mary | F38: Bob Dylan | G38: 1962 | H38: Folk | J38: acoustic;oldies;retro;folk | K38: =CONCATENATE(SUBSTITUTE(Spotify!J43,",",";"),";",J38) -> ;acoustic;oldies;retro;folk | M38: =Spotify!B43 -> Brown Eyed Girl | N38: =Spotify!D43 -> Van Morrison | O38: =Spotify!E43 -> 1967-09 | P38: =ROUND(Spotify!U43,0) -> 151 | Q38: =ROUND(Spotify!L43*100,0) -> 58 | R38: =ROUND(Spotify!K43*100,0) -> 49 | S38: =Spotify!N43 -> -10.964 | T38: =ROUND(Spotify!T43*100,0) -> 91 | U38: =ROUND(Spotify!F43/60000,1) -> 3.1 | V38: =ROUND(Spotify!Q43*100,0) -> 19 | W38: =Spotify!G43 -> 19
A39: =RAND() -> 0.19987132 | C39: E | D39: Brandy | E39: Looking Glass | G39: 1972 | H39: Rock | I39: Soft | J39: groovy;dance;fast;oldies;retro | K39: =CONCATENATE(SUBSTITUTE(Spotify!J44,",",";"),";",J39) -> ;groovy;dance;fast;oldies;retro | M39: =Spotify!B44 -> Budapest | N39: =Spotify!D44 -> George Ezra | O39: =Spotify!E44 -> 41820 | P39: =ROUND(Spotify!U44,0) -> 128 | Q39: =ROUND(Spotify!L44*100,0) -> 46 | R39: =ROUND(Spotify!K44*100,0) -> 72 | S39: =Spotify!N44 -> -8.303 | T39: =ROUND(Spotify!T44*100,0) -> 39 | U39: =ROUND(Spotify!F44/60000,1) -> 3.3 | V39: =ROUND(Spotify!Q44*100,0) -> 8 | W39: =Spotify!G44 -> 83
A40: =RAND() -> 0.53505531 | B40: WIP | C40: A | D40: Brasileirinho | E40: Waldir Azavedo | G40: 1947 | H40: Choro | J40: instrumental | K40: =CONCATENATE(SUBSTITUTE(Spotify!J45,",",";"),";",J40) -> soft pop;acoustic pop;instrumental | M40: =Spotify!B45 -> Butterfly | N40: =Spotify!D45 -> Jason Mraz | O40: =Spotify!E45 -> 39580 | P40: =ROUND(Spotify!U45,0) -> 108 | Q40: =ROUND(Spotify!L45*100,0) -> 66 | R40: =ROUND(Spotify!K45*100,0) -> 72 | S40: =Spotify!N45 -> -7.207 | T40: =ROUND(Spotify!T45*100,0) -> 80 | U40: =ROUND(Spotify!F45/60000,1) -> 5 | V40: =ROUND(Spotify!Q45*100,0) -> 15 | W40: =Spotify!G45 -> 46
A41: =RAND() -> 0.34474758 | B41: WIP | C41: D | D41: Breakfast At Tiffany's | E41: Deep Blue Something | G41: 1995 | H41: Rock | I41: Alternative | J41: love | K41: =CONCATENATE(SUBSTITUTE(Spotify!J46,",",";"),";",J41) -> doo-wop;love | M41: =Spotify!B46 -> Bye Bye Love | N41: =Spotify!D46 -> The Everly Brothers | O41: =Spotify!E46 -> 23590 | P41: =ROUND(Spotify!U46,0) -> 170 | Q41: =ROUND(Spotify!L46*100,0) -> 52 | R41: =ROUND(Spotify!K46*100,0) -> 55 | S41: =Spotify!N46 -> -9.176 | T41: =ROUND(Spotify!T46*100,0) -> 89 | U41: =ROUND(Spotify!F46/60000,1) -> 2.4 | V41: =ROUND(Spotify!Q46*100,0) -> 72 | W41: =Spotify!G46 -> 54
B42: WIP | D42: Breathe (2 AM) | E42: Anna Nalick | G42: 2004 | H42: Folk | I42: Country | K42: =CONCATENATE(SUBSTITUTE(Spotify!J47,",",";"),";",J42) -> doo-wop;adult standards; | M42: =Spotify!B47 -> Calendar Girl | N42: =Spotify!D47 -> Neil Sedaka | O42: =Spotify!E47 -> 21713 | P42: =ROUND(Spotify!U47,0) -> 123 | Q42: =ROUND(Spotify!L47*100,0) -> 65 | R42: =ROUND(Spotify!K47*100,0) -> 70 | S42: =Spotify!N47 -> -7.727 | T42: =ROUND(Spotify!T47*100,0) -> 86 | U42: =ROUND(Spotify!F47/60000,1) -> 2.7 | V42: =ROUND(Spotify!Q47*100,0) -> 40 | W42: =Spotify!G47 -> 57
A43: =RAND() -> 0.046716813 | C43: G | D43: Brown Eyed Girl | E43: Van Morrison | G43: 1967 | H43: Rock | J43: love;dance;fast;oldies;retro | K43: =CONCATENATE(SUBSTITUTE(Spotify!J48,",",";"),";",J43) -> funk rock;alternative rock;rock;love;dance;fast;oldies;retro | M43: =Spotify!B48 -> Californication | N43: =Spotify!D48 -> Red Hot Chili Peppers | O43: =Spotify!E48 -> 36319 | P43: =ROUND(Spotify!U48,0) -> 96 | Q43: =ROUND(Spotify!L48*100,0) -> 77 | R43: =ROUND(Spotify!K48*100,0) -> 59 | S43: =Spotify!N48 -> -2.788 | T43: =ROUND(Spotify!T48*100,0) -> 33 | U43: =ROUND(Spotify!F48/60000,1) -> 5.5 | V43: =ROUND(Spotify!Q48*100,0) -> 0 | W43: =Spotify!G48 -> 88
A44: =RAND() -> 0.14728375 | C44: F | D44: Budapest | E44: George Ezra | G44: 2013 | H44: Rock | I44: Folk | J44: love;dance | K44: =CONCATENATE(SUBSTITUTE(Spotify!J49,",",";"),";",J44) -> rockabilly;rock and roll;love;dance | M44: =Spotify!B49 -> Can't Help Falling in Love | N44: =Spotify!D49 -> Elvis Presley | O44: =Spotify!E49 -> 22574 | P44: =ROUND(Spotify!U49,0) -> 100 | Q44: =ROUND(Spotify!L49*100,0) -> 29 | R44: =ROUND(Spotify!K49*100,0) -> 40 | S44: =Spotify!N49 -> -14.062 | T44: =ROUND(Spotify!T49*100,0) -> 34 | U44: =ROUND(Spotify!F49/60000,1) -> 3.1 | V44: =ROUND(Spotify!Q49*100,0) -> 94 | W44: =Spotify!G49 -> 83
A45: =RAND() -> 0.333134 | B45: WIP | C45: Fm | D45: Butterfly | E45: Jason Mraz | G45: 2008 | H45: Pop | J45: love;dance;fast | K45: =CONCATENATE(SUBSTITUTE(Spotify!J50,",",";"),";",J45) -> yacht rock;adult standards;love;dance;fast | M45: =Spotify!B50 -> Can't Smile Without You | N45: =Spotify!D50 -> Barry Manilow | O45: =Spotify!E50 -> 1978 | P45: =ROUND(Spotify!U50,0) -> 98 | Q45: =ROUND(Spotify!L50*100,0) -> 52 | R45: =ROUND(Spotify!K50*100,0) -> 42 | S45: =Spotify!N50 -> -9.937 | T45: =ROUND(Spotify!T50*100,0) -> 48 | U45: =ROUND(Spotify!F50/60000,1) -> 3.2 | V45: =ROUND(Spotify!Q50*100,0) -> 49 | W45: =Spotify!G50 -> 65
A46: =RAND() -> 0.19880304 | B46: WIP | C46: G | D46: Bye Bye Love | E46: Everly Brothers | G46: 1957 | H46: Country | I46: Rock | J46: oldies;retro;love | K46: =CONCATENATE(SUBSTITUTE(Spotify!J51,",",";"),";",J46) -> ;oldies;retro;love | M46: =Spotify!B51 -> Careless Whisper | N46: =Spotify!D51 -> George Michael | O46: =Spotify!E51 -> 36108 | P46: =ROUND(Spotify!U51,0) -> 153 | Q46: =ROUND(Spotify!L51*100,0) -> 63 | R46: =ROUND(Spotify!K51*100,0) -> 57 | S46: =Spotify!N51 -> -8.815 | T46: =ROUND(Spotify!T51*100,0) -> 80 | U46: =ROUND(Spotify!F51/60000,1) -> 5 | V46: =ROUND(Spotify!Q51*100,0) -> 13 | W46: =Spotify!G51 -> 8
A47: =RAND() -> 0.35600692 | B47: WIP | D47: Calendar Girl | E47: Neil Sedaka | G47: 1959 | H47: Pop | J47: oldies;retro;love;sweet | K47: =CONCATENATE(SUBSTITUTE(Spotify!J52,",",";"),";",J47) -> ;oldies;retro;love;sweet | M47: =Spotify!B52 -> Carry You Home | N47: =Spotify!D52 -> James Blunt | O47: =Spotify!E52 -> 39330 | P47: =ROUND(Spotify!U52,0) -> 83 | Q47: =ROUND(Spotify!L52*100,0) -> 55 | R47: =ROUND(Spotify!K52*100,0) -> 34 | S47: =Spotify!N52 -> -7.194 | T47: =ROUND(Spotify!T52*100,0) -> 21 | U47: =ROUND(Spotify!F52/60000,1) -> 3.9 | V47: =ROUND(Spotify!Q52*100,0) -> 70 | W47: =Spotify!G52 -> 65
A48: =RAND() -> 0.32173703 | C48: Am | D48: Californication | E48: Red Hot Chili Peppers | G48: 1999 | H48: Alternative | J48: groovy | K48: =CONCATENATE(SUBSTITUTE(Spotify!J53,",",";"),";",J48) -> ;groovy | M48: =Spotify!B53 -> Catch & Release | N48: =Spotify!D53 -> Matt Simons | O48: =Spotify!E53 -> 42265 | P48: =ROUND(Spotify!U53,0) -> 87 | Q48: =ROUND(Spotify!L53*100,0) -> 45 | R48: =ROUND(Spotify!K53*100,0) -> 62 | S48: =Spotify!N53 -> -9.383 | T48: =ROUND(Spotify!T53*100,0) -> 61 | U48: =ROUND(Spotify!F53/60000,1) -> 4 | V48: =ROUND(Spotify!Q53*100,0) -> 82 | W48: =Spotify!G53 -> 52
A49: =RAND() -> 0.98028794 | C49: D | D49: Can't Help Falling In Love | E49: Elvis Presley | G49: 1961 | H49: Rock | I49: Soft Rock | J49: love;slow;oldies;retro;waltz | K49: =CONCATENATE(SUBSTITUTE(Spotify!J54,",",";"),";",J49) -> pop;reggae;love;slow;oldies;retro;waltz | M49: =Spotify!B54 -> Chained To The Rhythm | N49: =Spotify!D54 -> Katy Perry;Skip Marley | O49: =Spotify!E54 -> 42895 | P49: =ROUND(Spotify!U54,0) -> 95 | Q49: =ROUND(Spotify!L54*100,0) -> 80 | R49: =ROUND(Spotify!K54*100,0) -> 56 | S49: =Spotify!N54 -> -5.404 | T49: =ROUND(Spotify!T54*100,0) -> 47 | U49: =ROUND(Spotify!F54/60000,1) -> 4 | V49: =ROUND(Spotify!Q54*100,0) -> 8 | W49: =Spotify!G54 -> 73
A50: =RAND() -> 0.14315331 | B50: WIP | D50: Can't Smile Without You | E50: Barry Manilow | G50: 1978 | H50: Pop | I50: RnB | J50: oldies;retro;love;sweet | K50: =CONCATENATE(SUBSTITUTE(Spotify!J55,",",";"),";",J50) -> ;oldies;retro;love;sweet | M50: =Spotify!B55 -> Cheap Thrills | N50: =Spotify!D55 -> Sia | O50: =Spotify!E55 -> 42664 | P50: =ROUND(Spotify!U55,0) -> 90 | Q50: =ROUND(Spotify!L55*100,0) -> 70 | R50: =ROUND(Spotify!K55*100,0) -> 63 | S50: =Spotify!N55 -> -5.608 | T50: =ROUND(Spotify!T55*100,0) -> 73 | U50: =ROUND(Spotify!F55/60000,1) -> 3.5 | V50: =ROUND(Spotify!Q55*100,0) -> 5 | W50: =Spotify!G55 -> 72
A51: =RAND() -> 0.53860955 | C51: Cm | D51: Careless Whisper | E51: George Michael | G51: 1984 | H51: Pop | J51: oldies;retro | K51: =CONCATENATE(SUBSTITUTE(Spotify!J56,",",";"),";",J51) -> ;oldies;retro | M51: =Spotify!B56 -> Chiquitita | N51: =Spotify!D56 -> ABBA | O51: =Spotify!E56 -> 1979 | P51: =ROUND(Spotify!U56,0) -> 84 | Q51: =ROUND(Spotify!L56*100,0) -> 55 | R51: =ROUND(Spotify!K56*100,0) -> 50 | S51: =Spotify!N56 -> -8.108 | T51: =ROUND(Spotify!T56*100,0) -> 37 | U51: =ROUND(Spotify!F56/60000,1) -> 5.4 | V51: =ROUND(Spotify!Q56*100,0) -> 73 | W51: =Spotify!G56 -> 78
A52: =RAND() -> 0.14452932 | B52: WIP | C52: C | D52: Carry You Home | E52: James Blunt | G52: 2008 | H52: Rock | I52: Folk | J52: love;alternative | K52: =CONCATENATE(SUBSTITUTE(Spotify!J57,",",";"),";",J52) -> ;love;alternative | M52: =Spotify!B57 -> Clocks | N52: =Spotify!D57 -> Coldplay | O52: =Spotify!E57 -> 37495 | P52: =ROUND(Spotify!U57,0) -> 131 | Q52: =ROUND(Spotify!L57*100,0) -> 75 | R52: =ROUND(Spotify!K57*100,0) -> 58 | S52: =Spotify!N57 -> -7.215 | T52: =ROUND(Spotify!T57*100,0) -> 26 | U52: =ROUND(Spotify!F57/60000,1) -> 5.1 | V52: =ROUND(Spotify!Q57*100,0) -> 60 | W52: =Spotify!G57 -> 87
A53: =RAND() -> 0.4329374 | B53: WIP | C53: A | D53: Catch and Release | E53: Matt Simons | G53: 2007 | H53: Pop | J53: slow;love | K53: =CONCATENATE(SUBSTITUTE(Spotify!J58,",",";"),";",J53) -> ;slow;love | M53: =Spotify!B58 -> Closing Time | N53: =Spotify!D58 -> Semisonic | O53: =Spotify!E58 -> 37622 | P53: =ROUND(Spotify!U58,0) -> 92 | Q53: =ROUND(Spotify!L58*100,0) -> 85 | R53: =ROUND(Spotify!K58*100,0) -> 48 | S53: =Spotify!N58 -> -5.454 | T53: =ROUND(Spotify!T58*100,0) -> 27 | U53: =ROUND(Spotify!F58/60000,1) -> 4.6 | V53: =ROUND(Spotify!Q58*100,0) -> 2 | W53: =Spotify!G58 -> 70
A54: =RAND() -> 0.37856893 | B54: WIP | C54: Am | D54: Chained To The Rhythm | E54: Katy Perry | G54: 2017 | H54: Disco | J54: groovy;dance;fast | K54: =CONCATENATE(SUBSTITUTE(Spotify!J59,",",";"),";",J54) -> ;groovy;dance;fast | M54: =Spotify!B59 -> Cloud Number Nine | N54: =Spotify!D59 -> Bryan Adams | O54: =Spotify!E59 -> 35796 | P54: =ROUND(Spotify!U59,0) -> 110 | Q54: =ROUND(Spotify!L59*100,0) -> 72 | R54: =ROUND(Spotify!K59*100,0) -> 59 | S54: =Spotify!N59 -> -7.127 | T54: =ROUND(Spotify!T59*100,0) -> 62 | U54: =ROUND(Spotify!F59/60000,1) -> 3.8 | V54: =ROUND(Spotify!Q59*100,0) -> 6 | W54: =Spotify!G59 -> 53
A55: =RAND() -> 0.85207168 | C55: F#m | D55: Cheap Thrills | E55: Sia | G55: 2016 | H55: Pop | J55: groovy;dance;fast | K55: =CONCATENATE(SUBSTITUTE(Spotify!J60,",",";"),";",J55) -> yacht rock;adult standards;groovy;dance;fast | M55: =Spotify!B60 -> Copacabana (At the Copa) | N55: =Spotify!D60 -> Barry Manilow | O55: =Spotify!E60 -> 39335 | P55: =ROUND(Spotify!U60,0) -> 108 | Q55: =ROUND(Spotify!L60*100,0) -> 67 | R55: =ROUND(Spotify!K60*100,0) -> 76 | S55: =Spotify!N60 -> -7.914 | T55: =ROUND(Spotify!T60*100,0) -> 80 | U55: =ROUND(Spotify!F60/60000,1) -> 4 | V55: =ROUND(Spotify!Q60*100,0) -> 54 | W55: =Spotify!G60 -> 50
A56: =RAND() -> 0.14043572 | B56: WIP | D56: Chiquitita | E56: ABBA | G56: 1979 | H56: Pop | J56: oldies;retro;love | K56: =CONCATENATE(SUBSTITUTE(Spotify!J61,",",";"),";",J56) -> ;oldies;retro;love | M56: =Spotify!B61 -> Count on Me | N56: =Spotify!D61 -> Bruno Mars | O56: =Spotify!E61 -> 40309 | P56: =ROUND(Spotify!U61,0) -> 89 | Q56: =ROUND(Spotify!L61*100,0) -> 39 | R56: =ROUND(Spotify!K61*100,0) -> 59 | S56: =Spotify!N61 -> -5.972 | T56: =ROUND(Spotify!T61*100,0) -> 50 | U56: =ROUND(Spotify!F61/60000,1) -> 3.3 | V56: =ROUND(Spotify!Q61*100,0) -> 85 | W56: =Spotify!G61 -> 81
A57: =RAND() -> 0.32355652 | C57: G | D57: Clocks | E57: Coldplay | G57: 2002 | H57: Rock | I57: Alternative | J57: alternative | K57: =CONCATENATE(SUBSTITUTE(Spotify!J62,",",";"),";",J57) -> soft pop;alternative | M57: =Spotify!B62 -> Counting Stars | N57: =Spotify!D62 -> OneRepublic | O57: =Spotify!E62 -> 41640 | P57: =ROUND(Spotify!U62,0) -> 122 | Q57: =ROUND(Spotify!L62*100,0) -> 71 | R57: =ROUND(Spotify!K62*100,0) -> 66 | S57: =Spotify!N62 -> -4.972 | T57: =ROUND(Spotify!T62*100,0) -> 47 | U57: =ROUND(Spotify!F62/60000,1) -> 4.3 | V57: =ROUND(Spotify!Q62*100,0) -> 7 | W57: =Spotify!G62 -> 74
A58: =RAND() -> 0.060789827 | B58: WIP | C58: F | D58: Closing Time | E58: Semisonic | G58: 1998 | H58: Rock | J58: alternative | K58: =CONCATENATE(SUBSTITUTE(Spotify!J63,",",";"),";",J58) -> folk;alternative | M58: =Spotify!B63 -> Take Me Home, Country Roads - Original Version | N58: =Spotify!D63 -> John Denver | O58: =Spotify!E63 -> 1971 | P58: =ROUND(Spotify!U63,0) -> 82 | Q58: =ROUND(Spotify!L63*100,0) -> 40 | R58: =ROUND(Spotify!K63*100,0) -> 46 | S58: =Spotify!N63 -> -9.376 | T58: =ROUND(Spotify!T63*100,0) -> 63 | U58: =ROUND(Spotify!F63/60000,1) -> 3.2 | V58: =ROUND(Spotify!Q63*100,0) -> 76 | W58: =Spotify!G63 -> 79
A59: =RAND() -> 0.48341531 | D59: Cloud Number Nine | E59: Bryan Adams | G59: 1999 | H59: Pop | J59: love;dance;sweet;groovy | K59: =CONCATENATE(SUBSTITUTE(Spotify!J64,",",";"),";",J59) -> ;love;dance;sweet;groovy | M59: =Spotify!B64 -> Crazy | N59: =Spotify!D64 -> Gnarls Barkley | O59: =Spotify!E64 -> 38839 | P59: =ROUND(Spotify!U64,0) -> 112 | Q59: =ROUND(Spotify!L64*100,0) -> 74 | R59: =ROUND(Spotify!K64*100,0) -> 84 | S59: =Spotify!N64 -> -1.609 | T59: =ROUND(Spotify!T64*100,0) -> 61 | U59: =ROUND(Spotify!F64/60000,1) -> 3 | V59: =ROUND(Spotify!Q64*100,0) -> 2 | W59: =Spotify!G64 -> 4
A60: =RAND() -> 0.92518896 | B60: WIP | C60: Em | D60: Copacabana | E60: Barry Manilow | G60: 1978 | H60: Disco | J60: acoustic;love;dance;groovy;oldies;retro | K60: =CONCATENATE(SUBSTITUTE(Spotify!J65,",",";"),";",J60) -> classic rock;rock;glam rock;acoustic;love;dance;groovy;oldies;retro | M60: =Spotify!B65 -> Crazy Little Thing Called Love | N60: =Spotify!D65 -> Queen | O60: =Spotify!E65 -> 29399 | P60: =ROUND(Spotify!U65,0) -> 77 | Q60: =ROUND(Spotify!L65*100,0) -> 57 | R60: =ROUND(Spotify!K65*100,0) -> 63 | S60: =Spotify!N65 -> -13.453 | T60: =ROUND(Spotify!T65*100,0) -> 75 | U60: =ROUND(Spotify!F65/60000,1) -> 2.7 | V60: =ROUND(Spotify!Q65*100,0) -> 50 | W60: =Spotify!G65 -> 0
A61: =RAND() -> 0.57047293 | C61: D | D61: Count On Me | E61: Bruno Mars | G61: 2010 | H61: Pop | J61: groovy;acoustic;love;fast;sweet | K61: =CONCATENATE(SUBSTITUTE(Spotify!J66,",",";"),";",J61) -> ;groovy;acoustic;love;fast;sweet | M61: =Spotify!B66 -> Dance with Me Tonight | N61: =Spotify!D66 -> Olly Murs | O61: =Spotify!E66 -> 40875 | P61: =ROUND(Spotify!U66,0) -> 164 | Q61: =ROUND(Spotify!L66*100,0) -> 75 | R61: =ROUND(Spotify!K66*100,0) -> 67 | S61: =Spotify!N66 -> -5.922 | T61: =ROUND(Spotify!T66*100,0) -> 96 | U61: =ROUND(Spotify!F66/60000,1) -> 3.4 | V61: =ROUND(Spotify!Q66*100,0) -> 31 | W61: =Spotify!G66 -> 67
D62: Counting Stars | E62: OneRepublic | G62: 2013 | H62: Pop | K62: =CONCATENATE(SUBSTITUTE(Spotify!J67,",",";"),";",J62) -> ; | M62: =Spotify!B67 -> Dancing in the Moonlight | N62: =Spotify!D67 -> Toploader | O62: =Spotify!E67 -> 2000 | P62: =ROUND(Spotify!U67,0) -> 119 | Q62: =ROUND(Spotify!L67*100,0) -> 86 | R62: =ROUND(Spotify!K67*100,0) -> 63 | S62: =Spotify!N67 -> -3.463 | T62: =ROUND(Spotify!T67*100,0) -> 87 | U62: =ROUND(Spotify!F67/60000,1) -> 3.9 | V62: =ROUND(Spotify!Q67*100,0) -> 6 | W62: =Spotify!G67 -> 80
A63: =RAND() -> 0.23480399 | C63: G | D63: Country Roads | E63: John Denver | G63: 1971 | H63: Country | J63: oldies;retro;groovy | K63: =CONCATENATE(SUBSTITUTE(Spotify!J68,",",";"),";",J63) -> ;oldies;retro;groovy | M63: =Spotify!B68 -> Dancing Queen | N63: =Spotify!D68 -> ABBA | O63: =Spotify!E68 -> 1976 | P63: =ROUND(Spotify!U68,0) -> 101 | Q63: =ROUND(Spotify!L68*100,0) -> 87 | R63: =ROUND(Spotify!K68*100,0) -> 54 | S63: =Spotify!N68 -> -6.514 | T63: =ROUND(Spotify!T68*100,0) -> 75 | U63: =ROUND(Spotify!F68/60000,1) -> 3.8 | V63: =ROUND(Spotify!Q68*100,0) -> 36 | W63: =Spotify!G68 -> 87
A64: =RAND() -> 0.72997315 | C64: Em | D64: Crazy | E64: Gnarles Barkley | G64: 2006 | H64: Soul | J64: alternative;groovy | K64: =CONCATENATE(SUBSTITUTE(Spotify!J69,",",";"),";",J64) -> singer-songwriter;alternative;groovy | M64: =Spotify!B69 -> Daughters | N64: =Spotify!D69 -> John Mayer | O64: =Spotify!E69 -> 37873 | P64: =ROUND(Spotify!U69,0) -> 125 | Q64: =ROUND(Spotify!L69*100,0) -> 41 | R64: =ROUND(Spotify!K69*100,0) -> 67 | S64: =Spotify!N69 -> -7.816 | T64: =ROUND(Spotify!T69*100,0) -> 50 | U64: =ROUND(Spotify!F69/60000,1) -> 4 | V64: =ROUND(Spotify!Q69*100,0) -> 84 | W64: =Spotify!G69 -> 67
A65: =RAND() -> 0.52465551 | C65: D | D65: Crazy Little Thing Called Love | E65: Queen | G65: 1979 | H65: Rock | J65: groovy;dance;fast;oldies;retro | K65: =CONCATENATE(SUBSTITUTE(Spotify!J70,",",";"),";",J65) -> ;groovy;dance;fast;oldies;retro | M65: =Spotify!B70 -> Dear Future Husband | N65: =Spotify!D70 -> Meghan Trainor | O65: =Spotify!E70 -> 42016 | P65: =ROUND(Spotify!U70,0) -> 79 | Q65: =ROUND(Spotify!L70*100,0) -> 78 | R65: =ROUND(Spotify!K70*100,0) -> 66 | S65: =Spotify!N70 -> -4.789 | T65: =ROUND(Spotify!T70*100,0) -> 83 | U65: =ROUND(Spotify!F70/60000,1) -> 3.1 | V65: =ROUND(Spotify!Q70*100,0) -> 38 | W65: =Spotify!G70 -> 70
A66: =RAND() -> 0.39090475 | C66: C | D66: Dance With Me Tonight | E66: Olly Murs | G66: 2011 | H66: Pop | J66: dance;fast;love;groovy;sweet | K66: =CONCATENATE(SUBSTITUTE(Spotify!#REF!,",",";"),";",J66) -> #REF! | M66: =Spotify!#REF! -> #REF! | N66: =Spotify!#REF! -> #REF! | O66: =Spotify!#REF! -> #REF! | P66: =ROUND(Spotify!#REF!,0) -> #REF! | Q66: =ROUND(Spotify!#REF!*100,0) -> #REF! | R66: =ROUND(Spotify!#REF!*100,0) -> #REF! | S66: =Spotify!#REF! -> #REF! | T66: =ROUND(Spotify!#REF!*100,0) -> #REF! | U66: =ROUND(Spotify!#REF!/60000,1) -> #REF! | V66: =ROUND(Spotify!#REF!*100,0) -> #REF! | W66: =Spotify!#REF! -> #REF!
A67: =RAND() -> 0.75297598 | C67: C | D67: Dancing In The Moonlight | E67: Toploader | G67: 1999 | H67: Pop | J67: groovy;dance | K67: =CONCATENATE(SUBSTITUTE(Spotify!J71,",",";"),";",J67) -> indie folk;folk;newgrass;americana;bluegrass;alt country;folk rock;groovy;dance | M67: =Spotify!B71 -> Die Die Die | N67: =Spotify!D71 -> The Avett Brothers | O67: =Spotify!E71 -> 39217 | P67: =ROUND(Spotify!U71,0) -> 119 | Q67: =ROUND(Spotify!L71*100,0) -> 70 | R67: =ROUND(Spotify!K71*100,0) -> 53 | S67: =Spotify!N71 -> -5.309 | T67: =ROUND(Spotify!T71*100,0) -> 77 | U67: =ROUND(Spotify!F71/60000,1) -> 2.8 | V67: =ROUND(Spotify!Q71*100,0) -> 13 | W67: =Spotify!G71 -> 36
A68: =RAND() -> 0.020861481 | D68: Dancing Queen | E68: ABBA | G68: 1976 | H68: Pop | J68: groovy;dance;jive;oldies;retro;fast | K68: =CONCATENATE(SUBSTITUTE(Spotify!J72,",",";"),";",J68) -> ;groovy;dance;jive;oldies;retro;fast | M68: =Spotify!B72 -> Does Your Mother Know | N68: =Spotify!D72 -> ABBA | O68: =Spotify!E72 -> 1979 | P68: =ROUND(Spotify!U72,0) -> 136 | Q68: =ROUND(Spotify!L72*100,0) -> 87 | R68: =ROUND(Spotify!K72*100,0) -> 73 | S68: =Spotify!N72 -> -5.68 | T68: =ROUND(Spotify!T72*100,0) -> 98 | U68: =ROUND(Spotify!F72/60000,1) -> 3.2 | V68: =ROUND(Spotify!Q72*100,0) -> 15 | W68: =Spotify!G72 -> 69
A69: =RAND() -> 0.0013149262 | B69: WIP | C69: D | D69: Daughters | E69: John Mayer | G69: 2004 | H69: Rock | I69: Acoustic / Blues | J69: groovy;slow;alternative | K69: =CONCATENATE(SUBSTITUTE(Spotify!J73,",",";"),";",J69) -> classic country;groovy;slow;alternative | M69: =Spotify!B73 -> Don't It Make My Brown Eyes Blue | N69: =Spotify!D73 -> Crystal Gayle | O69: =Spotify!E73 -> 28126 | P69: =ROUND(Spotify!U73,0) -> 85 | Q69: =ROUND(Spotify!L73*100,0) -> 32 | R69: =ROUND(Spotify!K73*100,0) -> 74 | S69: =Spotify!N73 -> -13.474 | T69: =ROUND(Spotify!T73*100,0) -> 34 | U69: =ROUND(Spotify!F73/60000,1) -> 2.6 | V69: =ROUND(Spotify!Q73*100,0) -> 80 | W69: =Spotify!G73 -> 61
A70: =RAND() -> 0.23398906 | B70: WIP | D70: Dear Future Husband | E70: Meghan Trainor | G70: 2014 | H70: Pop | J70: dance;groovy;love;sweet | K70: =CONCATENATE(SUBSTITUTE(Spotify!J74,",",";"),";",J70) -> jazz pop;dance;groovy;love;sweet | M70: =Spotify!B74 -> Don't Know Why | N70: =Spotify!D74 -> Norah Jones | O70: =Spotify!E74 -> 37313 | P70: =ROUND(Spotify!U74,0) -> 89 | Q70: =ROUND(Spotify!L74*100,0) -> 22 | R70: =ROUND(Spotify!K74*100,0) -> 75 | S70: =Spotify!N74 -> -11.216 | T70: =ROUND(Spotify!T74*100,0) -> 64 | U70: =ROUND(Spotify!F74/60000,1) -> 3.1 | V70: =ROUND(Spotify!Q74*100,0) -> 85 | W70: =Spotify!G74 -> 79
A71: =RAND() -> 0.17438869 | B71: WIP | C71: G | D71: Die Die Die | E71: Avett Brothers | G71: 2007 | H71: Folk | I71: Rock | J71: alternative;groovy;acoustic | K71: =CONCATENATE(SUBSTITUTE(Spotify!J75,",",";"),";",J71) -> britpop;madchester;alternative;groovy;acoustic | M71: =Spotify!B75 -> Don't Look Back In Anger | N71: =Spotify!D75 -> Oasis | O71: =Spotify!E75 -> 34974 | P71: =ROUND(Spotify!U75,0) -> 164 | Q71: =ROUND(Spotify!L75*100,0) -> 92 | R71: =ROUND(Spotify!K75*100,0) -> 35 | S71: =Spotify!N75 -> -3.645 | T71: =ROUND(Spotify!T75*100,0) -> 21 | U71: =ROUND(Spotify!F75/60000,1) -> 4.8 | V71: =ROUND(Spotify!Q75*100,0) -> 3 | W71: =Spotify!G75 -> 74
A72: =RAND() -> 0.7187645 | C72: G | D72: Does Your Mother Know | E72: ABBA | G72: 1979 | H72: Pop | J72: dance;fast;love;groovy;oldies;retro | K72: =CONCATENATE(SUBSTITUTE(Spotify!J76,",",";"),";",J72) -> classic rock;rock;glam rock;dance;fast;love;groovy;oldies;retro | M72: =Spotify!B76 -> Don't Stop Me Now | N72: =Spotify!D76 -> Queen | O72: =Spotify!E76 -> 28804 | P72: =ROUND(Spotify!U76,0) -> 156 | Q72: =ROUND(Spotify!L76*100,0) -> 76 | R72: =ROUND(Spotify!K76*100,0) -> 56 | S72: =Spotify!N76 -> -10.061 | T72: =ROUND(Spotify!T76*100,0) -> 64 | U72: =ROUND(Spotify!F76/60000,1) -> 3.5 | V72: =ROUND(Spotify!Q76*100,0) -> 6 | W72: =Spotify!G76 -> 2
A73: =RAND() -> 0.34729558 | B73: WIP | C73: F# | D73: Don't It Make My Brown Eyes Blue | E73: Crystal Gayle | G73: 1977 | H73: Jazz | I73: Country | J73: groovy;jazz;slow;love;oldies;retro | K73: =CONCATENATE(SUBSTITUTE(Spotify!#REF!,",",";"),";",J73) -> #REF! | M73: =Spotify!#REF! -> #REF! | N73: =Spotify!#REF! -> #REF! | O73: =Spotify!#REF! -> #REF! | P73: =ROUND(Spotify!#REF!,0) -> #REF! | Q73: =ROUND(Spotify!#REF!*100,0) -> #REF! | R73: =ROUND(Spotify!#REF!*100,0) -> #REF! | S73: =Spotify!#REF! -> #REF! | T73: =ROUND(Spotify!#REF!*100,0) -> #REF! | U73: =ROUND(Spotify!#REF!/60000,1) -> #REF! | V73: =ROUND(Spotify!#REF!*100,0) -> #REF! | W73: =Spotify!#REF! -> #REF!
A74: =RAND() -> 0.5413257 | C74: Bb | D74: Don't Know Why | E74: Norah Jones | F74: Jesse Harris | G74: 2002 | H74: Pop | I74: Jazz | J74: groovy;slow;love | K74: =CONCATENATE(SUBSTITUTE(Spotify!J77,",",";"),";",J74) -> bluegrass;newgrass;folk;americana;groovy;slow;love | M74: =Spotify!B77 -> Doubting Thomas | N74: =Spotify!D77 -> Nickel Creek | O74: =Spotify!E77 -> 38353 | P74: =ROUND(Spotify!U77,0) -> 146 | Q74: =ROUND(Spotify!L77*100,0) -> 14 | R74: =ROUND(Spotify!K77*100,0) -> 39 | S74: =Spotify!N77 -> -14.873 | T74: =ROUND(Spotify!T77*100,0) -> 27 | U74: =ROUND(Spotify!F77/60000,1) -> 3.3 | V74: =ROUND(Spotify!Q77*100,0) -> 91 | W74: =Spotify!G77 -> 37
A75: =RAND() -> 0.74992831 | D75: Don't Look Back In Anger | E75: Oasis | G75: 1995 | H75: Pop | I75: Britpop | J75: groovy;slow;alternative;acoustic | K75: =CONCATENATE(SUBSTITUTE(Spotify!J79,",",";"),";",J75) -> yacht rock;classic rock;soft rock;groovy;slow;alternative;acoustic | M75: =Spotify!B79 -> Dreams - 2004 Remaster | N75: =Spotify!D79 -> Fleetwood Mac | O75: =Spotify!E79 -> 28160 | P75: =ROUND(Spotify!U79,0) -> 120 | Q75: =ROUND(Spotify!L79*100,0) -> 49 | R75: =ROUND(Spotify!K79*100,0) -> 83 | S75: =Spotify!N79 -> -9.744 | T75: =ROUND(Spotify!T79*100,0) -> 79 | U75: =ROUND(Spotify!F79/60000,1) -> 4.3 | V75: =ROUND(Spotify!Q79*100,0) -> 6 | W75: =Spotify!G79 -> 92
A76: =RAND() -> 0.56241876 | C76: D | D76: Don't Stop Me Now | E76: Queen | G76: 1979 | H76: Rock | I76: Glam | J76: dance;fast;love;groovy;oldies;retro | K76: =CONCATENATE(SUBSTITUTE(Spotify!J80,",",";"),";",J76) -> nu metal;funk rock;alternative metal;alternative rock;dance;fast;love;groovy;oldies;retro | M76: =Spotify!B80 -> Drive | N76: =Spotify!D80 -> Incubus | O76: =Spotify!E80 -> 36459 | P76: =ROUND(Spotify!U80,0) -> 91 | Q76: =ROUND(Spotify!L80*100,0) -> 79 | R76: =ROUND(Spotify!K80*100,0) -> 65 | S76: =Spotify!N80 -> -7.34 | T76: =ROUND(Spotify!T80*100,0) -> 67 | U76: =ROUND(Spotify!F80/60000,1) -> 3.9 | V76: =ROUND(Spotify!Q80*100,0) -> 6 | W76: =Spotify!G80 -> 82
A77: =RAND() -> 0.84344761 | B77: WIP | C77: F | D77: Doubting Thomas | E77: Nickel Creek | G77: 2005 | H77: Pop | I77: Folk | K77: =CONCATENATE(SUBSTITUTE(Spotify!J82,",",";"),";",J77) -> ; | M77: =Spotify!B82 -> Earth Angel | N77: =Spotify!D82 -> Death Cab for Cutie | O77: =Spotify!E82 -> 38353 | P77: =ROUND(Spotify!U82,0) -> 187 | Q77: =ROUND(Spotify!L82*100,0) -> 65 | R77: =ROUND(Spotify!K82*100,0) -> 23 | S77: =Spotify!N82 -> -5.456 | T77: =ROUND(Spotify!T82*100,0) -> 31 | U77: =ROUND(Spotify!F82/60000,1) -> 3.3 | V77: =ROUND(Spotify!Q82*100,0) -> 24 | W77: =Spotify!G82 -> 0
A78: =RAND() -> 0.057226623 | B78: WIP | D78: Dream A Little Dream Of Me | E78: Laura Fygi | G78: 2002 | H78: Jazz | J78: love;slow;acoustic;jazz;sweet | K78: =CONCATENATE(SUBSTITUTE(Spotify!J83,",",";"),";",J78) -> classic rock;psychedelic rock;love;slow;acoustic;jazz;sweet | M78: =Spotify!B83 -> Eight Days A Week - Remastered 2015 | N78: =Spotify!D83 -> The Beatles | O78: =Spotify!E83 -> 36843 | P78: =ROUND(Spotify!U83,0) -> 139 | Q78: =ROUND(Spotify!L83*100,0) -> 68 | R78: =ROUND(Spotify!K83*100,0) -> 64 | S78: =Spotify!N83 -> -5.605 | T78: =ROUND(Spotify!T83*100,0) -> 84 | U78: =ROUND(Spotify!F83/60000,1) -> 2.7 | V78: =ROUND(Spotify!Q83*100,0) -> 27 | W78: =Spotify!G83 -> 52
D79: Dreams | E79: Fleetwood Mac | G79: 1977 | H79: Rock | I79: Soft | K79: =CONCATENATE(SUBSTITUTE(Spotify!J85,",",";"),";",J79) -> ; | M79: =Spotify!B85 -> Every Breath You Take | N79: =Spotify!D85 -> The Police | O79: =Spotify!E85 -> 44765 | P79: =ROUND(Spotify!U85,0) -> 117 | Q79: =ROUND(Spotify!L85*100,0) -> 46 | R79: =ROUND(Spotify!K85*100,0) -> 82 | S79: =Spotify!N85 -> -9.722 | T79: =ROUND(Spotify!T85*100,0) -> 71 | U79: =ROUND(Spotify!F85/60000,1) -> 4.2 | V79: =ROUND(Spotify!Q85*100,0) -> 54 | W79: =Spotify!G85 -> 0
A80: =RAND() -> 0.81220531 | B80: WIP | C80: Em | D80: Drive | E80: Incubus | G80: 2000 | H80: Rock | I80: Alternative | J80: alternative;groovy;dance | K80: =CONCATENATE(SUBSTITUTE(Spotify!J86,",",";"),";",J80) -> ;alternative;groovy;dance | M80: =Spotify!B86 -> Every Little Thing She Does Is Magic - Live | N80: =Spotify!D86 -> Eric Hutchinson | O80: =Spotify!E86 -> 41919 | P80: =ROUND(Spotify!U86,0) -> 78 | Q80: =ROUND(Spotify!L86*100,0) -> 56 | R80: =ROUND(Spotify!K86*100,0) -> 71 | S80: =Spotify!N86 -> -4.974 | T80: =ROUND(Spotify!T86*100,0) -> 83 | U80: =ROUND(Spotify!F86/60000,1) -> 2.9 | V80: =ROUND(Spotify!Q86*100,0) -> 43 | W80: =Spotify!G86 -> 37
A81: =RAND() -> 0.38687338 | B81: WIP | C81: C | D81: Dust in the Wind | E81: Kansas | G81: 1978 | H81: Rock | I81: Progressive / Soft | J81: alternative;acoustic;oldies;retro;love | K81: =CONCATENATE(SUBSTITUTE(Spotify!J87,",",";"),";",J81) -> christmas;alternative;acoustic;oldies;retro;love | M81: =Spotify!B87 -> Everything | N81: =Spotify!D87 -> Michael Bublé | O81: =Spotify!E87 -> 39199 | P81: =ROUND(Spotify!U87,0) -> 123 | Q81: =ROUND(Spotify!L87*100,0) -> 69 | R81: =ROUND(Spotify!K87*100,0) -> 69 | S81: =Spotify!N87 -> -4.981 | T81: =ROUND(Spotify!T87*100,0) -> 49 | U81: =ROUND(Spotify!F87/60000,1) -> 3.5 | V81: =ROUND(Spotify!Q87*100,0) -> 39 | W81: =Spotify!G87 -> 72
A82: =RAND() -> 0.53864281 | B82: WIP | D82: Earth Angel | E82: Penguins | F82: Death Cab For Cutie | G82: 1954 | H82: RnB | I82: Soul | J82: oldies;retro;love;slow;waltz | K82: =CONCATENATE(SUBSTITUTE(Spotify!J88,",",";"),";",J82) -> soft rock;yacht rock;oldies;retro;love;slow;waltz | M82: =Spotify!B88 -> Everything I Own | N82: =Spotify!D88 -> Bread | O82: =Spotify!E88 -> 1972 | P82: =ROUND(Spotify!U88,0) -> 79 | Q82: =ROUND(Spotify!L88*100,0) -> 34 | R82: =ROUND(Spotify!K88*100,0) -> 37 | S82: =Spotify!N88 -> -13.406 | T82: =ROUND(Spotify!T88*100,0) -> 45 | U82: =ROUND(Spotify!F88/60000,1) -> 3.1 | V82: =ROUND(Spotify!Q88*100,0) -> 74 | W82: =Spotify!G88 -> 76
A83: =RAND() -> 0.3948149 | C83: G | D83: Eight Days A Week | E83: Beatles | G83: 1964 | H83: Rock | J83: oldies;retro;love;dance;fast | K83: =CONCATENATE(SUBSTITUTE(Spotify!J89,",",";"),";",J83) -> yacht rock;classic rock;soft rock;oldies;retro;love;dance;fast | M83: =Spotify!B89 -> Everywhere | N83: =Spotify!D89 -> Fleetwood Mac | O83: =Spotify!E89 -> 32468 | P83: =ROUND(Spotify!U89,0) -> 115 | Q83: =ROUND(Spotify!L89*100,0) -> 54 | R83: =ROUND(Spotify!K89*100,0) -> 69 | S83: =Spotify!N89 -> -10.516 | T83: =ROUND(Spotify!T89*100,0) -> 76 | U83: =ROUND(Spotify!F89/60000,1) -> 3.7 | V83: =ROUND(Spotify!Q89*100,0) -> 22 | W83: =Spotify!G89 -> 71
A84: =RAND() -> 0.24896259 | C84: F | D84: Escape (Pina Colada) | E84: Rupert Holmes | G84: 1979 | H84: Rock | J84: groovy;love;dance;oldies;retro | K84: =CONCATENATE(SUBSTITUTE(Spotify!J91,",",";"),";",J84) -> ;groovy;love;dance;oldies;retro | M84: =Spotify!B91 -> Faith | N84: =Spotify!D91 -> George Michael | O84: =Spotify!E91 -> 36108 | P84: =ROUND(Spotify!U91,0) -> 96 | Q84: =ROUND(Spotify!L91*100,0) -> 50 | R84: =ROUND(Spotify!K91*100,0) -> 92 | S84: =Spotify!N91 -> -10.435 | T84: =ROUND(Spotify!T91*100,0) -> 55 | U84: =ROUND(Spotify!F91/60000,1) -> 3.2 | V84: =ROUND(Spotify!Q91*100,0) -> 1 | W84: =Spotify!G91 -> 1
D85: Every Breath You Take | E85: The Police | G85: 1983 | H85: Rock | K85: =CONCATENATE(SUBSTITUTE(Spotify!J92,",",";"),";",J85) -> folk; | M85: =Spotify!B92 -> Fare Thee Well (Dink's Song) | N85: =Spotify!D92 -> Oscar Isaac;Marcus Mumford | O85: =Spotify!E92 -> 41684 | P85: =ROUND(Spotify!U92,0) -> 82 | Q85: =ROUND(Spotify!L92*100,0) -> 43 | R85: =ROUND(Spotify!K92*100,0) -> 50 | S85: =Spotify!N92 -> -8.079 | T85: =ROUND(Spotify!T92*100,0) -> 23 | U85: =ROUND(Spotify!F92/60000,1) -> 3 | V85: =ROUND(Spotify!Q92*100,0) -> 90 | W85: =Spotify!G92 -> 51
A86: =RAND() -> 0.06121854 | C86: F | D86: Every Little Thing She Does Is Magic | E86: Eric Hutchinson | F86: The Police | G86: 1981 | H86: Pop | J86: alternative;dance;fast;love | K86: =CONCATENATE(SUBSTITUTE(Spotify!J93,",",";"),";",J86) -> ;alternative;dance;fast;love | M86: =Spotify!B93 -> Feels Like Home | N86: =Spotify!D93 -> Edwina Hayes | O86: =Spotify!E93 -> 39908 | P86: =ROUND(Spotify!U93,0) -> 108 | Q86: =ROUND(Spotify!L93*100,0) -> 26 | R86: =ROUND(Spotify!K93*100,0) -> 46 | S86: =Spotify!N93 -> -9.152 | T86: =ROUND(Spotify!T93*100,0) -> 50 | U86: =ROUND(Spotify!F93/60000,1) -> 4.2 | V86: =ROUND(Spotify!Q93*100,0) -> 87 | W86: =Spotify!G93 -> 44
A87: =RAND() -> 0.73786438 | B87: WIP | C87: D | D87: Everything | E87: Michael Buble | G87: 2006 | H87: Pop | J87: groovy;dance | K87: =CONCATENATE(SUBSTITUTE(Spotify!J94,",",";"),";",J87) -> singer-songwriter;groovy;dance | M87: =Spotify!B94 -> 50 Ways to Leave Your Lover | N87: =Spotify!D94 -> Paul Simon | O87: =Spotify!E94 -> 27692 | P87: =ROUND(Spotify!U94,0) -> 102 | Q87: =ROUND(Spotify!L94*100,0) -> 37 | R87: =ROUND(Spotify!K94*100,0) -> 82 | S87: =Spotify!N94 -> -12.814 | T87: =ROUND(Spotify!T94*100,0) -> 29 | U87: =ROUND(Spotify!F94/60000,1) -> 3.6 | V87: =ROUND(Spotify!Q94*100,0) -> 17 | W87: =Spotify!G94 -> 74
A88: =RAND() -> 0.3739696 | B88: WIP | C88: F | D88: Everything I Own | E88: Bread | G88: 1972 | H88: Rock | I88: Soft Rock | J88: love;slow;oldies;retro | K88: =CONCATENATE(SUBSTITUTE(Spotify!J95,",",";"),";",J88) -> indie folk;love;slow;oldies;retro | M88: =Spotify!B95 -> First Day of My Life | N88: =Spotify!D95 -> Bright Eyes | O88: =Spotify!E95 -> 38377 | P88: =ROUND(Spotify!U95,0) -> 95 | Q88: =ROUND(Spotify!L95*100,0) -> 25 | R88: =ROUND(Spotify!K95*100,0) -> 60 | S88: =Spotify!N95 -> -14.369 | T88: =ROUND(Spotify!T95*100,0) -> 37 | U88: =ROUND(Spotify!F95/60000,1) -> 3.1 | V88: =ROUND(Spotify!Q95*100,0) -> 90 | W88: =Spotify!G95 -> 66
D89: Everywhere | E89: Fleetwood Mac | G89: 1987 | H89: Rock | K89: =CONCATENATE(SUBSTITUTE(Spotify!J96,",",";"),";",J89) -> folk;folk rock; | M89: =Spotify!B96 -> 500 Miles | N89: =Spotify!D96 -> Peter, Paul and Mary | O89: =Spotify!E96 -> 22767 | P89: =ROUND(Spotify!U96,0) -> 97 | Q89: =ROUND(Spotify!L96*100,0) -> 7 | R89: =ROUND(Spotify!K96*100,0) -> 44 | S89: =Spotify!N96 -> -19.735 | T89: =ROUND(Spotify!T96*100,0) -> 26 | U89: =ROUND(Spotify!F96/60000,1) -> 2.7 | V89: =ROUND(Spotify!Q96*100,0) -> 86 | W89: =Spotify!G96 -> 81
A90: =RAND() -> 0.92914357 | C90: Am | D90: Eye Of The Tiger | E90: Survivor | G90: 1982 | H90: Rock | J90: groovy;dance;fast;oldies;retro | K90: =CONCATENATE(SUBSTITUTE(Spotify!J97,",",";"),";",J90) -> ;groovy;dance;fast;oldies;retro | M90: =Spotify!B97 -> Fix You | N90: =Spotify!D97 -> Coldplay | O90: =Spotify!E97 -> 38510 | P90: =ROUND(Spotify!U97,0) -> 138 | Q90: =ROUND(Spotify!L97*100,0) -> 42 | R90: =ROUND(Spotify!K97*100,0) -> 21 | S90: =Spotify!N97 -> -8.74 | T90: =ROUND(Spotify!T97*100,0) -> 12 | U90: =ROUND(Spotify!F97/60000,1) -> 4.9 | V90: =ROUND(Spotify!Q97*100,0) -> 16 | W90: =Spotify!G97 -> 86
A91: =RAND() -> 0.59808427 | B91: WIP | C91: G | D91: Faith | E91: George Michael | G91: 1987 | H91: Rock | I91: Pop | J91: groovy;dance;fast;oldies;retro;love | K91: =CONCATENATE(SUBSTITUTE(Spotify!J98,",",";"),";",J91) -> ;groovy;dance;fast;oldies;retro;love | M91: =Spotify!B98 -> Flowers | N91: =Spotify!D98 -> Miley Cyrus | O91: =Spotify!E98 -> 44939 | P91: =ROUND(Spotify!U98,0) -> 118 | Q91: =ROUND(Spotify!L98*100,0) -> 68 | R91: =ROUND(Spotify!K98*100,0) -> 71 | S91: =Spotify!N98 -> -4.325 | T91: =ROUND(Spotify!T98*100,0) -> 65 | U91: =ROUND(Spotify!F98/60000,1) -> 3.3 | V91: =ROUND(Spotify!Q98*100,0) -> 6 | W91: =Spotify!G98 -> 14
A92: =RAND() -> 0.99895938 | B92: WIP | D92: Fare Thee Well (Dink's Song) | E92: Various | G92: 2002 | H92: Folk | J92: acoustic;slow;alternative;folk | K92: =CONCATENATE(SUBSTITUTE(Spotify!J100,",",";"),";",J92) -> ;acoustic;slow;alternative;folk | M92: =Spotify!B100 -> Follow Me | N92: =Spotify!D100 -> Uncle Kracker | O92: =Spotify!E100 -> 36690 | P92: =ROUND(Spotify!U100,0) -> 105 | Q92: =ROUND(Spotify!L100*100,0) -> 59 | R92: =ROUND(Spotify!K100*100,0) -> 82 | S92: =Spotify!N100 -> -4.688 | T92: =ROUND(Spotify!T100*100,0) -> 92 | U92: =ROUND(Spotify!F100/60000,1) -> 3.6 | V92: =ROUND(Spotify!Q100*100,0) -> 44 | W92: =Spotify!G100 -> 75
A93: =RAND() -> 0.75873506 | B93: WIP | C93: D# | D93: Feels Like Home | E93: Edwina Hayes | F93: Randy Newman | G93: 2009 | H93: Folk | J93: slow;love | K93: =CONCATENATE(SUBSTITUTE(Spotify!J101,",",";"),";",J93) -> folk rock;country rock;slow;love | M93: =Spotify!B101 -> For What It's Worth | N93: =Spotify!D101 -> Buffalo Springfield | O93: =Spotify!E101 -> 24446 | P93: =ROUND(Spotify!U101,0) -> 99 | Q93: =ROUND(Spotify!L101*100,0) -> 52 | R93: =ROUND(Spotify!K101*100,0) -> 65 | S93: =Spotify!N101 -> -10.164 | T93: =ROUND(Spotify!T101*100,0) -> 82 | U93: =ROUND(Spotify!F101/60000,1) -> 2.6 | V93: =ROUND(Spotify!Q101*100,0) -> 41 | W93: =Spotify!G101 -> 81
A94: =RAND() -> 0.74419411 | B94: WIP | C94: Em | D94: Fifty Ways To Leave Your Lover | E94: Paul Simon | G94: 1975 | H94: Rock | I94: Folk / Soft | J94: oldies;retro;love;groovy | K94: =CONCATENATE(SUBSTITUTE(Spotify!J102,",",";"),";",J94) -> ;oldies;retro;love;groovy | M94: =Spotify!B102 -> Forever | N94: =Spotify!D102 -> Eric Hutchinson | O94: =Spotify!E102 -> 41737 | P94: =ROUND(Spotify!U102,0) -> 144 | Q94: =ROUND(Spotify!L102*100,0) -> 80 | R94: =ROUND(Spotify!K102*100,0) -> 57 | S94: =Spotify!N102 -> -6.462 | T94: =ROUND(Spotify!T102*100,0) -> 52 | U94: =ROUND(Spotify!F102/60000,1) -> 3.7 | V94: =ROUND(Spotify!Q102*100,0) -> 2 | W94: =Spotify!G102 -> 22
A95: =RAND() -> 0.73368029 | B95: WIP | D95: First Day Of My Life | E95: Bright Eyes | G95: 2005 | H95: Folk | I95: Indie | J95: alternative;acoustic;love;sweet | K95: =CONCATENATE(SUBSTITUTE(Spotify!J104,",",";"),";",J95) -> soft pop;alternative;acoustic;love;sweet | M95: =Spotify!B104 -> Galway Girl | N95: =Spotify!D104 -> Ed Sheeran | O95: =Spotify!E104 -> 42797 | P95: =ROUND(Spotify!U104,0) -> 100 | Q95: =ROUND(Spotify!L104*100,0) -> 88 | R95: =ROUND(Spotify!K104*100,0) -> 62 | S95: =Spotify!N104 -> -3.374 | T95: =ROUND(Spotify!T104*100,0) -> 78 | U95: =ROUND(Spotify!F104/60000,1) -> 2.8 | V95: =ROUND(Spotify!Q104*100,0) -> 7 | W95: =Spotify!G104 -> 82
A96: =RAND() -> 0.75170365 | C96: A | D96: Five Hundred Miles | E96: Peter Paul and Mary | G96: 1962 | H96: Folk | I96: Country | J96: slow;love;acoustic;alternative;oldies;retro;waltz;folk | K96: =CONCATENATE(SUBSTITUTE(Spotify!J105,",",";"),";",J96) -> ;slow;love;acoustic;alternative;oldies;retro;waltz;folk | M96: =Spotify!B105 -> Genie In a Bottle | N96: =Spotify!D105 -> Christina Aguilera | O96: =Spotify!E105 -> 1999 | P96: =ROUND(Spotify!U105,0) -> 176 | Q96: =ROUND(Spotify!L105*100,0) -> 80 | R96: =ROUND(Spotify!K105*100,0) -> 63 | S96: =Spotify!N105 -> -6.945 | T96: =ROUND(Spotify!T105*100,0) -> 91 | U96: =ROUND(Spotify!F105/60000,1) -> 3.6 | V96: =ROUND(Spotify!Q105*100,0) -> 21 | W96: =Spotify!G105 -> 84
A97: =RAND() -> 0.65441778 | D97: Fix You | E97: Coldplay | G97: 2005 | H97: Rock | I97: Alternative | J97: love;slow | K97: =CONCATENATE(SUBSTITUTE(Spotify!J106,",",";"),";",J97) -> french house;electronic;electro;love;slow | M97: =Spotify!B106 -> Get Lucky (feat. Pharrell Williams and Nile Rodgers) | N97: =Spotify!D106 -> Daft Punk;Pharrell Williams;Nile Rodgers | O97: =Spotify!E106 -> 43441 | P97: =ROUND(Spotify!U106,0) -> 116 | Q97: =ROUND(Spotify!L106*100,0) -> 79 | R97: =ROUND(Spotify!K106*100,0) -> 81 | S97: =Spotify!N106 -> -9.404 | T97: =ROUND(Spotify!T106*100,0) -> 86 | U97: =ROUND(Spotify!F106/60000,1) -> 6.2 | V97: =ROUND(Spotify!Q106*100,0) -> 4 | W97: =Spotify!G106 -> 21
A98: =RAND() -> 0.25710209 | D98: Flowers | E98: Miley Cyrus | G98: 2023 | H98: Pop | I98: Alternative | J98: love;dance;groovy;fast | K98: =CONCATENATE(SUBSTITUTE(Spotify!J108,",",";"),";",J98) -> acoustic pop;love;dance;groovy;fast | M98: =Spotify!B108 -> Girls Just Wanna Have Fun - Acoustic | N98: =Spotify!D108 -> The Mayries | O98: =Spotify!E108 -> 42839 | P98: =ROUND(Spotify!U108,0) -> 186 | Q98: =ROUND(Spotify!L108*100,0) -> 36 | R98: =ROUND(Spotify!K108*100,0) -> 44 | S98: =Spotify!N108 -> -11.448 | T98: =ROUND(Spotify!T108*100,0) -> 36 | U98: =ROUND(Spotify!F108/60000,1) -> 2.9 | V98: =ROUND(Spotify!Q108*100,0) -> 74 | W98: =Spotify!G108 -> 51
A99: =RAND() -> 0.48554713 | C99: Am | D99: Fly Me To The Moon | E99: Frank Sinatra | F99: Bart Howard | G99: 1954 | H99: Pop | I99: Traditional | J99: jazz;love;groovy;dance;oldies;retro | K99: =CONCATENATE(SUBSTITUTE(Spotify!J109,",",";"),";",J99) -> pop;jazz;love;groovy;dance;oldies;retro | M99: =Spotify!B109 -> Give A Little More | N99: =Spotify!D109 -> Maroon 5 | O99: =Spotify!E109 -> 2010 | P99: =ROUND(Spotify!U109,0) -> 118 | Q99: =ROUND(Spotify!L109*100,0) -> 82 | R99: =ROUND(Spotify!K109*100,0) -> 75 | S99: =Spotify!N109 -> -4.301 | T99: =ROUND(Spotify!T109*100,0) -> 94 | U99: =ROUND(Spotify!F109/60000,1) -> 3 | V99: =ROUND(Spotify!Q109*100,0) -> 0 | W99: =Spotify!G109 -> 44
D100: Follow Me | E100: Uncle Kracker | G100: 2000 | H100: Country | K100: =CONCATENATE(SUBSTITUTE(Spotify!#REF!,",",";"),";",J100) -> #REF! | M100: =Spotify!#REF! -> #REF! | N100: =Spotify!#REF! -> #REF! | O100: =Spotify!#REF! -> #REF! | P100: =ROUND(Spotify!#REF!,0) -> #REF! | Q100: =ROUND(Spotify!#REF!*100,0) -> #REF! | R100: =ROUND(Spotify!#REF!*100,0) -> #REF! | S100: =Spotify!#REF! -> #REF! | T100: =ROUND(Spotify!#REF!*100,0) -> #REF! | U100: =ROUND(Spotify!#REF!/60000,1) -> #REF! | V100: =ROUND(Spotify!#REF!*100,0) -> #REF! | W100: =Spotify!#REF! -> #REF!
A101: =RAND() -> 0.10872481 | B101: WIP | C101: E | D101: For What It's Worth | E101: Buffalo Springfield | G101: 1966 | H101: Folk | I101: Rock | J101: alternative;groovy;dance;oldies;retro;folk;slow | K101: =CONCATENATE(SUBSTITUTE(Spotify!J110,",",";"),";",J101) -> punk;pop punk;alternative;groovy;dance;oldies;retro;folk;slow | M101: =Spotify!B110 -> Good Riddance (Time of Your Life) | N101: =Spotify!D110 -> Green Day | O101: =Spotify!E110 -> 35717 | P101: =ROUND(Spotify!U110,0) -> 95 | Q101: =ROUND(Spotify!L110*100,0) -> 43 | R101: =ROUND(Spotify!K110*100,0) -> 48 | S101: =Spotify!N110 -> -7.844 | T101: =ROUND(Spotify!T110*100,0) -> 65 | U101: =ROUND(Spotify!F110/60000,1) -> 2.6 | V101: =ROUND(Spotify!Q110*100,0) -> 18 | W101: =Spotify!G110 -> 82
...

Sheet Classical
A1: Title | C1: Work number | D1: Composer | E1: Length
A3: Minuet in G - Gm | C3: 114-115 | D3: Bach, J. S. (Petzold) | E3: 0.0024305556
A4: Minuet in G | C4: 116 | D4: Bach, J. S. | E4: 0.0013888889
A5: Jesu Joy of Man’s Desiring | B5: ♪♪ | C5: 147 | D5: Bach, J. S. | E5: 0.0024305556
A6: Arioso | B6: ♪♪ | C6: 156 | D6: Bach, J. S. | E6: 0.0017361111
A7: Prelude in C No 1 | C7: 553 | D7: Bach, J. S. | E7: 0.0020833333
A8: Invention 01 | C8: 772 | D8: Bach, J. S. | E8: 0.00069444444
A9: Invention 04 | C9: 775 | D9: Bach, J. S. | E9: 0.00069444444
A10: Invention 10 | C10: 781 | D10: Bach, J. S. | E10: 0.00081018519
A11: Prelude for Piano No. 1 | C11: 846 | D11: Bach, J. S. | E11: 0.0015625
A12: Prelude for Piano No. 3 | C12: 848 | D12: Bach, J. S. | E12: 0.0013888889
A13: Prelude for Piano No. 5 | C13: 850 | D13: Bach, J. S. | E13: 0.0010416667
A14: Goldberg Variations, Var. 1 | B14: ♪♪ | C14: 988 | D14: Bach, J. S. | E14: 0.0015625
A15: Goldberg Variations, Var. 5 | C15: 988 | D15: Bach, J. S. | E15: 0.0013888889
A16: Violin Partita 2 Mvt 4 - Gigue | B16: ♪♪ | C16: 1004 | D16: Bach, J. S. | E16: 0.0017361111 | F16: no repeats
A17: Orchestral Suite 3 - Air | C17: 1068 | D17: Bach, J. S. | E17: 0.003125
A18: Piano Sonata 8 Mvt 2 - Adagio Cantabile | C18: 13 | D18: Beethoven, L. v. | E18: 0.0034722222
A19: Bolero | B19: ♪♪ | D19: Calace, Rafael | E19: 0.0020833333
A20: Allemande | C20: 437 | D20: Handel, G. F. | E20: 0.0015046296
A21: Piano Sonata 16 “Facile” | C21: 545 | D21: Mozart, W. A. | E21: 0.0069444444
A22: Carnival of the Animals – The Swan | D22: Saint-Saens, Camille | E22: 0.0017361111
A23: Gymnopedie for Piano No 1 | B23: ♪♪ | D23: Satie, Erik | E23: 0.0018518519
A24: Estudio No 6 | B24: ♪♪ | D24: Sor, Fernando | E24: 0.0015046296
A25: Cavatina | B25: ♪♪ | D25: Stanley Myers | E25: 0.0027777778
A26: Recuerdos de la Alhambra | B26: ♪♪ | D26: Tarrega, Francisco | E26: 0.0034722222
A27: Bistro Fada | B27: ♪♪ | D27: Wrembel, Stephane | E27: 0.0020833333
A28: Tico Tico No Fubá | D28: Zequinha de Abreu | E28: 0.0017361111
A29: Cantabile | B29: ♪♪ | E29: 0.002662037
A38: SOLO
A39: Violin Partita 1 Mvt 3 - Double | C39: 1002 | D39: Bach, J. S. | E39: 0.0019097222
A40: Violin Partita 2 Mvt 4 - Gigue | B40: ♪♪ | C40: 1004 | D40: Bach, J. S. | E40: 0.0017361111 | F40: no repeats
A41: Violin Partita 3 Mvt 6 - Gigue | C41: 1006 | D41: Bach, J. S. | E41: 0.0013888889
A42: Cello Suite No. 1 Mvt. 3 | C42: 1007 | D42: Bach, J. S. | E42: 0.0019097222
A43: Cello Suite No. 3 Mvt. 3 | C43: 1009 | D43: Bach, J. S. | E43: 0.0024305556

Sheet Duo
A1: # | B1: WIP | C1: Key | D1: Title | E1: Artist | F1: Cover? | G1: Year | H1: Genre | I1: Genre 2 | J1: BPM | K1: Listen
A3: =RAND() -> 0.14837152 | C3: F#m | D3: 1973 | E3: James Blunt | G3: 2007 | H3: Rock | I3: Pop | J3: 135 | K3: 1973
A4: =RAND() -> 0.67025593 | C4: F | D4: A Little More | E4: Eric Hutchinson | G4: 2014 | H4: Rock | I4: Pop | J4: 160 | K4: A Little More
A5: =RAND() -> 0.36790162 | B5: WIP | C5: Dm | D5: A Man For All Seasons | E5: Robbie Williams | G5: 2003 | H5: Soundtrack | J5: 130 | K5: A Man For All Seasons
A6: =RAND() -> 0.70158295 | C6: Gm | D6: Adventure Of A Lifetime | E6: Coldplay | G6: 2015 | H6: Pop | I6: Alternative | J6: 115 | K6: Adventure Of A Lifetime
A7: =RAND() -> 0.37373296 | B7: WIP | C7: G# | D7: Africa | E7: Toto | G7: 2002 | H7: Rock | I7: Soft Rock | J7: 90 | K7: Africa
A8: =RAND() -> 0.21364367 | D8: After Midnight | E8: J J Cale | G8: 1966 | H8: Rock | J8: 95 | K8: After Midnight
A9: =RAND() -> 0.41549909 | C9: C# | D9: All About You | E9: McFly | G9: 2005 | H9: Rock | I9: Pop | J9: 140 | K9: All About You
A10: =RAND() -> 0.41023602 | C10: D | D10: All I Have To Do Is Dream | E10: Everly Brothers | G10: 1958 | H10: Rock 'n' roll | J10: 110 | K10: All I Have To Do Is Dream
A11: =RAND() -> 0.12518281 | C11: F | D11: All Star | E11: Smash Mouth | G11: 1999 | H11: Rock | I11: Alternative | J11: 120 | K11: All Star
A12: =RAND() -> 0.78891691 | C12: G | D12: Angel Of The Morning | E12: Juice Newton | G12: 1981 | H12: Country | J12: 85 | K12: Angel Of The Morning
A13: =RAND() -> 0.82450178 | D13: Angels | E13: Robbie Williams | G13: 1997 | H13: Rock | I13: Pop / Gospel | J13: 85 | K13: Angels
A14: =RAND() -> 0.43959258 | C14: G | D14: Annie's Song | E14: John Denver | G14: 1974 | H14: Rock | I14: Folk / Country | J14: 60 | K14: Annie's Song
A15: =RAND() -> 0.80834218 | C15: Cm | D15: Antonio's Song | E15: Michael Franks | F15: Til Broenner | G15: 1977 | H15: Jazz | I15: Smooth | J15: 100 | K15: Antonio's Song
A16: =RAND() -> 0.74316684 | C16: G# | D16: April Come She Will | E16: Simon and Garfunkel | G16: 1966 | H16: Rock | I16: Folk | J16: 100 | K16: April Come She Will
A17: =RAND() -> 0.98779878 | C17: Em | D17: Bistro Fada | E17: Stephane Wrembel | G17: 2011 | H17: Soundtrack | I17: Gypsy Jazz | J17: 160 | K17: Bistro Fada
A18: =RAND() -> 0.92569413 | C18: G | D18: Blackbird | E18: Beatles | G18: 1968 | H18: Folk | J18: 100 | K18: Blackbird
A19: =RAND() -> 0.23174325 | D19: Blinding Lights | E19: Weeknd | G19: 2019 | H19: RnB | I19: Soul | J19: 160 | K19: Blinding Lights
A20: =RAND() -> 0.46256639 | C20: D | D20: Blowin' In The Wind | E20: Peter Paul and Mary | F20: Bob Dylan | G20: 1962 | H20: Folk | J20: 80 | K20: Blowin' In The Wind
A21: =RAND() -> 0.47303474 | B21: WIP | C21: F | D21: Brandy | E21: Looking Glass | G21: 1972 | H21: Rock | I21: Soft | J21: 140 | K21: Brandy
A22: =RAND() -> 0.37361949 | B22: WIP | C22: A | D22: Brasileirinho | E22: Waldir Azavedo | G22: 1947 | H22: Choro | J22: 110 | K22: Brasileirinho
A23: =RAND() -> 0.78475559 | B23: WIP | C23: D | D23: Breakfast At Tiffany's | E23: Deep Blue Something | G23: 1995 | H23: Rock | I23: Alternative | J23: 115 | K23: Breakfast At Tiffany's
A24: =RAND() -> 0.0024338179 | C24: G | D24: Brown Eyed Girl | E24: Van Morrison | G24: 1967 | H24: Rock | J24: 150 | K24: Brown Eyed Girl
A25: =RAND() -> 0.90966384 | C25: F | D25: Budapest | E25: George Ezra | G25: 2013 | H25: Rock | I25: Folk | J25: 120 | K25: Budapest
A26: =RAND() -> 0.44947692 | C26: Fm | D26: Butterfly | E26: Jason Mraz | G26: 2008 | H26: Pop | J26: 120 | K26: Butterfly
A27: =RAND() -> 0.95274883 | C27: G | D27: Bye Bye Love | E27: Everly Brothers | G27: 1957 | H27: Country | I27: Rock | J27: 170 | K27: Bye Bye Love
A28: =RAND() -> 0.28659819 | B28: WIP | D28: Calendar Girl | E28: Neil Sedaka | G28: 1959 | H28: Pop | J28: 140 | K28: Calendar Girl
A29: =RAND() -> 0.52360261 | C29: Am | D29: Californication | E29: Red Hot Chili Peppers | G29: 1999 | H29: Alternative | J29: 90 | K29: Californication
A30: =RAND() -> 0.76350061 | C30: D | D30: Can't Help Falling In Love | E30: Elvis Presley | G30: 1961 | H30: Rock | I30: Soft Rock | J30: 40 | K30: Can't Help Falling In Love
A31: =RAND() -> 0.71882195 | C31: Dm | D31: Careless Whisper | E31: George Michael | G31: 1984 | H31: Pop | J31: 90 | K31: Careless Whisper
A32: =RAND() -> 0.023050649 | C32: C | D32: Carry You Home | E32: James Blunt | G32: 2008 | H32: Rock | I32: Folk | J32: 95 | K32: Carry You Home
A33: =RAND() -> 0.89729297 | B33: WIP | C33: A | D33: Catch and Release | E33: Matt Simons | G33: 2007 | H33: Pop | J33: 85 | K33: Catch and Release
A34: =RAND() -> 0.64450656 | B34: WIP | C34: Am | D34: Chained To The Rhythm | E34: Katy Perry | G34: 2017 | H34: Disco | J34: 100 | K34: Chained To The Rhythm
A35: =RAND() -> 0.83584534 | C35: G | D35: Clocks | E35: Coldplay | G35: 2002 | H35: Rock | I35: Alternative | J35: 130 | K35: Clocks
A36: =RAND() -> 0.060624896 | C36: F | D36: Closing Time | E36: Semisonic | G36: 1998 | H36: Rock | J36: 100 | K36: Closing Time
A37: =RAND() -> 0.36658231 | D37: Cloud Number Nine | E37: Bryan Adams | G37: 1999 | H37: Pop | J37: 120 | K37: Cloud Number Nine
A38: =RAND() -> 0.51157962 | B38: WIP | D38: Come Away With Me | E38: Norah Jones | G38: 2002 | H38: Pop | I38: Jazz | K38: Come Away With Me
A39: =RAND() -> 0.38444713 | D39: Count On Me | E39: Bruno Mars | G39: 2010 | H39: Pop | J39: 110 | K39: Count On Me
A40: =RAND() -> 0.76468641 | D40: Country Roads | E40: John Denver | G40: 1971 | H40: Country | J40: 100 | K40: Country Roads
A41: =RAND() -> 0.98522209 | C41: Cm | D41: Crazy | E41: Gnarles Barkley | G41: 2006 | H41: Soul | J41: 110 | K41: Crazy
A42: =RAND() -> 0.20241054 | C42: D | D42: Crazy Little Thing Called Love | E42: Queen | G42: 1979 | H42: Rock | J42: 150 | K42: Crazy Little Thing Called Love
A43: =RAND() -> 0.91907321 | C43: C | D43: Dancing In The Moonlight | E43: Toploader | G43: 1999 | H43: Pop | J43: 130 | K43: Dancing In The Moonlight
A44: =RAND() -> 0.75799295 | B44: WIP | D44: Dancing Queen | E44: ABBA | G44: 1976 | H44: Pop | K44: Dancing Queen
A45: =RAND() -> 0.72415678 | C45: D | D45: Daughters | E45: John Mayer | G45: 2004 | H45: Rock | I45: Acoustic / Blues | J45: 45 | K45: Daughters
A46: =RAND() -> 0.63712408 | C46: G | D46: Die Die Die | E46: Avett Brothers | G46: 2007 | H46: Folk | I46: Rock | J46: 125 | K46: Die, Die, Die
A47: =RAND() -> 0.97256984 | C47: Bb | D47: Don't Know Why | E47: Norah Jones | F47: Jesse Harris | G47: 2002 | H47: Pop | I47: Jazz | J47: 85 | K47: Don't Know Why
A48: =RAND() -> 0.88607606 | B48: WIP | C48: Em | D48: Don't Let Me Be Lonely Tonight | E48: James Taylor | G48: 1972 | H48: Rock | I48: Folk | J48: 90 | K48: Don't Let Me Be Lonely Tonight
A49: =RAND() -> 0.42362174 | D49: Don't Look Back In Anger | E49: Oasis | G49: 1995 | H49: Pop | I49: Britpop | J49: 95 | K49: Don't Look Back In Anger
A50: =RAND() -> 0.9745759 | C50: D | D50: Don't Stop Me Now | E50: Queen | G50: 1979 | H50: Rock | I50: Glam | J50: 130 | K50: Don't Stop Me Now
A51: =RAND() -> 0.4563741 | B51: WIP | C51: F | D51: Doubting Thomas | E51: Nickel Creek | G51: 2005 | H51: Pop | I51: Folk | J51: 70 | K51: Doubting Thomas
A52: =RAND() -> 0.56002978 | D52: Dream A Little Dream Of Me | E52: Various | F52: Laura Fygi | G52: 2002 | H52: Jazz | J52: 100 | K52: Dream A Little Dream Of Me
A53: =RAND() -> 0.98654226 | C53: Em | D53: Drive | E53: Incubus | G53: 2000 | H53: Rock | I53: Alternative | J53: 105 | K53: Drive
A54: =RAND() -> 0.36395673 | C54: C | D54: Dust in the Wind | E54: Kansas | G54: 1978 | H54: Rock | I54: Progressive / Soft | J54: 95 | K54: Dust in the Wind
A55: =RAND() -> 0.27294312 | D55: Earth Angel | E55: Death Cab for Cutie | F55: The Penguins | G55: 1954 | H55: RnB | I55: Soul | J55: 70 | K55: Earth Angel
A56: =RAND() -> 0.63858512 | C56: G | D56: Eight Days A Week | E56: Beatles | G56: 1964 | H56: Rock | J56: 145 | K56: Eight Days A Week
A57: =RAND() -> 0.98171743 | C57: F | D57: Escape (Pina Colada) | E57: Rupert Holmes | G57: 1979 | H57: Rock | J57: 60 | K57: Escape (Pina Colada)
A58: =RAND() -> 0.3367252 | C58: F | D58: Every Little Thing She Does Is Magic | E58: Eric Hutchinson | F58: The Police | G58: 1981 | H58: Pop | J58: 140 | K58: Every Little Thing She Does Is Magic
A59: =RAND() -> 0.55523848 | B59: WIP | C59: D | D59: Everything | E59: Michael Buble | G59: 2006 | H59: Pop | J59: 130 | K59: Everything
A60: =RAND() -> 0.53104635 | C60: F | D60: Everything I Own | E60: Bread | G60: 1972 | H60: Rock | I60: Soft Rock | J60: 85 | K60: Everything I Own
A61: =RAND() -> 0.4188601 | C61: G | D61: Faith | E61: George Michael | G61: 1987 | H61: Rock | I61: Pop | J61: 95 | K61: Faith
A62: =RAND() -> 0.74213173 | D62: Fare Thee Well (Dink's Song) | E62: Various | G62: 2002 | H62: Folk | J62: 80 | K62: Fare Thee Well (Dink's Song)
A63: =RAND() -> 0.17739646 | B63: WIP | C63: C | D63: Fire and Rain | E63: James Taylor | G63: 1970 | H63: Rock | I63: Folk / Soft | J63: 80 | K63: Fire and Rain
A64: =RAND() -> 0.14051117 | B64: WIP | D64: Fireflies | E64: Owl City | G64: 2009 | H64: Pop | I64: Synthpop | J64: 90 | K64: Fireflies
A65: =RAND() -> 0.79063474 | D65: First Day Of My Life | E65: Bright Eyes | G65: 2005 | H65: Folk | I65: Indie | J65: 100 | K65: First Day Of My Life
A66: =RAND() -> 0.72587768 | C66: A | D66: Five Hundred Miles | E66: Peter Paul and Mary | G66: 1962 | H66: Folk | I66: Country | J66: 60 | K66: Five Hundred Miles
A67: =RAND() -> 0.92777294 | D67: Flightless Bird American Mouth | E67: Iron and Wine | G67: 2008 | H67: Rock | I67: Soft Rock | J67: 50 | K67: Flightless Bird, American Mouth
A68: =RAND() -> 0.96367183 | C68: Am | D68: Fly Me To The Moon | E68: Frank Sinatra | F68: Bart Howard | G68: 1954 | H68: Pop | I68: Traditional | J68: 130 | K68: Fly Me To The Moon
A69: =RAND() -> 0.93825749 | D69: Free Falling | E69: John Mayer | F69: Tom Petty | G69: 1989 | H69: Rock | I69: Classic | J69: 90 | K69: Free Falling
A70: =RAND() -> 0.26715903 | B70: WIP | C70: Dm | D70: Give A Little More | E70: Maroon 5 | G70: 2010 | H70: Disco | J70: 125 | K70: Give A Little More
A71: =RAND() -> 0.91052623 | D71: Good Riddance (Time Of Your Life) | E71: Green Day | G71: 1997 | H71: Rock | I71: Acoustic / Alternative | J71: 100 | K71: Good Riddance (Time Of Your Life)
A72: =RAND() -> 0.64151129 | B72: WIP | C72: F | D72: Goodnight Goodbye | E72: Eric Hutchinson | G72: 2014 | H72: Rock | I72: Folk | J72: 120 | K72: Goodnight, Goodbye
A73: =RAND() -> 0.10217342 | B73: WIP | C73: D | D73: Got You Under My Skin | E73: Frank Sinatra | G73: 1956 | H73: Pop | I73: Traditional | K73: Got You Under My Skin
A74: =RAND() -> 0.58438588 | C74: A | D74: Green Eyes | E74: Coldplay | G74: 2002 | H74: Alternative | J74: 70 | K74: Green Eyes
A75: =RAND() -> 0.11722763 | C75: G | D75: Guitar Man | E75: Bread | G75: 1972 | H75: Rock | J75: 70 | K75: Guitar Man
A76: =RAND() -> 0.032182009 | D76: Hallelujah | E76: Jeff Buckley | F76: Leonard Cohen | G76: 1984 | H76: Rock | I76: Folk / Gospel | J76: 60 | K76: Hallelujah
A77: =RAND() -> 0.44601378 | B77: WIP | C77: E | D77: Happy | E77: Pharell Williams | G77: 2013 | H77: Pop | J77: 150 | K77: Happy
A78: =RAND() -> 0.95017988 | C78: C | D78: Have You Ever Seen The Rain | E78: CCR | G78: 1971 | H78: Rock | I78: Roots | J78: 130 | K78: Have You Ever Seen The Rain
A79: =RAND() -> 0.73491358 | D79: Heart Of Gold | E79: Neil Young | G79: 1972 | H79: Rock | I79: Classic | J79: 90 | K79: Heart Of Gold
A80: =RAND() -> 0.8418853 | B80: WIP | C80: Am | D80: Hello | E80: Lionel Richie | G80: 1983 | H80: Pop | J80: 85
A81: =RAND() -> 0.45387987 | C81: Am | D81: Here Without You | E81: 3 Doors Down | G81: 2002 | H81: Rock | J81: 80 | K81: Here Without You
A82: =RAND() -> 0.15502258 | C82: D | D82: Hey Jude | E82: Beatles | G82: 1968 | H82: Rock | I82: Pop | J82: 85 | K82: Hey Jude
A83: =RAND() -> 0.93618572 | C83: D | D83: Hey Soul Sister | E83: Train | G83: 2002 | H83: Rock | I83: Folk / Pop | J83: 100 | K83: Hey, Soul Sister
A84: =RAND() -> 0.42869811 | C84: D | D84: Hey There Delilah | E84: Plain White T's | G84: 2004 | H84: Pop | I84: Acoustic | J84: 105 | K84: Hey There Delilah
A85: =RAND() -> 0.4099496 | C85: Am | D85: Hotel California | E85: Eagles | G85: 1976 | H85: Rock | J85: 80 | K85: Hotel California
A86: =RAND() -> 0.0042522337 | D86: Hymn For The Weekend | E86: Coldplay | G86: 2015 | H86: Pop | I86: Alternative | J86: 95 | K86: Hymn For The Weekend
A87: =RAND() -> 0.55681332 | C87: C | D87: I Saw Her Standing There | E87: Beatles | G87: 1968 | H87: Rock | I87: Pop | J87: 150 | K87: I Saw Her Standing There
A88: =RAND() -> 0.98867454 | C88: D | D88: I Wanna Hold Your Hand | E88: Beatles | G88: 1963 | H88: Rock | I88: Pop | J88: 125 | K88: I Wanna Hold Your Hand
A89: =RAND() -> 0.27340056 | C89: D | D89: I Will Follow You Into The Dark | E89: Death Cab for Cutie | G89: 2006 | H89: Rock | I89: Acoustic / Indie | J89: 85 | K89: I Will Follow You Into The Dark
A90: =RAND() -> 0.39735233 | C90: Em | D90: I'd Love To Change The World | E90: Ten Years After | G90: 2002 | H90: Rock | I90: 70s | J90: 120 | K90: I'd Love To Change The World
A91: =RAND() -> 0.67123752 | B91: WIP | C91: F | D91: If | E91: Bread | G91: 1971 | H91: Folk Rock | I91: Soft Rock | J91: 50 | K91: If
A92: =RAND() -> 0.49508813 | C92: A | D92: If I Had A Hammer | E92: Peter Paul and Mary | F92: Seeger / Hayes | G92: 1962 | H92: Folk | J92: 95 | K92: If I Had A Hammer
A93: =RAND() -> 0.76987626 | C93: G# | D93: I'll Be There For You ("Friends" theme) | E93: Rembrandts | G93: 1995 | H93: Rock | I93: Alternative / Pop | J93: 100 | K93: I'll Be There For You
A94: =RAND() -> 0.2032691 | C94: G | D94: I'm A Believer | E94: Monkees | G94: 1967 | H94: Pop | I94: 60s | J94: 150 | K94: I'm A Believer
A95: =RAND() -> 0.039710706 | D95: I'm Yours | E95: Jason Mraz | G95: 2008 | H95: Rock | I95: Folk / Reggae | J95: 80 | K95: I'm Yours
A96: =RAND() -> 0.010422169 | C96: Am | D96: Killing Me Softly | E96: Lori Lieberman | G96: 1972 | H96: Folk | J96: 55 | K96: Killing Me Softly
A97: =RAND() -> 0.25020719 | B97: WIP | C97: D | D97: La Vie En Rose | E97: Louis Armstrong | F97: Edith Piaf | G97: 1950 | H97: Jazz | I97: Blues | K97: La Vie En Rose
A98: =RAND() -> 0.62717673 | B98: WIP | D98: Layla | E98: Eric Clapton | G98: 1971 | H98: Rock | I98: Blues / Hard | K98: Layla
A99: =RAND() -> 0.1618025 | D99: Leaving On A Jet Plane | E99: John Denver | G99: 1966 | H99: Folk | J99: 65 | K99: Leaving On A Jet Plane
A100: =RAND() -> 0.81526333 | D100: Lemon Tree | E100: Fool's Garden | G100: 1995 | H100: Pop | J100: 140 | K100: Lemon Tree
A101: =RAND() -> 0.076079037 | B101: WIP | D101: Let Her Go | E101: Passenger | G101: 2012 | H101: Rock | I101: Folk / Indie | K101: Let Her Go
...

Sheet CSV
A1: =IF((Contemporary!D1<>""),(CONCATENATE(Contemporary!D1,",",Contemporary!E1,",",Contemporary!G1,",",Contemporary!H1,",",Contemporary!P1,",",Contemporary!Q1,",",Contemporary!R1,",",Contemporary!T1,",",Contemporary!W1,",",Contemporary!B1,",",SUBSTITUTE(B1,",","%2c"),",",IF(Contemporary!K1<>"",Contemporary!K1,CONCATENATE(Contemporary!H1,";",Contemporary!I1)),",",Spotify!A1)),"") -> Title,Artist,Year,Genre,BPM,Energy,Dance,Valence,Popularity,WIP,,Tags,Spotify ID
A2: =IF((Contemporary!D2<>""),(CONCATENATE(Contemporary!D2,",",Contemporary!E2,",",Contemporary!G2,",",Contemporary!H2,",",Contemporary!P2,",",Contemporary!Q2,",",Contemporary!R2,",",Contemporary!T2,",",Contemporary!W2,",",Contemporary!B2,",",SUBSTITUTE(B2,",","%2c"),",",IF(Contemporary!K2<>"",Contemporary!K2,CONCATENATE(Contemporary!H2,";",Contemporary!I2)),",",Spotify!A2)),"")
A3: =IF((Contemporary!D3<>""),(CONCATENATE(Contemporary!D3,",",Contemporary!E3,",",Contemporary!G3,",",Contemporary!H3,",",Contemporary!P3,",",Contemporary!Q3,",",Contemporary!R3,",",Contemporary!T3,",",Contemporary!W3,",",Contemporary!B3,",",SUBSTITUTE(B3,",","%2c"),",",IF(Contemporary!K3<>"",Contemporary!K3,CONCATENATE(Contemporary!H3,";",Contemporary!I3)),",",Spotify!A3)),"") -> 1973,James Blunt,2007,Rock,123,67,72,77,75,WIP,,;pop;alternative;love;dance,1BV0m40U0M4t1SLIsDnwZl
A4: =IF((Contemporary!D4<>""),(CONCATENATE(Contemporary!D4,",",Contemporary!E4,",",Contemporary!G4,",",Contemporary!H4,",",Contemporary!P4,",",Contemporary!Q4,",",Contemporary!R4,",",Contemporary!T4,",",Contemporary!W4,",",Contemporary!B4,",",SUBSTITUTE(B4,",","%2c"),",",IF(Contemporary!K4<>"",Contemporary!K4,CONCATENATE(Contemporary!H4,";",Contemporary!I4)),",",Spotify!A4)),"") -> A Hard Day's Night,Beatles,1964,Rock,139,82,55,76,54,,,classic rock;psychedelic rock;dance;jive;fast;groovy;love;oldies;retro,1pctwlBtIcKIjQMzsVcGHB
A5: =IF((Contemporary!D5<>""),(CONCATENATE(Contemporary!D5,",",Contemporary!E5,",",Contemporary!G5,",",Contemporary!H5,",",Contemporary!P5,",",Contemporary!Q5,",",Contemporary!R5,",",Contemporary!T5,",",Contemporary!W5,",",Contemporary!B5,",",SUBSTITUTE(B5,",","%2c"),",",IF(Contemporary!K5<>"",Contemporary!K5,CONCATENATE(Contemporary!H5,";",Contemporary!I5)),",",Spotify!A5)),"") -> A Little Less Conversation,Elvis Presley,1968,Rock,114,80,58,84,56,WIP,,rockabilly;rock and roll;dance;jive;fast;groovy;love;oldies;retro,47y8hRlWLEJ4VafE6LMjEZ
A6: =IF((Contemporary!D6<>""),(CONCATENATE(Contemporary!D6,",",Contemporary!E6,",",Contemporary!G6,",",Contemporary!H6,",",Contemporary!P6,",",Contemporary!Q6,",",Contemporary!R6,",",Contemporary!T6,",",Contemporary!W6,",",Contemporary!B6,",",SUBSTITUTE(B6,",","%2c"),",",IF(Contemporary!K6<>"",Contemporary!K6,CONCATENATE(Contemporary!H6,";",Contemporary!I6)),",",Spotify!A6)),"") -> A Little More,Eric Hutchinson,2014,Rock,80,74,64,94,44,WIP,,;fast;dance;groovy;alternative,3AH12fVi34vJVqriMpM6Bo
A7: =IF((Contemporary!D7<>""),(CONCATENATE(Contemporary!D7,",",Contemporary!E7,",",Contemporary!G7,",",Contemporary!H7,",",Contemporary!P7,",",Contemporary!Q7,",",Contemporary!R7,",",Contemporary!T7,",",Contemporary!W7,",",Contemporary!B7,",",SUBSTITUTE(B7,",","%2c"),",",IF(Contemporary!K7<>"",Contemporary!K7,CONCATENATE(Contemporary!H7,";",Contemporary!I7)),",",Spotify!A7)),"") -> A Man For All Seasons,Robbie Williams,2003,Soundtrack,124,74,58,82,42,WIP,,soundtrack;score;dance;groovy,3RIm56NRLSZYo1xgHlbPH4
A8: =IF((Contemporary!D8<>""),(CONCATENATE(Contemporary!D8,",",Contemporary!E8,",",Contemporary!G8,",",Contemporary!H8,",",Contemporary!P8,",",Contemporary!Q8,",",Contemporary!R8,",",Contemporary!T8,",",Contemporary!W8,",",Contemporary!B8,",",SUBSTITUTE(B8,",","%2c"),",",IF(Contemporary!K8<>"",Contemporary!K8,CONCATENATE(Contemporary!H8,";",Contemporary!I8)),",",Spotify!A8)),"") -> A Sky Full Of Stars,Coldplay,2014,Rock,125,68,55,16,88,,,;alternative,0FDzzruyVECATHXKHFs9eJ
A9: =IF((Contemporary!D9<>""),(CONCATENATE(Contemporary!D9,",",Contemporary!E9,",",Contemporary!G9,",",Contemporary!H9,",",Contemporary!P9,",",Contemporary!Q9,",",Contemporary!R9,",",Contemporary!T9,",",Contemporary!W9,",",Contemporary!B9,",",SUBSTITUTE(B9,",","%2c"),",",IF(Contemporary!K9<>"",Contemporary!K9,CONCATENATE(Contemporary!H9,";",Contemporary!I9)),",",Spotify!A9)),"") -> A Thousand Miles,Vanessa Carlton,2002,Pop,95,83,56,27,83,,,;dance;groovy;love;waltz,4w1lzcaoZ1IC2K5TwjalRP
A10: =IF((Contemporary!D10<>""),(CONCATENATE(Contemporary!D10,",",Contemporary!E10,",",Contemporary!G10,",",Contemporary!H10,",",Contemporary!P10,",",Contemporary!Q10,",",Contemporary!R10,",",Contemporary!T10,",",Contemporary!W10,",",Contemporary!B10,",",SUBSTITUTE(B10,",","%2c"),",",IF(Contemporary!K10<>"",Contemporary!K10,CONCATENATE(Contemporary!H10,";",Contemporary!I10)),",",Spotify!A10)),"") -> A Thousand Years,Christina Perri,2011,Soundtrack,139,41,42,16,86,,,soft pop;love;slow,6lanRgr6wXibZr8KgzXxBl
A11: =IF((Contemporary!D11<>""),(CONCATENATE(Contemporary!D11,",",Contemporary!E11,",",Contemporary!G11,",",Contemporary!H11,",",Contemporary!P11,",",Contemporary!Q11,",",Contemporary!R11,",",Contemporary!T11,",",Contemporary!W11,",",Contemporary!B11,",",SUBSTITUTE(B11,",","%2c"),",",IF(Contemporary!K11<>"",Contemporary!K11,CONCATENATE(Contemporary!H11,";",Contemporary!I11)),",",Spotify!A11)),"") -> Adventure Of A Lifetime,Coldplay,2015,Pop,112,92,64,53,88,,,;dance;alternative,69uxyAqqPIsUyTO8txoP2M
A12: =IF((Contemporary!D12<>""),(CONCATENATE(Contemporary!D12,",",Contemporary!E12,",",Contemporary!G12,",",Contemporary!H12,",",Contemporary!P12,",",Contemporary!Q12,",",Contemporary!R12,",",Contemporary!T12,",",Contemporary!W12,",",Contemporary!B12,",",SUBSTITUTE(B12,",","%2c"),",",IF(Contemporary!K12<>"",Contemporary!K12,CONCATENATE(Contemporary!H12,";",Contemporary!I12)),",",Spotify!A12)),"") -> Africa,Toto,1982,Rock,93,37,67,73,90,,,yacht rock;soft rock;retro;oldies,2374M0fQpWi3dLnB54qaLX
... A24: =IF((Contemporary!D24<>""),(CONCATENATE(Contemporary!D24,",",Contemporary!E24,",",Contemporary!G24,",",Contemporary!H24,",",Contemporary!P24,",",Contemporary!Q24,",",Contemporary!R24,",",Contemporary!T24,",",Contemporary!W24,",",Contemporary!B24,",",SUBSTITUTE(B24,",","%2c"),",",IF(Contemporary!K24<>"",Contemporary!K24,CONCATENATE(Contemporary!H24,";",Contemporary!I24)),",",Spotify!A24)),"") -> Antonio's Song,Till Brönner,1977,Jazz,114,39,68,65,27,WIP,,smooth jazz;jazz;groovy;jazz;slow;oldies;retro,51FAWuc1iPdM06S65Plx11
A25: =IF((Contemporary!#REF!<>""),(CONCATENATE(Contemporary!#REF!,",",Contemporary!#REF!,",",Contemporary!#REF!,",",Contemporary!#REF!,",",Contemporary!#REF!,",",Contemporary!#REF!,",",Contemporary!#REF!,",",Contemporary!#REF!,",",Contemporary!#REF!,",",Contemporary!#REF!,",",SUBSTITUTE(B25,",","%2c"),",",IF(Contemporary!#REF!<>"",Contemporary!#REF!,CONCATENATE(Contemporary!#REF!,";",Contemporary!#REF!)),",",Spotify!#REF!)),"") -> #REF!
A26: =IF((Contemporary!#REF!<>""),(CONCATENATE(Contemporary!#REF!,",",Contemporary!#REF!,",",Contemporary!#REF!,",",Contemporary!#REF!,",",Contemporary!#REF!,",",Contemporary!#REF!,",",Contemporary!#REF!,",",Contemporary!#REF!,",",Contemporary!#REF!,",",Contemporary!#REF!,",",SUBSTITUTE(B26,",","%2c"),",",IF(Contemporary!#REF!<>"",Contemporary!#REF!,CONCATENATE(Contemporary!#REF!,";",Contemporary!#REF!)),",",Spotify!A25)),"") -> #REF!
A27: =IF((Contemporary!#REF!<>""),(CONCATENATE(Contemporary!#REF!,",",Contemporary!#REF!,",",Contemporary!#REF!,",",Contemporary!#REF!,",",Contemporary!#REF!,",",Contemporary!#REF!,",",Contemporary!#REF!,",",Contemporary!#REF!,",",Contemporary!#REF!,",",Contemporary!#REF!,",",SUBSTITUTE(B27,",","%2c"),",",IF(Contemporary!#REF!<>"",Contemporary!#REF!,CONCATENATE(Contemporary!#REF!,";",Contemporary!#REF!)),",",Spotify!A26)),"") -> #REF!
A28: =IF((Contemporary!#REF!<>""),(CONCATENATE(Contemporary!#REF!,",",Contemporary!#REF!,",",Contemporary!#REF!,",",Contemporary!#REF!,",",Contemporary!#REF!,",",Contemporary!#REF!,",",Contemporary!#REF!,",",Contemporary!#REF!,",",Contemporary!#REF!,",",Contemporary!#REF!,",",SUBSTITUTE(B28,",","%2c"),",",IF(Contemporary!#REF!<>"",Contemporary!#REF!,CONCATENATE(Contemporary!#REF!,";",Contemporary!#REF!)),",",Spotify!A27)),"") -> #REF!
A29: =IF((Contemporary!D25<>""),(CONCATENATE(Contemporary!D25,",",Contemporary!E25,",",Contemporary!G25,",",Contemporary!H25,",",Contemporary!P25,",",Contemporary!Q25,",",Contemporary!R25,",",Contemporary!T25,",",Contemporary!W25,",",Contemporary!B25,",",SUBSTITUTE(B29,",","%2c"),",",IF(Contemporary!K25<>"",Contemporary!K25,CONCATENATE(Contemporary!H25,";",Contemporary!I25)),",",Spotify!A28)),"") -> Ave Maria,Beyonce,2008,Pop,125,78,78,67,88,WIP,,;love;groovy,0pqnGHJpmpxLKifKRmU6WP
A30: =IF((Contemporary!D26<>""),(CONCATENATE(Contemporary!D26,",",Contemporary!E26,",",Contemporary!G26,",",Contemporary!H26,",",Contemporary!P26,",",Contemporary!Q26,",",Contemporary!R26,",",Contemporary!T26,",",Contemporary!W26,",",Contemporary!B26,",",SUBSTITUTE(B30,",","%2c"),",",IF(Contemporary!K26<>"",Contemporary!K26,CONCATENATE(Contemporary!H26,";",Contemporary!I26)),",",Spotify!A29)),"") -> Baby One More Time,Britney Spears,1998,Pop,95,50,52,38,65,WIP,,classical crossover;opera;love;groovy;dance,5WHnE8MsLFHqSUwecrs7WO
A31: =IF((Contemporary!#REF!<>""),(CONCATENATE(Contemporary!#REF!,",",Contemporary!#REF!,",",Contemporary!#REF!,",",Contemporary!#REF!,",",Contemporary!#REF!,",",Contemporary!#REF!,",",Contemporary!#REF!,",",Contemporary!#REF!,",",Contemporary!#REF!,",",Contemporary!#REF!,",",SUBSTITUTE(B31,",","%2c"),",",IF(Contemporary!#REF!<>"",Contemporary!#REF!,CONCATENATE(Contemporary!#REF!,";",Contemporary!#REF!)),",",Spotify!A30)),"") -> #REF!
A32: =IF((Contemporary!D27<>""),(CONCATENATE(Contemporary!D27,",",Contemporary!E27,",",Contemporary!G27,",",Contemporary!H27,",",Contemporary!P27,",",Contemporary!Q27,",",Contemporary!R27,",",Contemporary!T27,",",Contemporary!W27,",",Contemporary!B27,",",SUBSTITUTE(B32,",","%2c"),",",IF(Contemporary!K27<>"",Contemporary!K27,CONCATENATE(Contemporary!H27,";",Contemporary!I27)),",",Spotify!#REF!)),"") -> #REF!
A33: =IF((Contemporary!D28<>""),(CONCATENATE(Contemporary!D28,",",Contemporary!E28,",",Contemporary!G28,",",Contemporary!H28,",",Contemporary!P28,",",Contemporary!Q28,",",Contemporary!R28,",",Contemporary!T28,",",Contemporary!W28,",",Contemporary!B28,",",SUBSTITUTE(B33,",","%2c"),",",IF(Contemporary!K28<>"",Contemporary!K28,CONCATENATE(Contemporary!H28,";",Contemporary!I28)),",",Spotify!A31)),"") -> Believer,Imagine Dragons,2017,Rock,86,47,61,97,46,,,folk;folk rock;singer-songwriter;alternative,1wfzOH54LylpiG8hAOjKcS
A34: =IF((Contemporary!D29<>""),(CONCATENATE(Contemporary!D29,",",Contemporary!E29,",",Contemporary!G29,",",Contemporary!H29,",",Contemporary!P29,",",Contemporary!Q29,",",Contemporary!R29,",",Contemporary!T29,",",Contemporary!W29,",",Contemporary!B29,",",SUBSTITUTE(B34,",","%2c"),",",IF(Contemporary!K29<>"",Contemporary!K29,CONCATENATE(Contemporary!H29,";",Contemporary!I29)),",",Spotify!A32)),"") -> Besame Mucho,Andrea Bocelli,1940,Latin,117,65,92,85,82,,,;love;slow;jazz;bossa;oldies;retro,5ChkMS8OtdzJeqyybCc9R5
A35: =IF((Contemporary!D30<>""),(CONCATENATE(Contemporary!D30,",",Contemporary!E30,",",Contemporary!G30,",",Contemporary!H30,",",Contemporary!P30,",",Contemporary!Q30,",",Contemporary!R30,",",Contemporary!T30,",",Contemporary!W30,",",Contemporary!B30,",",SUBSTITUTE(B35,",","%2c"),",",IF(Contemporary!K30<>"",Contemporary!K30,CONCATENATE(Contemporary!H30,";",Contemporary!I30)),",",Spotify!A33)),"") -> Better When I'm Dancing,Meghan Trainor,2015,Pop,99,37,76,86,52,WIP,,french jazz;dance;fast,08T5wMbEnPN8ghT8o24KY6
A36: =IF((Contemporary!#REF!<>""),(CONCATENATE(Contemporary!#REF!,",",Contemporary!#REF!,",",Contemporary!#REF!,",",Contemporary!#REF!,",",Contemporary!#REF!,",",Contemporary!#REF!,",",Contemporary!#REF!,",",Contemporary!#REF!,",",Contemporary!#REF!,",",Contemporary!#REF!,",",SUBSTITUTE(B36,",","%2c"),",",IF(Contemporary!#REF!<>"",Contemporary!#REF!,CONCATENATE(Contemporary!#REF!,";",Contemporary!#REF!)),",",Spotify!A34)),"") -> #REF!
A37: =IF((Contemporary!D31<>""),(CONCATENATE(Contemporary!D31,",",Contemporary!E31,",",Contemporary!G31,",",Contemporary!H31,",",Contemporary!P31,",",Contemporary!Q31,",",Contemporary!R31,",",Contemporary!T31,",",Contemporary!W31,",",Contemporary!B31,",",SUBSTITUTE(B37,",","%2c"),",",IF(Contemporary!K31<>"",Contemporary!K31,CONCATENATE(Contemporary!H31,";",Contemporary!I31)),",",Spotify!A35)),"") -> Big Yellow Taxi,Joni Mitchell,1970,Rock,115,93,76,96,68,WIP,,;pop;acoustic;alternative;retro;oldies,6wdviVWctiZnY6tVn6bh6A
A38: =IF((Contemporary!D32<>""),(CONCATENATE(Contemporary!D32,",",Contemporary!E32,",",Contemporary!G32,",",Contemporary!H32,",",Contemporary!P32,",",Contemporary!Q32,",",Contemporary!R32,",",Contemporary!T32,",",Contemporary!W32,",",Contemporary!B32,",",SUBSTITUTE(B38,",","%2c"),",",IF(Contemporary!K32<>"",Contemporary!K32,CONCATENATE(Contemporary!H32,";",Contemporary!I32)),",",Spotify!A36)),"") -> Billie Jean,Michael Jackson,1982,Pop,94,13,69,37,80,,,classic rock;psychedelic rock;,5jgFfDIR6FR0gvlA56Nakr
A39: =IF((Contemporary!#REF!<>""),(CONCATENATE(Contemporary!#REF!,",",Contemporary!#REF!,",",Contemporary!#REF!,",",Contemporary!#REF!,",",Contemporary!#REF!,",",Contemporary!#REF!,",",Contemporary!#REF!,",",Contemporary!#REF!,",",Contemporary!#REF!,",",Contemporary!#REF!,",",SUBSTITUTE(B39,",","%2c"),",",IF(Contemporary!#REF!<>"",Contemporary!#REF!,CONCATENATE(Contemporary!#REF!,";",Contemporary!#REF!)),",",Spotify!A37)),"") -> #REF!
A40: =IF((Contemporary!D33<>""),(CONCATENATE(Contemporary!D33,",",Contemporary!E33,",",Contemporary!G33,",",Contemporary!H33,",",Contemporary!P33,",",Contemporary!Q33,",",Contemporary!R33,",",Contemporary!T33,",",Contemporary!W33,",",Contemporary!B33,",",SUBSTITUTE(B40,",","%2c"),",",IF(Contemporary!K33<>"",Contemporary!K33,CONCATENATE(Contemporary!H33,";",Contemporary!I33)),",",Spotify!A38)),"") -> Bistro Fada,Stephane Wrembel,2011,Jazz,155,8,38,56,60,WIP,,folk;folk rock;instrumental;waltz,62Yu8QL1g9pdbvN4XL9Rah
A41: =IF((Contemporary!D34<>""),(CONCATENATE(Contemporary!D34,",",Contemporary!E34,",",Contemporary!G34,",",Contemporary!H34,",",Contemporary!P34,",",Contemporary!Q34,",",Contemporary!R34,",",Contemporary!T34,",",Contemporary!W34,",",Contemporary!B34,",",SUBSTITUTE(B41,",","%2c"),",",IF(Contemporary!K34<>"",Contemporary!K34,CONCATENATE(Contemporary!H34,";",Contemporary!I34)),",",Spotify!A39)),"") -> Bitter Sweet Symphony,Verve,1997,Rock,125,63,72,83,78,,,yacht rock;alternative,2BY7ALEWdloFHgQZG6VMLA
A42: =IF((Contemporary!D35<>""),(CONCATENATE(Contemporary!D35,",",Contemporary!E35,",",Contemporary!G35,",",Contemporary!H35,",",Contemporary!P35,",",Contemporary!Q35,",",Contemporary!R35,",",Contemporary!T35,",",Contemporary!W35,",",Contemporary!B35,",",SUBSTITUTE(B42,",","%2c"),",",IF(Contemporary!K35<>"",Contemporary!K35,CONCATENATE(Contemporary!H35,";",Contemporary!I35)),",",Spotify!A40)),"") -> Black Or White,Michael Jackson,1991,Pop,105,52,49,92,33,WIP,,samba;seresta;classical;chamber music;brazilian jazz;bossa nova;latin jazz;afro-cuban jazz;big band;jazz;,6MTrtNdft6F4t64fEzhNNA
A43: =IF((Contemporary!D36<>""),(CONCATENATE(Contemporary!D36,",",Contemporary!E36,",",Contemporary!G36,",",Contemporary!H36,",",Contemporary!P36,",",Contemporary!Q36,",",Contemporary!R36,",",Contemporary!T36,",",Contemporary!W36,",",Contemporary!B36,",",SUBSTITUTE(B43,",","%2c"),",",IF(Contemporary!K36<>"",Contemporary!K36,CONCATENATE(Contemporary!H36,";",Contemporary!I36)),",",Spotify!A41)),"") -> Blackbird,Beatles,1968,Folk,110,83,62,54,73,WIP,,;oldies;retro;acoustic;alternative;folk,1uzWOoJdADfstQuFtQFTUn
A44: =IF((Contemporary!D37<>""),(CONCATENATE(Contemporary!D37,",",Contemporary!E37,",",Contemporary!G37,",",Contemporary!H37,",",Contemporary!P37,",",Contemporary!Q37,",",Contemporary!R37,",",Contemporary!T37,",",Contemporary!W37,",",Contemporary!B37,",",SUBSTITUTE(B44,",","%2c"),",",IF(Contemporary!K37<>"",Contemporary!K37,CONCATENATE(Contemporary!H37,";",Contemporary!I37)),",",Spotify!A42)),"") -> Blinding Lights,Weeknd,2019,RnB,170,45,39,29,66,,,;groovy;dance;fast;love,5auMzVHFr5Zfw6IbKarZ56
A45: =IF((Contemporary!D38<>""),(CONCATENATE(Contemporary!D38,",",Contemporary!E38,",",Contemporary!G38,",",Contemporary!H38,",",Contemporary!P38,",",Contemporary!Q38,",",Contemporary!R38,",",Contemporary!T38,",",Contemporary!W38,",",Contemporary!B38,",",SUBSTITUTE(B45,",","%2c"),",",IF(Contemporary!K38<>"",Contemporary!K38,CONCATENATE(Contemporary!H38,";",Contemporary!I38)),",",Spotify!A43)),"") -> Blowin' In The Wind,Peter Paul and Mary,1962,Folk,151,58,49,91,19,,,;acoustic;oldies;retro;folk,3yrSvpt2l1xhsV9Em88Pul
A46: =IF((Contemporary!D39<>""),(CONCATENATE(Contemporary!D39,",",Contemporary!E39,",",Contemporary!G39,",",Contemporary!H39,",",Contemporary!P39,",",Contemporary!Q39,",",Contemporary!R39,",",Contemporary!T39,",",Contemporary!W39,",",Contemporary!B39,",",SUBSTITUTE(B46,",","%2c"),",",IF(Contemporary!K39<>"",Contemporary!K39,CONCATENATE(Contemporary!H39,";",Contemporary!I39)),",",Spotify!A44)),"") -> Brandy,Looking Glass,1972,Rock,128,46,72,39,83,,,;groovy;dance;fast;oldies;retro,2ixsaeFioXJmMgkkbd4uj1
A47: =IF((Contemporary!D40<>""),(CONCATENATE(Contemporary!D40,",",Contemporary!E40,",",Contemporary!G40,",",Contemporary!H40,",",Contemporary!P40,",",Contemporary!Q40,",",Contemporary!R40,",",Contemporary!T40,",",Contemporary!W40,",",Contemporary!B40,",",SUBSTITUTE(B47,",","%2c"),",",IF(Contemporary!K40<>"",Contemporary!K40,CONCATENATE(Contemporary!H40,";",Contemporary!I40)),",",Spotify!A45)),"") -> Brasileirinho,Waldir Azavedo,1947,Choro,108,66,72,80,46,WIP,,soft pop;acoustic pop;instrumental,7rrmHHc1kY9vkIZnXrcH7T
A48: =IF((Contemporary!D41<>""),(CONCATENATE(Contemporary!D41,",",Contemporary!E41,",",Contemporary!G41,",",Contemporary!H41,",",Contemporary!P41,",",Contemporary!Q41,",",Contemporary!R41,",",Contemporary!T41,",",Contemporary!W41,",",Contemporary!B41,",",SUBSTITUTE(B48,",","%2c"),",",IF(Contemporary!K41<>"",Contemporary!K41,CONCATENATE(Contemporary!H41,";",Contemporary!I41)),",",Spotify!A46)),"") -> Breakfast At Tiffany's,Deep Blue Something,1995,Rock,170,52,55,89,54,WIP,,doo-wop;love,6oRHRkQigTzJ3KwpO3XOV6
A49: =IF((Contemporary!D42<>""),(CONCATENATE(Contemporary!D42,",",Contemporary!E42,",",Contemporary!G42,",",Contemporary!H42,",",Contemporary!P42,",",Contemporary!Q42,",",Contemporary!R42,",",Contemporary!T42,",",Contemporary!W42,",",Contemporary!B42,",",SUBSTITUTE(B49,",","%2c"),",",IF(Contemporary!K42<>"",Contemporary!K42,CONCATENATE(Contemporary!H42,";",Contemporary!I42)),",",Spotify!A47)),"") -> Breathe (2 AM),Anna Nalick,2004,Folk,123,65,70,86,57,WIP,,doo-wop;adult standards;,7Gpx2fNJiilvrf9Ss8qbit
A50: =IF((Contemporary!D43<>""),(CONCATENATE(Contemporary!D43,",",Contemporary!E43,",",Contemporary!G43,",",Contemporary!H43,",",Contemporary!P43,",",Contemporary!Q43,",",Contemporary!R43,",",Contemporary!T43,",",Contemporary!W43,",",Contemporary!B43,",",SUBSTITUTE(B50,",","%2c"),",",IF(Contemporary!K43<>"",Contemporary!K43,CONCATENATE(Contemporary!H43,";",Contemporary!I43)),",",Spotify!A48)),"") -> Brown Eyed Girl,Van Morrison,1967,Rock,96,77,59,33,88,,,funk rock;alternative rock;rock;love;dance;fast;oldies;retro,48UPSzbZjgc449aqz8bxox
A51: =IF((Contemporary!D44<>""),(CONCATENATE(Contemporary!D44,",",Contemporary!E44,",",Contemporary!G44,",",Contemporary!H44,",",Contemporary!P44,",",Contemporary!Q44,",",Contemporary!R44,",",Contemporary!T44,",",Contemporary!W44,",",Contemporary!B44,",",SUBSTITUTE(B51,",","%2c"),",",IF(Contemporary!K44<>"",Contemporary!K44,CONCATENATE(Contemporary!H44,";",Contemporary!I44)),",",Spotify!A49)),"") -> Budapest,George Ezra,2013,Rock,100,29,40,34,83,,,rockabilly;rock and roll;love;dance,44AyOl4qVkzS48vBsbNXaC
... A72: =IF((Contemporary!D65<>""),(CONCATENATE(Contemporary!D65,",",Contemporary!E65,",",Contemporary!G65,",",Contemporary!H65,",",Contemporary!P65,",",Contemporary!Q65,",",Contemporary!R65,",",Contemporary!T65,",",Contemporary!W65,",",Contemporary!B65,",",SUBSTITUTE(B72,",","%2c"),",",IF(Contemporary!K65<>"",Contemporary!K65,CONCATENATE(Contemporary!H65,";",Contemporary!I65)),",",Spotify!A70)),"") -> Crazy Little Thing Called Love,Queen,1979,Rock,79,78,66,83,70,,,;groovy;dance;fast;oldies;retro,3cU2wBxuV6nFiuf6PJZNlC
A73: =IF((Contemporary!D66<>""),(CONCATENATE(Contemporary!D66,",",Contemporary!E66,",",Contemporary!G66,",",Contemporary!H66,",",Contemporary!P66,",",Contemporary!Q66,",",Contemporary!R66,",",Contemporary!T66,",",Contemporary!W66,",",Contemporary!B66,",",SUBSTITUTE(B73,",","%2c"),",",IF(Contemporary!K66<>"",Contemporary!K66,CONCATENATE(Contemporary!H66,";",Contemporary!I66)),",",Spotify!#REF!)),"") -> #REF!
A74: =IF((Contemporary!D67<>""),(CONCATENATE(Contemporary!D67,",",Contemporary!E67,",",Contemporary!G67,",",Contemporary!H67,",",Contemporary!P67,",",Contemporary!Q67,",",Contemporary!R67,",",Contemporary!T67,",",Contemporary!W67,",",Contemporary!B67,",",SUBSTITUTE(B74,",","%2c"),",",IF(Contemporary!K67<>"",Contemporary!K67,CONCATENATE(Contemporary!H67,";",Contemporary!I67)),",",Spotify!A71)),"") -> Dancing In The Moonlight,Toploader,1999,Pop,119,70,53,77,36,,,indie folk;folk;newgrass;americana;bluegrass;alt country;folk rock;groovy;dance,2HK5MzOuCmkJQlJYGCQpUU
A75: =IF((Contemporary!D68<>""),(CONCATENATE(Contemporary!D68,",",Contemporary!E68,",",Contemporary!G68,",",Contemporary!H68,",",Contemporary!P68,",",Contemporary!Q68,",",Contemporary!R68,",",Contemporary!T68,",",Contemporary!W68,",",Contemporary!B68,",",SUBSTITUTE(B75,",","%2c"),",",IF(Contemporary!K68<>"",Contemporary!K68,CONCATENATE(Contemporary!H68,";",Contemporary!I68)),",",Spotify!A72)),"") -> Dancing Queen,ABBA,1976,Pop,136,87,73,98,69,,,;groovy;dance;jive;oldies;retro;fast,2HPB3px8MJZRMfu1L65Z41
A76: =IF((Contemporary!D69<>""),(CONCATENATE(Contemporary!D69,",",Contemporary!E69,",",Contemporary!G69,",",Contemporary!H69,",",Contemporary!P69,",",Contemporary!Q69,",",Contemporary!R69,",",Contemporary!T69,",",Contemporary!W69,",",Contemporary!B69,",",SUBSTITUTE(B76,",","%2c"),",",IF(Contemporary!K69<>"",Contemporary!K69,CONCATENATE(Contemporary!H69,";",Contemporary!I69)),",",Spotify!A73)),"") -> Daughters,John Mayer,2004,Rock,85,32,74,34,61,WIP,,classic country;groovy;slow;alternative,7Jpclr7tZ6aQXjoKzWXUJV
A77: =IF((Contemporary!D70<>""),(CONCATENATE(Contemporary!D70,",",Contemporary!E70,",",Contemporary!G70,",",Contemporary!H70,",",Contemporary!P70,",",Contemporary!Q70,",",Contemporary!R70,",",Contemporary!T70,",",Contemporary!W70,",",Contemporary!B70,",",SUBSTITUTE(B77,",","%2c"),",",IF(Contemporary!K70<>"",Contemporary!K70,CONCATENATE(Contemporary!H70,";",Contemporary!I70)),",",Spotify!A74)),"") -> Dear Future Husband,Meghan Trainor,2014,Pop,89,22,75,64,79,WIP,,jazz pop;dance;groovy;love;sweet,1zNXF2svmdlNxfS5XeNUgr
A78: =IF((Contemporary!#REF!<>""),(CONCATENATE(Contemporary!#REF!,",",Contemporary!#REF!,",",Contemporary!#REF!,",",Contemporary!#REF!,",",Contemporary!#REF!,",",Contemporary!#REF!,",",Contemporary!#REF!,",",Contemporary!#REF!,",",Contemporary!#REF!,",",Contemporary!#REF!,",",SUBSTITUTE(B78,",","%2c"),",",IF(Contemporary!#REF!<>"",Contemporary!#REF!,CONCATENATE(Contemporary!#REF!,";",Contemporary!#REF!)),",",Spotify!#REF!)),"") -> #REF!
A79: =IF((Contemporary!D71<>""),(CONCATENATE(Contemporary!D71,",",Contemporary!E71,",",Contemporary!G71,",",Contemporary!H71,",",Contemporary!P71,",",Contemporary!Q71,",",Contemporary!R71,",",Contemporary!T71,",",Contemporary!W71,",",Contemporary!B71,",",SUBSTITUTE(B79,",","%2c"),",",IF(Contemporary!K71<>"",Contemporary!K71,CONCATENATE(Contemporary!H71,";",Contemporary!I71)),",",Spotify!A75)),"") -> Die Die Die,Avett Brothers,2007,Folk,164,92,35,21,74,WIP,,britpop;madchester;alternative;groovy;acoustic,7ppPZa3TRUSGKaks9wH7VT
A80: =IF((Contemporary!D72<>""),(CONCATENATE(Contemporary!D72,",",Contemporary!E72,",",Contemporary!G72,",",Contemporary!H72,",",Contemporary!P72,",",Contemporary!Q72,",",Contemporary!R72,",",Contemporary!T72,",",Contemporary!W72,",",Contemporary!B72,",",SUBSTITUTE(B80,",","%2c"),",",IF(Contemporary!K72<>"",Contemporary!K72,CONCATENATE(Contemporary!H72,";",Contemporary!I72)),",",Spotify!A76)),"") -> Does Your Mother Know,ABBA,1979,Pop,156,76,56,64,2,,,classic rock;rock;glam rock;dance;fast;love;groovy;oldies;retro,43DHLzDkncpby82Po5jlOZ
A81: =IF((Contemporary!D73<>""),(CONCATENATE(Contemporary!D73,",",Contemporary!E73,",",Contemporary!G73,",",Contemporary!H73,",",Contemporary!P73,",",Contemporary!Q73,",",Contemporary!R73,",",Contemporary!T73,",",Contemporary!W73,",",Contemporary!B73,",",SUBSTITUTE(B81,",","%2c"),",",IF(Contemporary!K73<>"",Contemporary!K73,CONCATENATE(Contemporary!H73,";",Contemporary!I73)),",",Spotify!#REF!)),"") -> #REF!
A82: =IF((Contemporary!D74<>""),(CONCATENATE(Contemporary!D74,",",Contemporary!E74,",",Contemporary!G74,",",Contemporary!H74,",",Contemporary!P74,",",Contemporary!Q74,",",Contemporary!R74,",",Contemporary!T74,",",Contemporary!W74,",",Contemporary!B74,",",SUBSTITUTE(B82,",","%2c"),",",IF(Contemporary!K74<>"",Contemporary!K74,CONCATENATE(Contemporary!H74,";",Contemporary!I74)),",",Spotify!A77)),"") -> Don't Know Why,Norah Jones,2002,Pop,146,14,39,27,37,,,bluegrass;newgrass;folk;americana;groovy;slow;love,5Y5mqKOWd1wzqSqBeYaeO9
A83: =IF((Contemporary!#REF!<>""),(CONCATENATE(Contemporary!#REF!,",",Contemporary!#REF!,",",Contemporary!#REF!,",",Contemporary!#REF!,",",Contemporary!#REF!,",",Contemporary!#REF!,",",Contemporary!#REF!,",",Contemporary!#REF!,",",Contemporary!#REF!,",",Contemporary!#REF!,",",SUBSTITUTE(B83,",","%2c"),",",IF(Contemporary!#REF!<>"",Contemporary!#REF!,CONCATENATE(Contemporary!#REF!,";",Contemporary!#REF!)),",",Spotify!A78)),"") -> #REF!
A84: =IF((Contemporary!D75<>""),(CONCATENATE(Contemporary!D75,",",Contemporary!E75,",",Contemporary!G75,",",Contemporary!H75,",",Contemporary!P75,",",Contemporary!Q75,",",Contemporary!R75,",",Contemporary!T75,",",Contemporary!W75,",",Contemporary!B75,",",SUBSTITUTE(B84,",","%2c"),",",IF(Contemporary!K75<>"",Contemporary!K75,CONCATENATE(Contemporary!H75,";",Contemporary!I75)),",",Spotify!A79)),"") -> Don't Look Back In Anger,Oasis,1995,Pop,120,49,83,79,92,,,yacht rock;classic rock;soft rock;groovy;slow;alternative;acoustic,0ofHAoxe9vBkTCp2UQIavz
A85: =IF((Contemporary!D76<>""),(CONCATENATE(Contemporary!D76,",",Contemporary!E76,",",Contemporary!G76,",",Contemporary!H76,",",Contemporary!P76,",",Contemporary!Q76,",",Contemporary!R76,",",Contemporary!T76,",",Contemporary!W76,",",Contemporary!B76,",",SUBSTITUTE(B85,",","%2c"),",",IF(Contemporary!K76<>"",Contemporary!K76,CONCATENATE(Contemporary!H76,";",Contemporary!I76)),",",Spotify!A80)),"") -> Don't Stop Me Now,Queen,1979,Rock,91,79,65,67,82,,,nu metal;funk rock;alternative metal;alternative rock;dance;fast;love;groovy;oldies;retro,7nnWIPM5hwE3DaUBkvOIpy
A86: =IF((Contemporary!#REF!<>""),(CONCATENATE(Contemporary!#REF!,",",Contemporary!#REF!,",",Contemporary!#REF!,",",Contemporary!#REF!,",",Contemporary!#REF!,",",Contemporary!#REF!,",",Contemporary!#REF!,",",Contemporary!#REF!,",",Contemporary!#REF!,",",Contemporary!#REF!,",",SUBSTITUTE(B86,",","%2c"),",",IF(Contemporary!#REF!<>"",Contemporary!#REF!,CONCATENATE(Contemporary!#REF!,";",Contemporary!#REF!)),",",Spotify!A81)),"") -> #REF!
A87: =IF((Contemporary!D77<>""),(CONCATENATE(Contemporary!D77,",",Contemporary!E77,",",Contemporary!G77,",",Contemporary!H77,",",Contemporary!P77,",",Contemporary!Q77,",",Contemporary!R77,",",Contemporary!T77,",",Contemporary!W77,",",Contemporary!B77,",",SUBSTITUTE(B87,",","%2c"),",",IF(Contemporary!K77<>"",Contemporary!K77,CONCATENATE(Contemporary!H77,";",Contemporary!I77)),",",Spotify!A82)),"") -> Doubting Thomas,Nickel Creek,2005,Pop,187,65,23,31,0,WIP,,;,54JpZ7kVvW7VsMFj8FqY95
A88: =IF((Contemporary!D78<>""),(CONCATENATE(Contemporary!D78,",",Contemporary!E78,",",Contemporary!G78,",",Contemporary!H78,",",Contemporary!P78,",",Contemporary!Q78,",",Contemporary!R78,",",Contemporary!T78,",",Contemporary!W78,",",Contemporary!B78,",",SUBSTITUTE(B88,",","%2c"),",",IF(Contemporary!K78<>"",Contemporary!K78,CONCATENATE(Contemporary!H78,";",Contemporary!I78)),",",Spotify!A83)),"") -> Dream A Little Dream Of Me,Laura Fygi,2002,Jazz,139,68,64,84,52,WIP,,classic rock;psychedelic rock;love;slow;acoustic;jazz;sweet,5ylLypaOksxWd75YrGtx2N
A89: =IF((Contemporary!#REF!<>""),(CONCATENATE(Contemporary!#REF!,",",Contemporary!#REF!,",",Contemporary!#REF!,",",Contemporary!#REF!,",",Contemporary!#REF!,",",Contemporary!#REF!,",",Contemporary!#REF!,",",Contemporary!#REF!,",",Contemporary!#REF!,",",Contemporary!#REF!,",",SUBSTITUTE(B89,",","%2c"),",",IF(Contemporary!#REF!<>"",Contemporary!#REF!,CONCATENATE(Contemporary!#REF!,";",Contemporary!#REF!)),",",Spotify!A84)),"") -> #REF!
A90: =IF((Contemporary!D79<>""),(CONCATENATE(Contemporary!D79,",",Contemporary!E79,",",Contemporary!G79,",",Contemporary!H79,",",Contemporary!P79,",",Contemporary!Q79,",",Contemporary!R79,",",Contemporary!T79,",",Contemporary!W79,",",Contemporary!B79,",",SUBSTITUTE(B90,",","%2c"),",",IF(Contemporary!K79<>"",Contemporary!K79,CONCATENATE(Contemporary!H79,";",Contemporary!I79)),",",Spotify!A85)),"") -> Dreams,Fleetwood Mac,1977,Rock,117,46,82,71,0,,,;,7cBs6EjIeGQD28QMOC0F2X
A91: =IF((Contemporary!D80<>""),(CONCATENATE(Contemporary!D80,",",Contemporary!E80,",",Contemporary!G80,",",Contemporary!H80,",",Contemporary!P80,",",Contemporary!Q80,",",Contemporary!R80,",",Contemporary!T80,",",Contemporary!W80,",",Contemporary!B80,",",SUBSTITUTE(B91,",","%2c"),",",IF(Contemporary!K80<>"",Contemporary!K80,CONCATENATE(Contemporary!H80,";",Contemporary!I80)),",",Spotify!A86)),"") -> Drive,Incubus,2000,Rock,78,56,71,83,37,WIP,,;alternative;groovy;dance,13bJq2QpoHZEUrNWfHgOUu
A92: =IF((Contemporary!D81<>""),(CONCATENATE(Contemporary!D81,",",Contemporary!E81,",",Contemporary!G81,",",Contemporary!H81,",",Contemporary!P81,",",Contemporary!Q81,",",Contemporary!R81,",",Contemporary!T81,",",Contemporary!W81,",",Contemporary!B81,",",SUBSTITUTE(B92,",","%2c"),",",IF(Contemporary!K81<>"",Contemporary!K81,CONCATENATE(Contemporary!H81,";",Contemporary!I81)),",",Spotify!A87)),"") -> Dust in the Wind,Kansas,1978,Rock,123,69,69,49,72,WIP,,christmas;alternative;acoustic;oldies;retro;love,4T6HLdP6OcAtqC6tGnQelG
A93: =IF((Contemporary!D82<>""),(CONCATENATE(Contemporary!D82,",",Contemporary!E82,",",Contemporary!G82,",",Contemporary!H82,",",Contemporary!P82,",",Contemporary!Q82,",",Contemporary!R82,",",Contemporary!T82,",",Contemporary!W82,",",Contemporary!B82,",",SUBSTITUTE(B93,",","%2c"),",",IF(Contemporary!K82<>"",Contemporary!K82,CONCATENATE(Contemporary!H82,";",Contemporary!I82)),",",Spotify!A88)),"") -> Earth Angel,Penguins,1954,RnB,79,34,37,45,76,WIP,,soft rock;yacht rock;oldies;retro;love;slow;waltz,52VIdyKqp1pJRSyUQaxKUA
A94: =IF((Contemporary!D83<>""),(CONCATENATE(Contemporary!D83,",",Contemporary!E83,",",Contemporary!G83,",",Contemporary!H83,",",Contemporary!P83,",",Contemporary!Q83,",",Contemporary!R83,",",Contemporary!T83,",",Contemporary!W83,",",Contemporary!B83,",",SUBSTITUTE(B94,",","%2c"),",",IF(Contemporary!K83<>"",Contemporary!K83,CONCATENATE(Contemporary!H83,";",Contemporary!I83)),",",Spotify!A89)),"") -> Eight Days A Week,Beatles,1964,Rock,115,54,69,76,71,,,yacht rock;classic rock;soft rock;oldies;retro;love;dance;fast,1prZ0pr6XoRCxcrC3MCL0M
A95: =IF((Contemporary!#REF!<>""),(CONCATENATE(Contemporary!#REF!,",",Contemporary!#REF!,",",Contemporary!#REF!,",",Contemporary!#REF!,",",Contemporary!#REF!,",",Contemporary!#REF!,",",Contemporary!#REF!,",",Contemporary!#REF!,",",Contemporary!#REF!,",",Contemporary!#REF!,",",SUBSTITUTE(B95,",","%2c"),",",IF(Contemporary!#REF!<>"",Contemporary!#REF!,CONCATENATE(Contemporary!#REF!,";",Contemporary!#REF!)),",",Spotify!A90)),"") -> #REF!
A96: =IF((Contemporary!D84<>""),(CONCATENATE(Contemporary!D84,",",Contemporary!E84,",",Contemporary!G84,",",Contemporary!H84,",",Contemporary!P84,",",Contemporary!Q84,",",Contemporary!R84,",",Contemporary!T84,",",Contemporary!W84,",",Contemporary!B84,",",SUBSTITUTE(B96,",","%2c"),",",IF(Contemporary!K84<>"",Contemporary!K84,CONCATENATE(Contemporary!H84,";",Contemporary!I84)),",",Spotify!A91)),"") -> Escape (Pina Colada),Rupert Holmes,1979,Rock,96,50,92,55,1,,,;groovy;love;dance;oldies;retro,59eAcAyhYSLi5GKFrgHJzG
A97: =IF((Contemporary!D85<>""),(CONCATENATE(Contemporary!D85,",",Contemporary!E85,",",Contemporary!G85,",",Contemporary!H85,",",Contemporary!P85,",",Contemporary!Q85,",",Contemporary!R85,",",Contemporary!T85,",",Contemporary!W85,",",Contemporary!B85,",",SUBSTITUTE(B97,",","%2c"),",",IF(Contemporary!K85<>"",Contemporary!K85,CONCATENATE(Contemporary!H85,";",Contemporary!I85)),",",Spotify!A92)),"") -> Every Breath You Take,The Police,1983,Rock,82,43,50,23,51,,,folk;,0YOOXnCJihgyluizqhAcrz
A98: =IF((Contemporary!D86<>""),(CONCATENATE(Contemporary!D86,",",Contemporary!E86,",",Contemporary!G86,",",Contemporary!H86,",",Contemporary!P86,",",Contemporary!Q86,",",Contemporary!R86,",",Contemporary!T86,",",Contemporary!W86,",",Contemporary!B86,",",SUBSTITUTE(B98,",","%2c"),",",IF(Contemporary!K86<>"",Contemporary!K86,CONCATENATE(Contemporary!H86,";",Contemporary!I86)),",",Spotify!A93)),"") -> Every Little Thing She Does Is Magic,Eric Hutchinson,1981,Pop,108,26,46,50,44,,,;alternative;dance;fast;love,111i0gGDZQ3NbXdY2dbpet
A99: =IF((Contemporary!D87<>""),(CONCATENATE(Contemporary!D87,",",Contemporary!E87,",",Contemporary!G87,",",Contemporary!H87,",",Contemporary!P87,",",Contemporary!Q87,",",Contemporary!R87,",",Contemporary!T87,",",Contemporary!W87,",",Contemporary!B87,",",SUBSTITUTE(B99,",","%2c"),",",IF(Contemporary!K87<>"",Contemporary!K87,CONCATENATE(Contemporary!H87,";",Contemporary!I87)),",",Spotify!A94)),"") -> Everything,Michael Buble,2006,Pop,102,37,82,29,74,WIP,,singer-songwriter;groovy;dance,6Qb7gtV6Q4MnUjSbkFcopl
A100: =IF((Contemporary!#REF!<>""),(CONCATENATE(Contemporary!#REF!,",",Contemporary!#REF!,",",Contemporary!#REF!,",",Contemporary!#REF!,",",Contemporary!#REF!,",",Contemporary!#REF!,",",Contemporary!#REF!,",",Contemporary!#REF!,",",Contemporary!#REF!,",",Contemporary!#REF!,",",SUBSTITUTE(B100,",","%2c"),",",IF(Contemporary!#REF!<>"",Contemporary!#REF!,CONCATENATE(Contemporary!#REF!,";",Contemporary!#REF!)),",",Spotify!#REF!)),"") -> #REF!
A101: =IF((Contemporary!D88<>""),(CONCATENATE(Contemporary!D88,",",Contemporary!E88,",",Contemporary!G88,",",Contemporary!H88,",",Contemporary!P88,",",Contemporary!Q88,",",Contemporary!R88,",",Contemporary!T88,",",Contemporary!W88,",",Contemporary!B88,",",SUBSTITUTE(B101,",","%2c"),",",IF(Contemporary!K88<>"",Contemporary!K88,CONCATENATE(Contemporary!H88,";",Contemporary!I88)),",",Spotify!A95)),"") -> Everything I Own,Bread,1972,Rock,95,25,60,37,66,WIP,,indie folk;love;slow;oldies;retro,0eBryM7ePQH3Klt3jz8xZd
A102: =IF((Contemporary!D89<>""),(CONCATENATE(Contemporary!D89,",",Contemporary!E89,",",Contemporary!G89,",",Contemporary!H89,",",Contemporary!P89,",",Contemporary!Q89,",",Contemporary!R89,",",Contemporary!T89,",",Contemporary!W89,",",Contemporary!B89,",",SUBSTITUTE(B102,",","%2c"),",",IF(Contemporary!K89<>"",Contemporary!K89,CONCATENATE(Contemporary!H89,";",Contemporary!I89)),",",Spotify!A96)),"") -> Everywhere,Fleetwood Mac,1987,Rock,97,7,44,26,81,,,folk;folk rock;,6oMZhY0f1ReI6AJDDYfuSb
A103: =IF((Contemporary!D90<>""),(CONCATENATE(Contemporary!D90,",",Contemporary!E90,",",Contemporary!G90,",",Contemporary!H90,",",Contemporary!P90,",",Contemporary!Q90,",",Contemporary!R90,",",Contemporary!T90,",",Contemporary!W90,",",Contemporary!B90,",",SUBSTITUTE(B103,",","%2c"),",",IF(Contemporary!K90<>"",Contemporary!K90,CONCATENATE(Contemporary!H90,";",Contemporary!I90)),",",Spotify!A97)),"") -> Eye Of The Tiger,Survivor,1982,Rock,138,42,21,12,86,,,;groovy;dance;fast;oldies;retro,7LVHVU3tWfcxj5aiPFEW4Q
A104: =IF((Contemporary!D91<>""),(CONCATENATE(Contemporary!D91,",",Contemporary!E91,",",Contemporary!G91,",",Contemporary!H91,",",Contemporary!P91,",",Contemporary!Q91,",",Contemporary!R91,",",Contemporary!T91,",",Contemporary!W91,",",Contemporary!B91,",",SUBSTITUTE(B104,",","%2c"),",",IF(Contemporary!K91<>"",Contemporary!K91,CONCATENATE(Contemporary!H91,";",Contemporary!I91)),",",Spotify!A98)),"") -> Faith,George Michael,1987,Rock,118,68,71,65,14,WIP,,;groovy;dance;fast;oldies;retro;love,0yLdNVWF3Srea0uzk55zFn
A105: =IF((Contemporary!#REF!<>""),(CONCATENATE(Contemporary!#REF!,",",Contemporary!#REF!,",",Contemporary!#REF!,",",Contemporary!#REF!,",",Contemporary!#REF!,",",Contemporary!#REF!,",",Contemporary!#REF!,",",Contemporary!#REF!,",",Contemporary!#REF!,",",Contemporary!#REF!,",",SUBSTITUTE(B105,",","%2c"),",",IF(Contemporary!#REF!<>"",Contemporary!#REF!,CONCATENATE(Contemporary!#REF!,";",Contemporary!#REF!)),",",Spotify!A99)),"") -> #REF!
A106: =IF((Contemporary!D92<>""),(CONCATENATE(Contemporary!D92,",",Contemporary!E92,",",Contemporary!G92,",",Contemporary!H92,",",Contemporary!P92,",",Contemporary!Q92,",",Contemporary!R92,",",Contemporary!T92,",",Contemporary!W92,",",Contemporary!B92,",",SUBSTITUTE(B106,",","%2c"),",",IF(Contemporary!K92<>"",Contemporary!K92,CONCATENATE(Contemporary!H92,";",Contemporary!I92)),",",Spotify!A100)),"") -> Fare Thee Well (Dink's Song),Various,2002,Folk,105,59,82,92,75,WIP,,;acoustic;slow;alternative;folk,4KoecuyOpZaNFZ0UqVsllc
A107: =IF((Contemporary!D93<>""),(CONCATENATE(Contemporary!D93,",",Contemporary!E93,",",Contemporary!G93,",",Contemporary!H93,",",Contemporary!P93,",",Contemporary!Q93,",",Contemporary!R93,",",Contemporary!T93,",",Contemporary!W93,",",Contemporary!B93,",",SUBSTITUTE(B107,",","%2c"),",",IF(Contemporary!K93<>"",Contemporary!K93,CONCATENATE(Contemporary!H93,";",Contemporary!I93)),",",Spotify!A101)),"") -> Feels Like Home,Edwina Hayes,2009,Folk,99,52,65,82,81,WIP,,folk rock;country rock;slow;love,1qRA5BS78u3gME0loMl9AA
A108: =IF((Contemporary!D94<>""),(CONCATENATE(Contemporary!D94,",",Contemporary!E94,",",Contemporary!G94,",",Contemporary!H94,",",Contemporary!P94,",",Contemporary!Q94,",",Contemporary!R94,",",Contemporary!T94,",",Contemporary!W94,",",Contemporary!B94,",",SUBSTITUTE(B108,",","%2c"),",",IF(Contemporary!K94<>"",Contemporary!K94,CONCATENATE(Contemporary!H94,";",Contemporary!I94)),",",Spotify!A102)),"") -> Fifty Ways To Leave Your Lover,Paul Simon,1975,Rock,144,80,57,52,22,WIP,,;oldies;retro;love;groovy,2WSTUNo3ZtQLeOkp362tcB
A109: =IF((Contemporary!#REF!<>""),(CONCATENATE(Contemporary!#REF!,",",Contemporary!#REF!,",",Contemporary!#REF!,",",Contemporary!#REF!,",",Contemporary!#REF!,",",Contemporary!#REF!,",",Contemporary!#REF!,",",Contemporary!#REF!,",",Contemporary!#REF!,",",Contemporary!#REF!,",",SUBSTITUTE(B109,",","%2c"),",",IF(Contemporary!#REF!<>"",Contemporary!#REF!,CONCATENATE(Contemporary!#REF!,";",Contemporary!#REF!)),",",Spotify!A103)),"") -> #REF!
A110: =IF((Contemporary!D95<>""),(CONCATENATE(Contemporary!D95,",",Contemporary!E95,",",Contemporary!G95,",",Contemporary!H95,",",Contemporary!P95,",",Contemporary!Q95,",",Contemporary!R95,",",Contemporary!T95,",",Contemporary!W95,",",Contemporary!B95,",",SUBSTITUTE(B110,",","%2c"),",",IF(Contemporary!K95<>"",Contemporary!K95,CONCATENATE(Contemporary!H95,";",Contemporary!I95)),",",Spotify!A104)),"") -> First Day Of My Life,Bright Eyes,2005,Folk,100,88,62,78,82,WIP,,soft pop;alternative;acoustic;love;sweet,0afhq8XCExXpqazXczTSve
A111: =IF((Contemporary!D96<>""),(CONCATENATE(Contemporary!D96,",",Contemporary!E96,",",Contemporary!G96,",",Contemporary!H96,",",Contemporary!P96,",",Contemporary!Q96,",",Contemporary!R96,",",Contemporary!T96,",",Contemporary!W96,",",Contemporary!B96,",",SUBSTITUTE(B111,",","%2c"),",",IF(Contemporary!K96<>"",Contemporary!K96,CONCATENATE(Contemporary!H96,";",Contemporary!I96)),",",Spotify!A105)),"") -> Five Hundred Miles,Peter Paul and Mary,1962,Folk,176,80,63,91,84,,,;slow;love;acoustic;alternative;oldies;retro;waltz;folk,11mwFrKvLXCbcVGNxffGyP
A112: =IF((Contemporary!D97<>""),(CONCATENATE(Contemporary!D97,",",Contemporary!E97,",",Contemporary!G97,",",Contemporary!H97,",",Contemporary!P97,",",Contemporary!Q97,",",Contemporary!R97,",",Contemporary!T97,",",Contemporary!W97,",",Contemporary!B97,",",SUBSTITUTE(B112,",","%2c"),",",IF(Contemporary!K97<>"",Contemporary!K97,CONCATENATE(Contemporary!H97,";",Contemporary!I97)),",",Spotify!A106)),"") -> Fix You,Coldplay,2005,Rock,116,79,81,86,21,,,french house;electronic;electro;love;slow,5bDrb5U9wtV4tzeiVhw7kO
A113: =IF((Contemporary!#REF!<>""),(CONCATENATE(Contemporary!#REF!,",",Contemporary!#REF!,",",Contemporary!#REF!,",",Contemporary!#REF!,",",Contemporary!#REF!,",",Contemporary!#REF!,",",Contemporary!#REF!,",",Contemporary!#REF!,",",Contemporary!#REF!,",",Contemporary!#REF!,",",SUBSTITUTE(B113,",","%2c"),",",IF(Contemporary!#REF!<>"",Contemporary!#REF!,CONCATENATE(Contemporary!#REF!,";",Contemporary!#REF!)),",",Spotify!A107)),"") -> #REF!
A114: =IF((Contemporary!D98<>""),(CONCATENATE(Contemporary!D98,",",Contemporary!E98,",",Contemporary!G98,",",Contemporary!H98,",",Contemporary!P98,",",Contemporary!Q98,",",Contemporary!R98,",",Contemporary!T98,",",Contemporary!W98,",",Contemporary!B98,",",SUBSTITUTE(B114,",","%2c"),",",IF(Contemporary!K98<>"",Contemporary!K98,CONCATENATE(Contemporary!H98,";",Contemporary!I98)),",",Spotify!A108)),"") -> Flowers,Miley Cyrus,2023,Pop,186,36,44,36,51,,,acoustic pop;love;dance;groovy;fast,7rohDMzsbmSmol7sIZs0Px
A115: =IF((Contemporary!D99<>""),(CONCATENATE(Contemporary!D99,",",Contemporary!E99,",",Contemporary!G99,",",Contemporary!H99,",",Contemporary!P99,",",Contemporary!Q99,",",Contemporary!R99,",",Contemporary!T99,",",Contemporary!W99,",",Contemporary!B99,",",SUBSTITUTE(B115,",","%2c"),",",IF(Contemporary!K99<>"",Contemporary!K99,CONCATENATE(Contemporary!H99,";",Contemporary!I99)),",",Spotify!A109)),"") -> Fly Me To The Moon,Frank Sinatra,1954,Pop,118,82,75,94,44,,,pop;jazz;love;groovy;dance;oldies;retro,2TRuBFYZYw0Q7qIVBhqR1T
A116: =IF((Contemporary!D100<>""),(CONCATENATE(Contemporary!D100,",",Contemporary!E100,",",Contemporary!G100,",",Contemporary!H100,",",Contemporary!P100,",",Contemporary!Q100,",",Contemporary!R100,",",Contemporary!T100,",",Contemporary!W100,",",Contemporary!B100,",",SUBSTITUTE(B116,",","%2c"),",",IF(Contemporary!K100<>"",Contemporary!K100,CONCATENATE(Contemporary!H100,";",Contemporary!I100)),",",Spotify!#REF!)),"") -> #REF!
A117: =IF((Contemporary!D101<>""),(CONCATENATE(Contemporary!D101,",",Contemporary!E101,",",Contemporary!G101,",",Contemporary!H101,",",Contemporary!P101,",",Contemporary!Q101,",",Contemporary!R101,",",Contemporary!T101,",",Contemporary!W101,",",Contemporary!B101,",",SUBSTITUTE(B117,",","%2c"),",",IF(Contemporary!K101<>"",Contemporary!K101,CONCATENATE(Contemporary!H101,";",Contemporary!I101)),",",Spotify!A110)),"") -> For What It's Worth,Buffalo Springfield,1966,Folk,95,43,48,65,82,WIP,,punk;pop punk;alternative;groovy;dance;oldies;retro;folk;slow,6ORqU0bHbVCRjXm9AjyHyZ
A118: =IF((Contemporary!D102<>""),(CONCATENATE(Contemporary!D102,",",Contemporary!E102,",",Contemporary!G102,",",Contemporary!H102,",",Contemporary!P102,",",Contemporary!Q102,",",Contemporary!R102,",",Contemporary!T102,",",Contemporary!W102,",",Contemporary!B102,",",SUBSTITUTE(B118,",","%2c"),",",IF(Contemporary!K102<>"",Contemporary!K102,CONCATENATE(Contemporary!H102,";",Contemporary!I102)),",",Spotify!A111)),"") -> Forever,Eric Hutchinson,2014,Rock,118,63,68,60,23,WIP,,;love;dance;fast,0zzSZkEfZiZCAldZj8x128
A119: =IF((Contemporary!D103<>""),(CONCATENATE(Contemporary!D103,",",Contemporary!E103,",",Contemporary!G103,",",Contemporary!H103,",",Contemporary!P103,",",Contemporary!Q103,",",Contemporary!R103,",",Contemporary!T103,",",Contemporary!W103,",",Contemporary!B103,",",SUBSTITUTE(B119,",","%2c"),",",IF(Contemporary!K103<>"",Contemporary!K103,CONCATENATE(Contemporary!H103,";",Contemporary!I103)),",",Spotify!A112)),"") -> Free Falling,John Mayer,1989,Rock,127,37,59,63,57,,,christmas;big band;adult standards;swing music;jazz;vocal jazz;alternative;acoustic;oldies;retro;love,74jklVKHYTmNMp0baGm6FB
A120: =IF((Contemporary!D104<>""),(CONCATENATE(Contemporary!D104,",",Contemporary!E104,",",Contemporary!G104,",",Contemporary!H104,",",Contemporary!P104,",",Contemporary!Q104,",",Contemporary!R104,",",Contemporary!T104,",",Contemporary!W104,",",Contemporary!B104,",",SUBSTITUTE(B120,",","%2c"),",",IF(Contemporary!K104<>"",Contemporary!K104,CONCATENATE(Contemporary!H104,";",Contemporary!I104)),",",Spotify!A113)),"") -> Galway Girl,Ed Sheeran,2017,Pop,83,31,54,32,0,WIP,,;alternative;dance;fast;love,6HhRhNhizv18kTfHED0GNA
A121: =IF((Contemporary!D105<>""),(CONCATENATE(Contemporary!D105,",",Contemporary!E105,",",Contemporary!G105,",",Contemporary!H105,",",Contemporary!P105,",",Contemporary!Q105,",",Contemporary!R105,",",Contemporary!T105,",",Contemporary!W105,",",Contemporary!B105,",",SUBSTITUTE(B121,",","%2c"),",",IF(Contemporary!K105<>"",Contemporary!K105,CONCATENATE(Contemporary!H105,";",Contemporary!I105)),",",Spotify!A114)),"") -> Genie In A Bottle,Christina Aguilera,1999,Pop,80,63,59,91,0,WIP,,rockabilly;rock and roll;boogie-woogie;love;dance;fast;groovy,7xe3EQCvXnx6Q0zs41Y65n
A122: =IF((Contemporary!D106<>""),(CONCATENATE(Contemporary!D106,",",Contemporary!E106,",",Contemporary!G106,",",Contemporary!H106,",",Contemporary!P106,",",Contemporary!Q106,",",Contemporary!R106,",",Contemporary!T106,",",Contemporary!W106,",",Contemporary!B106,",",SUBSTITUTE(B122,",","%2c"),",",IF(Contemporary!K106<>"",Contemporary!K106,CONCATENATE(Contemporary!H106,";",Contemporary!I106)),",",Spotify!A115)),"") -> Get Lucky,Daft Punk,2013,Disco,130,41,61,23,68,WIP,,;,3ou9rSNUQnE7XYmJkUUIOc
A123: =IF((Contemporary!D107<>""),(CONCATENATE(Contemporary!D107,",",Contemporary!E107,",",Contemporary!G107,",",Contemporary!H107,",",Contemporary!P107,",",Contemporary!Q107,",",Contemporary!R107,",",Contemporary!T107,",",Contemporary!W107,",",Contemporary!B107,",",SUBSTITUTE(B123,",","%2c"),",",IF(Contemporary!K107<>"",Contemporary!K107,CONCATENATE(Contemporary!H107,";",Contemporary!I107)),",",Spotify!A116)),"") -> Gimme Gimme Gimme,ABBA,1979,Pop,143,51,55,51,69,,,soft rock;yacht rock;retro;oldies;dance;groovy;love,0gZXockVcE7rEhSf4mcGLO
A124: =IF((Contemporary!D108<>""),(CONCATENATE(Contemporary!D108,",",Contemporary!E108,",",Contemporary!G108,",",Contemporary!H108,",",Contemporary!P108,",",Contemporary!Q108,",",Contemporary!R108,",",Contemporary!T108,",",Contemporary!W108,",",Contemporary!B108,",",SUBSTITUTE(B124,",","%2c"),",",IF(Contemporary!K108<>"",Contemporary!K108,CONCATENATE(Contemporary!H108,";",Contemporary!I108)),",",Spotify!A117)),"") -> Girls Just Want To Have Fun,Mayries,1983,Pop,73,20,34,44,61,WIP,,singer-songwriter;acoustic;alternative;love;retro;oldies,5USZyz6dnBEn1oLsKcAKQy
A125: =IF((Contemporary!D109<>""),(CONCATENATE(Contemporary!D109,",",Contemporary!E109,",",Contemporary!G109,",",Contemporary!H109,",",Contemporary!P109,",",Contemporary!Q109,",",Contemporary!R109,",",Contemporary!T109,",",Contemporary!W109,",",Contemporary!B109,",",SUBSTITUTE(B125,",","%2c"),",",IF(Contemporary!K109<>"",Contemporary!K109,CONCATENATE(Contemporary!H109,";",Contemporary!I109)),",",Spotify!A118)),"") -> Give A Little More,Maroon 5,2010,Disco,80,72,51,47,76,WIP,,;alternative;dance;fast;love,4JehYebiI9JE8sR8MisGVb
A126: =IF((Contemporary!#REF!<>""),(CONCATENATE(Contemporary!#REF!,",",Contemporary!#REF!,",",Contemporary!#REF!,",",Contemporary!#REF!,",",Contemporary!#REF!,",",Contemporary!#REF!,",",Contemporary!#REF!,",",Contemporary!#REF!,",",Contemporary!#REF!,",",Contemporary!#REF!,",",SUBSTITUTE(B126,",","%2c"),",",IF(Contemporary!#REF!<>"",Contemporary!#REF!,CONCATENATE(Contemporary!#REF!,";",Contemporary!#REF!)),",",Spotify!A119)),"") -> #REF!
A127: =IF((Contemporary!D110<>""),(CONCATENATE(Contemporary!D110,",",Contemporary!E110,",",Contemporary!G110,",",Contemporary!H110,",",Contemporary!P110,",",Contemporary!Q110,",",Contemporary!R110,",",Contemporary!T110,",",Contemporary!W110,",",Contemporary!B110,",",SUBSTITUTE(B127,",","%2c"),",",IF(Contemporary!K110<>"",Contemporary!K110,CONCATENATE(Contemporary!H110,";",Contemporary!I110)),",",Spotify!A120)),"") -> Good Riddance (Time Of Your Life),Green Day,1997,Rock,113,31,65,41,63,WIP,,classic rock;folk rock;singer-songwriter;roots rock;alternative;acoustic,7sCHy8QQUz3CRvUMp53Cbm
A128: =IF((Contemporary!D111<>""),(CONCATENATE(Contemporary!D111,",",Contemporary!E111,",",Contemporary!G111,",",Contemporary!H111,",",Contemporary!P111,",",Contemporary!Q111,",",Contemporary!R111,",",Contemporary!T111,",",Contemporary!W111,",",Contemporary!B111,",",SUBSTITUTE(B128,",","%2c"),",",IF(Contemporary!K111<>"",Contemporary!K111,CONCATENATE(Contemporary!H111,";",Contemporary!I111)),",",Spotify!A121)),"") -> Goodnight Goodbye,Eric Hutchinson,2014,Rock,106,50,75,44,0,WIP,,;acoustic;love;dance;groovy,4ptonNXwbPtpiPX062ruaM
A129: =IF((Contemporary!D112<>""),(CONCATENATE(Contemporary!D112,",",Contemporary!E112,",",Contemporary!G112,",",Contemporary!H112,",",Contemporary!P112,",",Contemporary!Q112,",",Contemporary!R112,",",Contemporary!T112,",",Contemporary!W112,",",Contemporary!B112,",",SUBSTITUTE(B129,",","%2c"),",",IF(Contemporary!K112<>"",Contemporary!K112,CONCATENATE(Contemporary!H112,";",Contemporary!I112)),",",Spotify!A122)),"") -> Got You Under My Skin,Frank Sinatra,1956,Pop,116,47,74,89,70,WIP,,classic rock;southern rock;country rock;jazz;love;groovy;dance;oldies;retro,5DnT9a5IM3eMjKgXTWVJvi
A130: =IF((Contemporary!D113<>""),(CONCATENATE(Contemporary!D113,",",Contemporary!E113,",",Contemporary!G113,",",Contemporary!H113,",",Contemporary!P113,",",Contemporary!Q113,",",Contemporary!R113,",",Contemporary!T113,",",Contemporary!W113,",",Contemporary!B113,",",SUBSTITUTE(B130,",","%2c"),",",IF(Contemporary!K113<>"",Contemporary!K113,CONCATENATE(Contemporary!H113,";",Contemporary!I113)),",",Spotify!A123)),"") -> Grayscale,Skye Zentz,2012,Folk,171,40,54,83,77,WIP,,classic rock;folk rock;singer-songwriter;roots rock;acoustic;alternative;love;sweet;folk;waltz,26QKxvjlCo2fSd3T4c8Zpb
A131: =IF((Contemporary!D114<>""),(CONCATENATE(Contemporary!D114,",",Contemporary!E114,",",Contemporary!G114,",",Contemporary!H114,",",Contemporary!P114,",",Contemporary!Q114,",",Contemporary!R114,",",Contemporary!T114,",",Contemporary!W114,",",Contemporary!B114,",",SUBSTITUTE(B131,",","%2c"),",",IF(Contemporary!K114<>"",Contemporary!K114,CONCATENATE(Contemporary!H114,";",Contemporary!I114)),",",Spotify!A124)),"") -> Great Balls Of Fire,Jerry Lee Lewis,1957,Rock 'n' roll,140,59,38,33,85,WIP,,;groovy;fast;dance;love;oldies;retro,7Ewz6bJ97vUqk5HdkvguFQ
...

Sheet Spotify
A1: Spotify ID | B1: Track Name | C1: Album Name | D1: Artist Name(s) | E1: Release Date | F1: Duration (ms) | G1: Popularity | H1: Added By | I1: Added At | J1: Genres | K1: Danceability | L1: Energy | M1: Key | N1: Loudness | O1: Mode | P1: Speechiness | Q1: Acousticness | R1: Instrumentalness | S1: Liveness | T1: Valence | U1: Tempo | V1: Time Signature
A3: 1BV0m40U0M4t1SLIsDnwZl | B3: 1973 | C3: All the Lost Souls | D3: James Blunt | E3: 39330 | F3: 280026 | G3: 75 | H3: 125771062 | I3: 2022-09-20T14:38:56Z | K3: 0.72 | L3: 0.668 | M3: 9 | N3: -7.928 | O3: 1 | P3: 0.0269 | Q3: 0.0653 | R3: 0.00675 | S3: 0.0789 | T3: 0.769 | U3: 123.005 | V3: 4
A4: 1pctwlBtIcKIjQMzsVcGHB | B4: A Hard Day's Night - Remastered 2015 | C4: 1 (Remastered) | D4: The Beatles | E4: 36843 | F4: 152920 | G4: 54 | H4: 125771062 | I4: 2023-07-23T10:24:47Z | J4: classic rock,psychedelic rock | K4: 0.546 | L4: 0.818 | M4: 0 | N4: -4.89 | O4: 1 | P4: 0.031 | Q4: 0.0487 | R4: 0 | S4: 0.0983 | T4: 0.756 | U4: 138.561 | V4: 4
A5: 47y8hRlWLEJ4VafE6LMjEZ | B5: A Little Less Conversation | C5: The Essential Elvis Presley | D5: Elvis Presley | E5: 2007 | F5: 121584 | G5: 56 | H5: 125771062 | I5: 2022-10-01T17:44:33Z | J5: rockabilly,rock and roll | K5: 0.584 | L5: 0.802 | M5: 2 | N5: -8.03 | O5: 1 | P5: 0.0784 | Q5: 0.149 | R5: 0 | S5: 0.0683 | T5: 0.835 | U5: 114.172 | V5: 4
A6: 3AH12fVi34vJVqriMpM6Bo | B6: A Little More | C6: Pure Fiction | D6: Eric Hutchinson | E6: 41737 | F6: 196600 | G6: 44 | H6: 125771062 | I6: 2022-09-20T14:38:56Z | K6: 0.643 | L6: 0.741 | M6: 2 | N6: -5.084 | O6: 1 | P6: 0.0404 | Q6: 0.013 | R6: 2.34e-05 | S6: 0.0711 | T6: 0.935 | U6: 80.043 | V6: 4
A7: 3RIm56NRLSZYo1xgHlbPH4 | B7: Zimmer: A Man For All Seasons | C7: Johnny English - Original Motion Picture Soundtrack | D7: Hans Zimmer;Robbie Williams | E7: 37622 | F7: 239760 | G7: 42 | H7: 125771062 | I7: 2022-09-20T14:38:56Z | J7: soundtrack,score | K7: 0.583 | L7: 0.744 | M7: 2 | N7: -8.36 | O7: 0 | P7: 0.0318 | Q7: 0.0091 | R7: 0 | S7: 0.272 | T7: 0.818 | U7: 123.901 | V7: 4
A8: 0FDzzruyVECATHXKHFs9eJ | B8: A Sky Full of Stars | C8: Ghost Stories | D8: Coldplay | E8: 41775 | F8: 267866 | G8: 88 | H8: 125771062 | I8: 2024-02-21T16:47:29Z | K8: 0.545 | L8: 0.675 | M8: 6 | N8: -6.474 | O8: 1 | P8: 0.0279 | Q8: 0.00617 | R8: 0.00197 | S8: 0.209 | T8: 0.162 | U8: 124.97 | V8: 4
A9: 4w1lzcaoZ1IC2K5TwjalRP | B9: A Thousand Miles | C9: Be Not Nobody | D9: Vanessa Carlton | E9: 37376 | F9: 237493 | G9: 83 | H9: 125771062 | I9: 2022-09-20T14:38:56Z | K9: 0.56 | L9: 0.825 | M9: 11 | N9: -3.862 | O9: 1 | P9: 0.0379 | Q9: 0.323 | R9: 0 | S9: 0.161 | T9: 0.268 | U9: 94.931 | V9: 4
A10: 6lanRgr6wXibZr8KgzXxBl | B10: a thousand years | C10: a thousand years | D10: Christina Perri | E10: 40834 | F10: 285120 | G10: 86 | H10: 125771062 | I10: 2022-09-20T14:38:56Z | J10: soft pop | K10: 0.421 | L10: 0.407 | M10: 10 | N10: -7.445 | O10: 1 | P10: 0.0267 | Q10: 0.309 | R10: 0.000961 | S10: 0.11 | T10: 0.161 | U10: 139.028 | V10: 3
A11: 69uxyAqqPIsUyTO8txoP2M | B11: Adventure of a Lifetime | C11: A Head Full of Dreams | D11: Coldplay | E11: 42342 | F11: 263786 | G11: 88 | H11: 125771062 | I11: 2022-09-20T14:38:56Z | K11: 0.638 | L11: 0.924 | M11: 7 | N11: -3.887 | O11: 1 | P11: 0.036 | Q11: 0.00205 | R11: 0.000175 | S11: 0.149 | T11: 0.53 | U11: 111.995 | V11: 4
A12: 2374M0fQpWi3dLnB54qaLX | B12: Africa | C12: Toto IV | D12: TOTO | E12: 30049 | F12: 295282 | G12: 90 | H12: 125771062 | I12: 2022-09-20T14:38:56Z | J12: yacht rock,soft rock | K12: 0.671 | L12: 0.373 | M12: 9 | N12: -18.064 | O12: 1 | P12: 0.0323 | Q12: 0.257 | R12: 8.01e-05 | S12: 0.0481 | T12: 0.732 | U12: 92.718 | V12: 4
A13: 1PC5GV3OaoXx5em8ttQOMI | B13: After Midnight | C13: Naturally | D13: J.J. Cale | E13: 1972 | F13: 143693 | G13: 62 | H13: 125771062 | I13: 2022-09-20T14:38:56Z | J13: blues,roots rock,blues rock | K13: 0.694 | L13: 0.306 | M13: 2 | N13: -19.315 | O13: 1 | P13: 0.0353 | Q13: 0.171 | R13: 0.0736 | S13: 0.0866 | T13: 0.521 | U13: 95.989 | V13: 4
A14: 7mze3mJmu79AJu8SnS37pS | B14: Aicha | C14: Bread & Barrels Of Water (International Version) | D14: Outlandish | E14: 37712 | F14: 275680 | G14: 58 | H14: 125771062 | I14: 2024-02-21T16:47:38Z | J14: dansk pop | K14: 0.745 | L14: 0.64 | M14: 2 | N14: -5.494 | O14: 1 | P14: 0.0526 | Q14: 0.21 | R14: 5.3e-05 | S14: 0.112 | T14: 0.612 | U14: 86.98 | V14: 4
A15: 5jE48hhRu8E6zBDPRSkEq7 | B15: All About That Bass | C15: Title (Deluxe) | D15: Meghan Trainor | E15: 42016 | F15: 191488 | G15: 71 | H15: 125771062 | I15: 2022-09-20T14:38:56Z | K15: 0.807 | L15: 0.887 | M15: 9 | N15: -3.726 | O15: 1 | P15: 0.0503 | Q15: 0.0573 | R15: 2.87e-06 | S15: 0.124 | T15: 0.961 | U15: 134.052 | V15: 4
A16: 0ElmwRAsaxaUZXnMbaSllH | B16: All About You | C16: Wonderland | D16: McFly | E16: 38353 | F16: 186866 | G16: 59 | H16: 125771062 | I16: 2022-09-20T14:38:56Z | K16: 0.542 | L16: 0.559 | M16: 1 | N16: -5.313 | O16: 1 | P16: 0.0258 | Q16: 0.197 | R16: 0 | S16: 0.0989 | T16: 0.295 | U16: 129.898 | V16: 4
A17: 7dblNGnRXEBrVJunazs2U5 | B17: All I Have to Do Is Dream | C17: The Very Best of The Everly Brothers | D17: The Everly Brothers | E17: 23590 | F17: 143333 | G17: 70 | H17: 125771062 | I17: 2022-09-20T14:38:56Z | J17: doo-wop | K17: 0.534 | L17: 0.462 | M17: 4 | N17: -8.172 | O17: 1 | P17: 0.0266 | Q17: 0.839 | R17: 0 | S17: 0.129 | T17: 0.534 | U17: 96.195 | V17: 4
A18: 3cfOd4CMv2snFaKAnMdnvK | B18: All Star | C18: Astro Lounge | D18: Smash Mouth | E18: 36319 | F18: 200373 | G18: 82 | H18: 125771062 | I18: 2022-09-20T14:38:56Z | K18: 0.731 | L18: 0.867 | M18: 11 | N18: -5.881 | O18: 1 | P18: 0.032 | Q18: 0.0394 | R18: 0 | S18: 0.0861 | T18: 0.776 | U18: 104.02 | V18: 4
A19: 11y8GSP2ASv8S9n0FiiDva | B19: Angel Of The Morning | C19: Juice | D19: Juice Newton | E19: 29587 | F19: 250440 | G19: 68 | H19: 125771062 | I19: 2022-09-20T14:38:56Z | K19: 0.452 | L19: 0.313 | M19: 8 | N19: -9.309 | O19: 1 | P19: 0.026 | Q19: 0.433 | R19: 2.6e-05 | S19: 0.0772 | T19: 0.344 | U19: 75.806 | V19: 4
A20: 7CKbqqrs0AS1si1ZgaQdcj | B20: Angels | C20: Angels | D20: Robbie Williams | E20: 35431 | F20: 265333 | G20: 65 | H20: 125771062 | I20: 2022-09-20T14:38:56Z | K20: 0.431 | L20: 0.59 | M20: 4 | N20: -6.362 | O20: 1 | P20: 0.0284 | Q20: 0.163 | R20: 1.11e-05 | S20: 0.0981 | T20: 0.257 | U20: 150.193 | V20: 4
A21: 4J0DbyODwZJcmIAiTSJfMF | B21: Annie's Song | C21: Back Home Again | D21: John Denver | E21: 27195 | F21: 180693 | G21: 71 | H21: 125771062 | I21: 2022-09-20T14:38:56Z | J21: folk | K21: 0.304 | L21: 0.305 | M21: 2 | N21: -10.879 | O21: 1 | P21: 0.0298 | Q21: 0.871 | R21: 0.00368 | S21: 0.367 | T21: 0.464 | U21: 146.066 | V21: 3
A22: 1NCuYqMc8hKMb4cpNTcJbD | B22: Another Day in Paradise - 2016 Remaster | C22: ...But Seriously (Deluxe Edition) | D22: Phil Collins | E22: 32832 | F22: 322133 | G22: 84 | H22: 125771062 | I22: 2023-07-22T06:50:19Z | J22: soft rock | K22: 0.78 | L22: 0.565 | M22: 3 | N22: -7.32 | O22: 0 | P22: 0.0306 | Q22: 0.736 | R22: 0.00269 | S22: 0.063 | T22: 0.365 | U22: 101.967 | V22: 4
A23: 3NKzaAQXoHXhXqMHN9IsRb | B23: Answer Me, My Love | C23: For You | D23: Inger Marie Gundersen | E23: 40847 | F23: 229245 | G23: 18 | H23: 125771062 | I23: 2025-03-13T01:48:02Z | J23: vocal jazz,smooth jazz,jazz pop | K23: 0.627 | L23: 0.0819 | M23: 5 | N23: -27.517 | O23: 1 | P23: 0.0366 | Q23: 0.769 | R23: 0.0283 | S23: 0.113 | T23: 0.369 | U23: 88.638 | V23: 4
A24: 51FAWuc1iPdM06S65Plx11 | B24: Antonio's Song | C24: That Summer | D24: Till Brönner | E24: 38145 | F24: 299520 | G24: 27 | H24: 125771062 | I24: 2022-09-23T09:11:25Z | J24: smooth jazz,jazz | K24: 0.676 | L24: 0.389 | M24: 10 | N24: -14.082 | O24: 1 | P24: 0.0281 | Q24: 0.461 | R24: 0.432 | S24: 0.179 | T24: 0.646 | U24: 114.024 | V24: 4
A25: 1j9HwUMSkRUeVFRWlHcFsy | B25: Ave Maria | C25: I AM...SASHA FIERCE | D25: Beyoncé | E25: 39766 | F25: 221653 | G25: 48 | H25: 125771062 | I25: 2022-09-20T14:38:57Z | K25: 0.35 | L25: 0.403 | M25: 0 | N25: -9.57 | O25: 1 | P25: 0.0279 | Q25: 0.786 | R25: 0 | S25: 0.12 | T25: 0.201 | U25: 104.957 | V25: 3
A26: 3MjUtNVVq3C8Fn0MP3zhXa | B26: ...Baby One More Time | C26: ...Baby One More Time (Digital Deluxe Version) | D26: Britney Spears | E26: 36172 | F26: 211066 | G26: 86 | H26: 125771062 | I26: 2022-09-20T14:38:57Z | J26: pop | K26: 0.759 | L26: 0.699 | M26: 0 | N26: -5.745 | O26: 0 | P26: 0.0307 | Q26: 0.202 | R26: 0.000131 | S26: 0.443 | T26: 0.907 | U26: 92.96 | V26: 4
A27: 5AmekBD8x9RIu9MMX81aYz | B27: Beautiful Tango - Remastered | C27: Handmade (Remastered) | D27: Hindi Zahra | E27: 40578 | F27: 236866 | G27: 19 | H27: 125771062 | I27: 2022-09-23T09:12:53Z | J27: tango | K27: 0.745 | L27: 0.376 | M27: 6 | N27: -9.521 | O27: 0 | P27: 0.0541 | Q27: 0.975 | R27: 0.0478 | S27: 0.128 | T27: 0.654 | U27: 126.212 | V27: 4
A28: 0pqnGHJpmpxLKifKRmU6WP | B28: Believer | C28: Evolve | D28: Imagine Dragons | E28: 42909 | F28: 204346 | G28: 88 | H28: 125771062 | I28: 2023-03-27T14:35:21Z | K28: 0.776 | L28: 0.78 | M28: 10 | N28: -4.374 | O28: 0 | P28: 0.128 | Q28: 0.0622 | R28: 0 | S28: 0.081 | T28: 0.666 | U28: 124.949 | V28: 4
A29: 5WHnE8MsLFHqSUwecrs7WO | B29: Bésame Mucho | C29: Amor (Edición Especial En Español) | D29: Andrea Bocelli | E29: 38718 | F29: 241232 | G29: 65 | H29: 125771062 | I29: 2022-09-20T14:38:57Z | J29: classical crossover,opera | K29: 0.521 | L29: 0.502 | M29: 5 | N29: -8.521 | O29: 0 | P29: 0.0287 | Q29: 0.886 | R29: 0.02 | S29: 0.188 | T29: 0.378 | U29: 95.028 | V29: 4
A30: 0BMyRHOFOvHjAEzeNfQIeN | B30: Better When I'm Dancin' | C30: The Peanuts Movie - Original Motion Picture Soundtrack | D30: Meghan Trainor | E30: 42516 | F30: 176266 | G30: 56 | H30: 125771062 | I30: 2022-09-20T14:38:57Z | K30: 0.756 | L30: 0.789 | M30: 2 | N30: -7.002 | O30: 1 | P30: 0.0324 | Q30: 0.53 | R30: 0.000711 | S30: 0.157 | T30: 0.873 | U30: 127.987 | V30: 4
A31: 1wfzOH54LylpiG8hAOjKcS | B31: Big Yellow Taxi | C31: 100 Greatest Summer Songs | D31: Joni Mitchell | E31: 43560 | F31: 134800 | G31: 46 | H31: 125771062 | I31: 2023-02-12T10:29:03Z | J31: folk,folk rock,singer-songwriter | K31: 0.611 | L31: 0.47 | M31: 4 | N31: -9.135 | O31: 1 | P31: 0.0356 | Q31: 0.585 | R31: 0 | S31: 0.58 | T31: 0.97 | U31: 85.527 | V31: 4
A32: 5ChkMS8OtdzJeqyybCc9R5 | B32: Billie Jean | C32: Thriller 25 Super Deluxe Edition | D32: Michael Jackson | E32: 39486 | F32: 293826 | G32: 82 | H32: 125771062 | I32: 2024-02-24T05:36:52Z | K32: 0.92 | L32: 0.654 | M32: 11 | N32: -3.051 | O32: 0 | P32: 0.0401 | Q32: 0.0236 | R32: 0.0153 | S32: 0.036 | T32: 0.847 | U32: 117.046 | V32: 4
A33: 08T5wMbEnPN8ghT8o24KY6 | B33: Bistro Fada | C33: Bistro Fada | D33: Stephane Wrembel | E33: 40676 | F33: 182933 | G33: 52 | H33: 125771062 | I33: 2022-09-20T14:38:57Z | J33: french jazz | K33: 0.761 | L33: 0.371 | M33: 4 | N33: -10.908 | O33: 0 | P33: 0.0403 | Q33: 0.892 | R33: 0.853 | S33: 0.0791 | T33: 0.864 | U33: 98.989 | V33: 3
A34: 57iDDD9N9tTWe75x6qhStw | B34: Bitter Sweet Symphony - Remastered 2016 | C34: Urban Hymns (Remastered 2016) | D34: The Verve | E34: 35702 | F34: 357266 | G34: 87 | H34: 125771062 | I34: 2023-02-15T17:10:29Z | J34: britpop,shoegaze | K34: 0.356 | L34: 0.917 | M34: 9 | N34: -6.006 | O34: 1 | P34: 0.0479 | Q34: 0.0335 | R34: 0 | S34: 0.406 | T34: 0.518 | U34: 171.176 | V34: 4
A35: 6wdviVWctiZnY6tVn6bh6A | B35: Black or White - Single Version | C35: Number Ones | D35: Michael Jackson | E35: 37942 | F35: 200060 | G35: 68 | H35: 125771062 | I35: 2025-09-19T07:29:05Z | K35: 0.759 | L35: 0.927 | M35: 9 | N35: -2.768 | O35: 1 | P35: 0.051 | Q35: 0.11 | R35: 0.029 | S35: 0.374 | T35: 0.96 | U35: 115.075 | V35: 4
A36: 5jgFfDIR6FR0gvlA56Nakr | B36: Blackbird - Remastered 2009 | C36: The Beatles (Remastered) | D36: The Beatles | E36: 25164 | F36: 138386 | G36: 80 | H36: 125771062 | I36: 2024-08-25T02:13:39Z | J36: classic rock,psychedelic rock | K36: 0.686 | L36: 0.127 | M36: 7 | N36: -14.361 | O36: 1 | P36: 0.0342 | Q36: 0.754 | R36: 1.41e-05 | S36: 0.0573 | T36: 0.372 | U36: 93.699 | V36: 4
A37: 0VjIjW4GlUZAMYd2vXMi3b | B37: Blinding Lights | C37: After Hours | D37: The Weeknd | E37: 43910 | F37: 200040 | G37: 90 | H37: 125771062 | I37: 2022-09-20T14:38:57Z | K37: 0.513 | L37: 0.73 | M37: 1 | N37: -5.94 | O37: 1 | P37: 0.0598 | Q37: 0.00143 | R37: 9.54e-05 | S37: 0.0897 | T37: 0.334 | U37: 171.001 | V37: 4
A38: 62Yu8QL1g9pdbvN4XL9Rah | B38: Blowin' in the Wind | C38: In the Wind | D38: Peter, Paul and Mary | E38: 1963 | F38: 177360 | G38: 60 | H38: 125771062 | I38: 2022-09-20T14:38:57Z | J38: folk,folk rock | K38: 0.381 | L38: 0.0848 | M38: 5 | N38: -17.77 | O38: 1 | P38: 0.032 | Q38: 0.834 | R38: 0 | S38: 0.112 | T38: 0.557 | U38: 155.036 | V38: 4
A39: 2BY7ALEWdloFHgQZG6VMLA | B39: Brandy (You're a Fine Girl) | C39: Looking Glass | D39: Looking Glass | E39: 1972 | F39: 189044 | G39: 78 | H39: 125771062 | I39: 2022-09-20T14:38:57Z | J39: yacht rock | K39: 0.716 | L39: 0.625 | M39: 1 | N39: -11.369 | O39: 0 | P39: 0.0601 | Q39: 0.396 | R39: 1.97e-05 | S39: 0.134 | T39: 0.826 | U39: 125.276 | V39: 4
A40: 6MTrtNdft6F4t64fEzhNNA | B40: Brasileirinho | C40: Obrigado Brazil (Remastered) | D40: Waldir Azevedo;Yo-Yo Ma;Romero Lubambo;Cyro Baptista;Jose De Faria;José Da Silva;Helio Alves;Nilson Matta;Paquito D'Rivera | E40: 2003 | F40: 205426 | G40: 33 | H40: 125771062 | I40: 2022-09-20T14:38:57Z | J40: samba,seresta,classical,chamber music,brazilian jazz,bossa nova,latin jazz,afro-cuban jazz,big band,jazz | K40: 0.492 | L40: 0.521 | M40: 5 | N40: -13.08 | O40: 1 | P40: 0.0635 | Q40: 0.35 | R40: 0.77 | S40: 0.0797 | T40: 0.92 | U40: 105.03 | V40: 3
A41: 1uzWOoJdADfstQuFtQFTUn | B41: Breakfast At Tiffany's | C41: Home | D41: Deep Blue Something | E41: 34700 | F41: 257373 | G41: 73 | H41: 125771062 | I41: 2022-09-20T14:38:57Z | K41: 0.622 | L41: 0.829 | M41: 2 | N41: -5.548 | O41: 1 | P41: 0.029 | Q41: 0.11 | R41: 0 | S41: 0.0954 | T41: 0.539 | U41: 110.367 | V41: 4
A42: 5auMzVHFr5Zfw6IbKarZ56 | B42: Breathe (2 AM) | C42: Wreck of the Day | D42: Anna Nalick | E42: 2005 | F42: 279826 | G42: 66 | H42: 125771062 | I42: 2023-10-22T03:01:10Z | K42: 0.386 | L42: 0.452 | M42: 2 | N42: -7.715 | O42: 1 | P42: 0.0278 | Q42: 0.417 | R42: 0 | S42: 0.0881 | T42: 0.287 | U42: 169.837 | V42: 3
A43: 3yrSvpt2l1xhsV9Em88Pul | B43: Brown Eyed Girl | C43: Blowin' Your Mind! | D43: Van Morrison | E43: 1967-09 | F43: 183306 | G43: 19 | H43: 125771062 | I43: 2022-09-20T14:38:57Z | K43: 0.491 | L43: 0.583 | M43: 7 | N43: -10.964 | O43: 1 | P43: 0.0376 | Q43: 0.185 | R43: 0 | S43: 0.406 | T43: 0.908 | U43: 150.566 | V43: 4
A44: 2ixsaeFioXJmMgkkbd4uj1 | B44: Budapest | C44: Wanted on Voyage (Expanded Edition) | D44: George Ezra | E44: 41820 | F44: 200573 | G44: 83 | H44: 125771062 | I44: 2022-09-20T14:38:57Z | K44: 0.717 | L44: 0.455 | M44: 5 | N44: -8.303 | O44: 1 | P44: 0.0276 | Q44: 0.0846 | R44: 0 | S44: 0.11 | T44: 0.389 | U44: 127.812 | V44: 4
A45: 7rrmHHc1kY9vkIZnXrcH7T | B45: Butterfly | C45: We Sing. We Dance. We Steal Things. | D45: Jason Mraz | E45: 39580 | F45: 299066 | G45: 46 | H45: 125771062 | I45: 2022-09-20T14:38:57Z | J45: soft pop,acoustic pop | K45: 0.718 | L45: 0.658 | M45: 10 | N45: -7.207 | O45: 0 | P45: 0.0664 | Q45: 0.146 | R45: 0 | S45: 0.202 | T45: 0.804 | U45: 108.103 | V45: 4
A46: 6oRHRkQigTzJ3KwpO3XOV6 | B46: Bye Bye Love | C46: The Very Best of The Everly Brothers | D46: The Everly Brothers | E46: 23590 | F46: 142906 | G46: 54 | H46: 125771062 | I46: 2022-09-20T14:38:57Z | J46: doo-wop | K46: 0.547 | L46: 0.523 | M46: 9 | N46: -9.176 | O46: 1 | P46: 0.0572 | Q46: 0.724 | R46: 0 | S46: 0.103 | T46: 0.89 | U46: 169.598 | V46: 4
A47: 7Gpx2fNJiilvrf9Ss8qbit | B47: Calendar Girl | C47: Rock with Sedaka (Expanded Edition) | D47: Neil Sedaka | E47: 21713 | F47: 159693 | G47: 57 | H47: 125771062 | I47: 2022-09-20T14:38:57Z | J47: doo-wop,adult standards | K47: 0.703 | L47: 0.649 | M47: 8 | N47: -7.727 | O47: 0 | P47: 0.0312 | Q47: 0.397 | R47: 0 | S47: 0.209 | T47: 0.862 | U47: 122.719 | V47: 4
A48: 48UPSzbZjgc449aqz8bxox | B48: Californication | C48: Californication (Deluxe Edition) | D48: Red Hot Chili Peppers | E48: 36319 | F48: 329733 | G48: 88 | H48: 125771062 | I48: 2022-09-20T14:38:57Z | J48: funk rock,alternative rock,rock | K48: 0.592 | L48: 0.767 | M48: 9 | N48: -2.788 | O48: 0 | P48: 0.027 | Q48: 0.0021 | R48: 0.00165 | S48: 0.127 | T48: 0.328 | U48: 96.483 | V48: 4
A49: 44AyOl4qVkzS48vBsbNXaC | B49: Can't Help Falling in Love | C49: Blue Hawaii | D49: Elvis Presley | E49: 22574 | F49: 185877 | G49: 83 | H49: 125771062 | I49: 2022-09-20T14:38:57Z | J49: rockabilly,rock and roll | K49: 0.396 | L49: 0.293 | M49: 2 | N49: -14.062 | O49: 1 | P49: 0.0275 | Q49: 0.941 | R49: 0.000196 | S49: 0.105 | T49: 0.343 | U49: 100.307 | V49: 3
A50: 7qUTZEf6bgiApJEXpMAH5y | B50: Can't Smile Without You | C50: Even Now | D50: Barry Manilow | E50: 1978 | F50: 193440 | G50: 65 | H50: 125771062 | I50: 2022-10-13T06:27:22Z | J50: yacht rock,adult standards | K50: 0.419 | L50: 0.516 | M50: 7 | N50: -9.937 | O50: 1 | P50: 0.0335 | Q50: 0.494 | R50: 4.41e-06 | S50: 0.148 | T50: 0.476 | U50: 97.884 | V50: 4
A51: 4jDmJ51x1o9NZB5Nxxc7gY | B51: Careless Whisper | C51: Ladies And Gentlemen... The Best Of George Michael | D51: George Michael | E51: 36108 | F51: 300106 | G51: 8 | H51: 125771062 | I51: 2022-09-20T14:38:57Z | K51: 0.574 | L51: 0.628 | M51: 2 | N51: -8.815 | O51: 0 | P51: 0.036 | Q51: 0.13 | R51: 0 | S51: 0.271 | T51: 0.803 | U51: 153.119 | V51: 4
A52: 1zVBU0PAj7ZUVmVfG2pgQG | B52: Carry You Home | C52: All the Lost Souls | D52: James Blunt | E52: 39330 | F52: 234786 | G52: 65 | H52: 125771062 | I52: 2022-09-20T14:38:57Z | K52: 0.344 | L52: 0.549 | M52: 2 | N52: -7.194 | O52: 1 | P52: 0.037 | Q52: 0.7 | R52: 1.16e-06 | S52: 0.101 | T52: 0.206 | U52: 83.046 | V52: 4
A53: 29MwtMspIroR2wFYEJ7ps0 | B53: Catch & Release | C53: Catch & Release | D53: Matt Simons | E53: 42265 | F53: 240466 | G53: 52 | H53: 125771062 | I53: 2022-09-20T14:38:57Z | K53: 0.62 | L53: 0.447 | M53: 1 | N53: -9.383 | O53: 0 | P53: 0.147 | Q53: 0.815 | R53: 0.000216 | S53: 0.111 | T53: 0.612 | U53: 86.647 | V53: 4
A54: 7qvxFz3JodM0A7xEM7k3YD | B54: Chained To The Rhythm | C54: Witness (Deluxe) | D54: Katy Perry;Skip Marley | E54: 42895 | F54: 237733 | G54: 73 | H54: 125771062 | I54: 2022-09-20T14:38:57Z | J54: pop,reggae | K54: 0.562 | L54: 0.8 | M54: 0 | N54: -5.404 | O54: 1 | P54: 0.112 | Q54: 0.0814 | R54: 0 | S54: 0.199 | T54: 0.471 | U54: 95.029 | V54: 4
A55: 3S4px9f4lceWdKf0gWciFu | B55: Cheap Thrills | C55: This Is Acting (Deluxe Version) | D55: Sia | E55: 42664 | F55: 211666 | G55: 72 | H55: 125771062 | I55: 2022-09-20T14:38:57Z | K55: 0.628 | L55: 0.698 | M55: 6 | N55: -5.608 | O55: 0 | P55: 0.105 | Q55: 0.0472 | R55: 0.00143 | S55: 0.0907 | T55: 0.732 | U55: 89.976 | V55: 4
A56: 762B4bOcXF7I2Y8UlKTyTy | B56: Chiquitita | C56: Voulez-Vous | D56: ABBA | E56: 1979 | F56: 326320 | G56: 78 | H56: 125771062 | I56: 2022-09-20T14:38:57Z | K56: 0.5 | L56: 0.554 | M56: 9 | N56: -8.108 | O56: 1 | P56: 0.0354 | Q56: 0.734 | R56: 3.72e-06 | S56: 0.312 | T56: 0.372 | U56: 84.229 | V56: 4
A57: 0BCPKOYdS2jbQ8iyB56Zns | B57: Clocks | C57: A Rush of Blood to the Head | D57: Coldplay | E57: 37495 | F57: 307879 | G57: 87 | H57: 125771062 | I57: 2022-09-20T14:38:57Z | K57: 0.577 | L57: 0.749 | M57: 5 | N57: -7.215 | O57: 0 | P57: 0.0279 | Q57: 0.599 | R57: 0.0115 | S57: 0.183 | T57: 0.255 | U57: 130.97 | V57: 4
A58: 1A5V1sxyCLpKJezp75tUXn | B58: Closing Time | C58: 20th Century Masters: The Millennium Collection: Best Of Semisonic | D58: Semisonic | E58: 37622 | F58: 274160 | G58: 70 | H58: 125771062 | I58: 2022-09-20T14:38:57Z | K58: 0.478 | L58: 0.854 | M58: 7 | N58: -5.454 | O58: 1 | P58: 0.0289 | Q58: 0.0204 | R58: 1.21e-06 | S58: 0.115 | T58: 0.274 | U58: 91.854 | V58: 4
A59: 1sdz3nsrkX4Yo42KLPrmYV | B59: Cloud Number Nine | C59: On A Day Like Today | D59: Bryan Adams | E59: 35796 | F59: 225573 | G59: 53 | H59: 125771062 | I59: 2022-09-20T14:38:57Z | K59: 0.59 | L59: 0.72 | M59: 2 | N59: -7.127 | O59: 1 | P59: 0.0263 | Q59: 0.0641 | R59: 0 | S59: 0.183 | T59: 0.617 | U59: 109.644 | V59: 4
A60: 3hWOGUIOcqKDoVpFBLp9Qc | B60: Copacabana (At the Copa) | C60: The Greatest Songs Of The Seventies | D60: Barry Manilow | E60: 39335 | F60: 241346 | G60: 50 | H60: 125771062 | I60: 2022-09-23T08:18:23Z | J60: yacht rock,adult standards | K60: 0.763 | L60: 0.665 | M60: 9 | N60: -7.914 | O60: 0 | P60: 0.0444 | Q60: 0.542 | R60: 3.28e-05 | S60: 0.0972 | T60: 0.803 | U60: 108.035 | V60: 4
A61: 7l1qvxWjxcKpB9PCtBuTbU | B61: Count on Me | C61: Doo-Wops & Hooligans | D61: Bruno Mars | E61: 40309 | F61: 197469 | G61: 81 | H61: 125771062 | I61: 2022-09-20T14:38:57Z | K61: 0.589 | L61: 0.389 | M61: 0 | N61: -5.972 | O61: 1 | P61: 0.028 | Q61: 0.851 | R61: 0 | S61: 0.0772 | T61: 0.501 | U61: 89.1 | V61: 4
A62: 6sy3LkhNFjJWlaeSMNwQ62 | B62: Counting Stars | C62: Native | D62: OneRepublic | E62: 41640 | F62: 257840 | G62: 74 | H62: 125771062 | I62: 2024-02-27T02:16:57Z | J62: soft pop | K62: 0.663 | L62: 0.706 | M62: 1 | N62: -4.972 | O62: 0 | P62: 0.0383 | Q62: 0.0654 | R62: 0 | S62: 0.115 | T62: 0.474 | U62: 122.013 | V62: 4
A63: 1YYhDizHx7PnDhAhko6cDS | B63: Take Me Home, Country Roads - Original Version | C63: Poems, Prayers and Promises | D63: John Denver | E63: 1971 | F63: 193937 | G63: 79 | H63: 125771062 | I63: 2022-09-20T14:38:57Z | J63: folk | K63: 0.462 | L63: 0.395 | M63: 9 | N63: -9.376 | O63: 1 | P63: 0.0264 | Q63: 0.758 | R63: 0 | S63: 0.121 | T63: 0.625 | U63: 82.259 | V63: 4
A64: 2N5zMZX7YeL1tico8oQxa9 | B64: Crazy | C64: St. Elsewhere | D64: Gnarls Barkley | E64: 38839 | F64: 182066 | G64: 4 | H64: 125771062 | I64: 2022-09-20T14:38:57Z | K64: 0.836 | L64: 0.741 | M64: 8 | N64: -1.609 | O64: 1 | P64: 0.0339 | Q64: 0.0172 | R64: 0.0583 | S64: 0.0826 | T64: 0.611 | U64: 111.963 | V64: 4
A65: 2NpKgRCZfFb8fVmvk16iMx | B65: Crazy Little Thing Called Love | C65: The Game | D65: Queen | E65: 29399 | F65: 163426 | G65: 0 | H65: 125771062 | I65: 2022-09-20T14:38:57Z | J65: classic rock,rock,glam rock | K65: 0.626 | L65: 0.57 | M65: 0 | N65: -13.453 | O65: 1 | P65: 0.0421 | Q65: 0.499 | R65: 0 | S65: 0.147 | T65: 0.745 | U65: 76.826 | V65: 4
A66: 1FSWSs9CL01RCYxXtm08Rf | B66: Dance with Me Tonight | C66: In Case You Didn't Know | D66: Olly Murs | E66: 40875 | F66: 202226 | G66: 67 | H66: 125771062 | I66: 2022-09-20T14:38:57Z | K66: 0.672 | L66: 0.748 | M66: 11 | N66: -5.922 | O66: 0 | P66: 0.0589 | Q66: 0.305 | R66: 0 | S66: 0.0811 | T66: 0.964 | U66: 163.984 | V66: 4
A67: 3Fzlg5r1IjhLk2qRw667od | B67: Dancing in the Moonlight | C67: Onka's Big Moka | D67: Toploader | E67: 2000 | F67: 232693 | G67: 80 | H67: 125771062 | I67: 2022-09-20T14:38:57Z | K67: 0.632 | L67: 0.856 | M67: 10 | N67: -3.463 | O67: 1 | P67: 0.0348 | Q67: 0.0624 | R67: 0 | S67: 0.347 | T67: 0.867 | U67: 119.397 | V67: 4
A68: 0GjEhVFGZW8afUYGChu3Rr | B68: Dancing Queen | C68: Arrival | D68: ABBA | E68: 1976 | F68: 230400 | G68: 87 | H68: 125771062 | I68: 2022-09-20T14:38:57Z | K68: 0.543 | L68: 0.87 | M68: 9 | N68: -6.514 | O68: 1 | P68: 0.0428 | Q68: 0.358 | R68: 0.000939 | S68: 0.792 | T68: 0.754 | U68: 100.804 | V68: 4
A69: 5FPnjikbwlDMULCCCa6ZCJ | B69: Daughters | C69: Heavier Things | D69: John Mayer | E69: 37873 | F69: 239320 | G69: 67 | H69: 125771062 | I69: 2022-09-20T14:38:57Z | J69: singer-songwriter | K69: 0.674 | L69: 0.413 | M69: 2 | N69: -7.816 | O69: 1 | P69: 0.0274 | Q69: 0.836 | R69: 1.95e-05 | S69: 0.098 | T69: 0.503 | U69: 124.893 | V69: 3
A70: 3cU2wBxuV6nFiuf6PJZNlC | B70: Dear Future Husband | C70: Title (Deluxe) | D70: Meghan Trainor | E70: 42016 | F70: 184214 | G70: 70 | H70: 125771062 | I70: 2022-09-20T14:38:58Z | K70: 0.655 | L70: 0.782 | M70: 1 | N70: -4.789 | O70: 1 | P70: 0.185 | Q70: 0.375 | R70: 0 | S70: 0.317 | T70: 0.832 | U70: 79.427 | V70: 4
A71: 2HK5MzOuCmkJQlJYGCQpUU | B71: Die Die Die | C71: Emotionalism (Bonus Track Version) | D71: The Avett Brothers | E71: 39217 | F71: 170866 | G71: 36 | H71: 125771062 | I71: 2022-09-20T14:38:58Z | J71: indie folk,folk,newgrass,americana,bluegrass,alt country,folk rock | K71: 0.531 | L71: 0.702 | M71: 8 | N71: -5.309 | O71: 1 | P71: 0.0303 | Q71: 0.132 | R71: 0 | S71: 0.105 | T71: 0.767 | U71: 118.794 | V71: 4
A72: 2HPB3px8MJZRMfu1L65Z41 | B72: Does Your Mother Know | C72: Voulez-Vous | D72: ABBA | E72: 1979 | F72: 193440 | G72: 69 | H72: 125771062 | I72: 2022-09-20T14:38:58Z | K72: 0.728 | L72: 0.865 | M72: 7 | N72: -5.68 | O72: 1 | P72: 0.0364 | Q72: 0.151 | R72: 2.43e-05 | S72: 0.0906 | T72: 0.975 | U72: 135.571 | V72: 4
A73: 7Jpclr7tZ6aQXjoKzWXUJV | B73: Don't It Make My Brown Eyes Blue | C73: We Must Believe In Magic | D73: Crystal Gayle | E73: 28126 | F73: 157653 | G73: 61 | H73: 125771062 | I73: 2022-09-20T14:38:58Z | J73: classic country | K73: 0.736 | L73: 0.321 | M73: 6 | N73: -13.474 | O73: 1 | P73: 0.0444 | Q73: 0.799 | R73: 0.00897 | S73: 0.0619 | T73: 0.342 | U73: 84.928 | V73: 4
A74: 1zNXF2svmdlNxfS5XeNUgr | B74: Don't Know Why | C74: Come Away With Me (Super Deluxe Edition) | D74: Norah Jones | E74: 37313 | F74: 186251 | G74: 79 | H74: 125771062 | I74: 2022-09-20T14:38:58Z | J74: jazz pop | K74: 0.745 | L74: 0.219 | M74: 5 | N74: -11.216 | O74: 1 | P74: 0.0276 | Q74: 0.851 | R74: 1.8e-05 | S74: 0.0678 | T74: 0.635 | U74: 88.609 | V74: 4
A75: 7ppPZa3TRUSGKaks9wH7VT | B75: Don't Look Back In Anger | C75: (What's The Story) Morning Glory? | D75: Oasis | E75: 34974 | F75: 287826 | G75: 74 | H75: 125771062 | I75: 2022-09-20T14:38:58Z | J75: britpop,madchester | K75: 0.349 | L75: 0.917 | M75: 0 | N75: -3.645 | O75: 1 | P75: 0.071 | Q75: 0.026 | R75: 7.25e-06 | S75: 0.0968 | T75: 0.206 | U75: 164.036 | V75: 4
A76: 43DHLzDkncpby82Po5jlOZ | B76: Don't Stop Me Now | C76: Jazz | D76: Queen | E76: 28804 | F76: 209560 | G76: 2 | H76: 125771062 | I76: 2022-09-20T14:38:58Z | J76: classic rock,rock,glam rock | K76: 0.562 | L76: 0.757 | M76: 5 | N76: -10.061 | O76: 1 | P76: 0.192 | Q76: 0.0563 | R76: 0.00128 | S76: 0.558 | T76: 0.64 | U76: 156.435 | V76: 4
A77: 5Y5mqKOWd1wzqSqBeYaeO9 | B77: Doubting Thomas | C77: Why Should The Fire Die? | D77: Nickel Creek | E77: 38353 | F77: 199106 | G77: 37 | H77: 125771062 | I77: 2022-09-20T14:38:58Z | J77: bluegrass,newgrass,folk,americana | K77: 0.392 | L77: 0.14 | M77: 1 | N77: -14.873 | O77: 1 | P77: 0.0305 | Q77: 0.905 | R77: 6.95e-05 | S77: 0.119 | T77: 0.274 | U77: 145.595 | V77: 4
A78: 5vVLUqs9ogEGnH44Lh8Tuc | B78: Dream A Little Dream | C78: Introducing | D78: Laura Fygi | E78: 33239 | F78: 217573 | G78: 58 | H78: 125771062 | I78: 2022-09-20T14:49:38Z | J78: french jazz,vocal jazz,jazz,smooth jazz | K78: 0.651 | L78: 0.221 | M78: 0 | N78: -15.223 | O78: 1 | P78: 0.0273 | Q78: 0.847 | R78: 1.11e-06 | S78: 0.0895 | T78: 0.319 | U78: 88.17 | V78: 4
A79: 0ofHAoxe9vBkTCp2UQIavz | B79: Dreams - 2004 Remaster | C79: Rumours (Super Deluxe) | D79: Fleetwood Mac | E79: 28160 | F79: 257800 | G79: 92 | H79: 125771062 | I79: 2025-09-19T07:28:54Z | J79: yacht rock,classic rock,soft rock | K79: 0.828 | L79: 0.492 | M79: 0 | N79: -9.744 | O79: 1 | P79: 0.0276 | Q79: 0.0644 | R79: 0.00428 | S79: 0.128 | T79: 0.789 | U79: 120.151 | V79: 4
A80: 7nnWIPM5hwE3DaUBkvOIpy | B80: Drive | C80: Make Yourself | D80: Incubus | E80: 36459 | F80: 232453 | G80: 82 | H80: 125771062 | I80: 2022-09-20T14:38:58Z | J80: nu metal,funk rock,alternative metal,alternative rock | K80: 0.645 | L80: 0.792 | M80: 4 | N80: -7.34 | O80: 0 | P80: 0.036 | Q80: 0.0562 | R80: 0.0121 | S80: 0.119 | T80: 0.666 | U80: 90.565 | V80: 4
A81: 6zeE5tKyr8Nu882DQhhSQI | B81: Dust in the Wind | C81: Point Of Know Return (Expanded Edition) | D81: Kansas | E81: 1977 | F81: 206266 | G81: 81 | H81: 125771062 | I81: 2022-09-20T14:38:58Z | J81: classic rock,progressive rock,aor | K81: 0.475 | L81: 0.322 | M81: 7 | N81: -10.687 | O81: 1 | P81: 0.0283 | Q81: 0.367 | R81: 0.00056 | S81: 0.11 | T81: 0.387 | U81: 93.503 | V81: 4
A82: 54JpZ7kVvW7VsMFj8FqY95 | B82: Earth Angel | C82: Stubbs The Zombie: The Soundtrack | D82: Death Cab for Cutie | E82: 38353 | F82: 196453 | G82: 0 | H82: 125771062 | I82: 2022-09-20T14:38:58Z | K82: 0.233 | L82: 0.645 | M82: 8 | N82: -5.456 | O82: 1 | P82: 0.0334 | Q82: 0.237 | R82: 2.39e-05 | S82: 0.378 | T82: 0.31 | U82: 187.281 | V82: 3
A83: 5ylLypaOksxWd75YrGtx2N | B83: Eight Days A Week - Remastered 2015 | C83: 1 (Remastered) | D83: The Beatles | E83: 36843 | F83: 163320 | G83: 52 | H83: 125771062 | I83: 2022-11-30T04:08:59Z | J83: classic rock,psychedelic rock | K83: 0.636 | L83: 0.677 | M83: 9 | N83: -5.605 | O83: 1 | P83: 0.0316 | Q83: 0.265 | R83: 0 | S83: 0.215 | T83: 0.837 | U83: 138.707 | V83: 4
A84: 5IMtdHjJ1OtkxbGe4zfUxQ | B84: Escape (The Pina Colada Song) | C84: Partners In Crime | D84: Rupert Holmes | E84: 28856 | F84: 276493 | G84: 78 | H84: 125771062 | I84: 2022-09-20T14:38:58Z | J84: yacht rock | K84: 0.835 | L84: 0.509 | M84: 0 | N84: -13.668 | O84: 1 | P84: 0.0548 | Q84: 0.469 | R84: 4.11e-06 | S84: 0.0436 | T84: 0.949 | U84: 138.711 | V84: 4
A85: 7cBs6EjIeGQD28QMOC0F2X | B85: Every Breath You Take | C85: The Best 80s Love Songs Album In The World...Ever! | D85: The Police | E85: 44765 | F85: 251760 | G85: 0 | H85: 125771062 | I85: 2024-02-28T04:28:52Z | K85: 0.823 | L85: 0.457 | M85: 1 | N85: -9.722 | O85: 1 | P85: 0.035 | Q85: 0.537 | R85: 0.00488 | S85: 0.0698 | T85: 0.709 | U85: 117.392 | V85: 4
A86: 13bJq2QpoHZEUrNWfHgOUu | B86: Every Little Thing She Does Is Magic - Live | C86: Almost Solo in NYC (Live) | D86: Eric Hutchinson | E86: 41919 | F86: 174532 | G86: 37 | H86: 125771062 | I86: 2022-09-20T14:38:58Z | K86: 0.71 | L86: 0.561 | M86: 0 | N86: -4.974 | O86: 1 | P86: 0.0507 | Q86: 0.43 | R86: 0 | S86: 0.692 | T86: 0.827 | U86: 78.275 | V86: 4
A87: 4T6HLdP6OcAtqC6tGnQelG | B87: Everything | C87: Call Me Irresponsible | D87: Michael Bublé | E87: 39199 | F87: 212373 | G87: 72 | H87: 125771062 | I87: 2022-09-20T14:38:58Z | J87: christmas | K87: 0.686 | L87: 0.688 | M87: 6 | N87: -4.981 | O87: 0 | P87: 0.0254 | Q87: 0.39 | R87: 1.03e-06 | S87: 0.0924 | T87: 0.493 | U87: 123.125 | V87: 4
A88: 52VIdyKqp1pJRSyUQaxKUA | B88: Everything I Own | C88: Baby I'm-a Want You | D88: Bread | E88: 1972 | F88: 187000 | G88: 76 | H88: 125771062 | I88: 2022-09-20T14:38:58Z | J88: soft rock,yacht rock | K88: 0.365 | L88: 0.338 | M88: 2 | N88: -13.406 | O88: 1 | P88: 0.0322 | Q88: 0.735 | R88: 0 | S88: 0.104 | T88: 0.446 | U88: 79.241 | V88: 4
A89: 1prZ0pr6XoRCxcrC3MCL0M | B89: Everywhere | C89: Greatest Hits | D89: Fleetwood Mac | E89: 32468 | F89: 222733 | G89: 71 | H89: 125771062 | I89: 2023-12-26T16:41:33Z | J89: yacht rock,classic rock,soft rock | K89: 0.69 | L89: 0.54 | M89: 4 | N89: -10.516 | O89: 1 | P89: 0.0317 | Q89: 0.218 | R89: 0.00657 | S89: 0.115 | T89: 0.764 | U89: 114.846 | V89: 4
A90: 2KH16WveTQWT6KOG9Rg6e2 | B90: Eye of the Tiger | C90: Rocky IV | D90: Survivor | E90: 1985 | F90: 245640 | G90: 79 | H90: 125771062 | I90: 2022-09-20T14:38:58Z | K90: 0.817 | L90: 0.599 | M90: 0 | N90: -9.249 | O90: 0 | P90: 0.0328 | Q90: 0.132 | R90: 0.000311 | S90: 0.0873 | T90: 0.548 | U90: 108.873 | V90: 4
A91: 59eAcAyhYSLi5GKFrgHJzG | B91: Faith | C91: Ladies And Gentlemen... The Best Of George Michael | D91: George Michael | E91: 36108 | F91: 194493 | G91: 1 | H91: 125771062 | I91: 2022-09-20T14:38:58Z | K91: 0.915 | L91: 0.497 | M91: 11 | N91: -10.435 | O91: 1 | P91: 0.102 | Q91: 0.00547 | R91: 0.000108 | S91: 0.067 | T91: 0.553 | U91: 95.852 | V91: 4
A92: 0YOOXnCJihgyluizqhAcrz | B92: Fare Thee Well (Dink's Song) | C92: Inside Llewyn Davis: Original Soundtrack Recording | D92: Oscar Isaac;Marcus Mumford | E92: 41684 | F92: 180400 | G92: 51 | H92: 125771062 | I92: 2022-09-23T09:19:55Z | J92: folk | K92: 0.495 | L92: 0.434 | M92: 2 | N92: -8.079 | O92: 1 | P92: 0.0313 | Q92: 0.897 | R92: 0.000393 | S92: 0.109 | T92: 0.23 | U92: 82.16 | V92: 4
A93: 111i0gGDZQ3NbXdY2dbpet | B93: Feels Like Home | C93: Pour Me a Drink | D93: Edwina Hayes | E93: 39908 | F93: 254746 | G93: 44 | H93: 125771062 | I93: 2022-09-20T14:38:58Z | K93: 0.456 | L93: 0.255 | M93: 3 | N93: -9.152 | O93: 1 | P93: 0.0309 | Q93: 0.869 | R93: 0 | S93: 0.109 | T93: 0.502 | U93: 108.303 | V93: 4
A94: 6Qb7gtV6Q4MnUjSbkFcopl | B94: 50 Ways to Leave Your Lover | C94: Still Crazy After All These Years | D94: Paul Simon | E94: 27692 | F94: 217573 | G94: 74 | H94: 125771062 | I94: 2022-09-20T14:51:10Z | J94: singer-songwriter | K94: 0.815 | L94: 0.372 | M94: 7 | N94: -12.814 | O94: 1 | P94: 0.0752 | Q94: 0.166 | R94: 0.000116 | S94: 0.0767 | T94: 0.293 | U94: 101.684 | V94: 4
A95: 0eBryM7ePQH3Klt3jz8xZd | B95: First Day of My Life | C95: I'm Wide Awake, It's Morning | D95: Bright Eyes | E95: 38377 | F95: 188877 | G95: 66 | H95: 125771062 | I95: 2022-09-20T14:38:58Z | J95: indie folk | K95: 0.596 | L95: 0.253 | M95: 1 | N95: -14.369 | O95: 0 | P95: 0.0349 | Q95: 0.896 | R95: 5.17e-05 | S95: 0.102 | T95: 0.368 | U95: 95.162 | V95: 4
A96: 6oMZhY0f1ReI6AJDDYfuSb | B96: 500 Miles | C96: Peter, Paul and Mary | D96: Peter, Paul and Mary | E96: 22767 | F96: 162933 | G96: 81 | H96: 125771062 | I96: 2022-09-20T14:38:58Z | J96: folk,folk rock | K96: 0.436 | L96: 0.0695 | M96: 7 | N96: -19.735 | O96: 1 | P96: 0.0298 | Q96: 0.858 | R96: 0 | S96: 0.107 | T96: 0.255 | U96: 97.128 | V96: 4
A97: 7LVHVU3tWfcxj5aiPFEW4Q | B97: Fix You | C97: X&Y | D97: Coldplay | E97: 38510 | F97: 295533 | G97: 86 | H97: 125771062 | I97: 2022-09-20T14:38:58Z | K97: 0.209 | L97: 0.417 | M97: 3 | N97: -8.74 | O97: 1 | P97: 0.0338 | Q97: 0.164 | R97: 0.00196 | S97: 0.113 | T97: 0.124 | U97: 138.178 | V97: 4
A98: 0yLdNVWF3Srea0uzk55zFn | B98: Flowers | C98: Flowers | D98: Miley Cyrus | E98: 44939 | F98: 200454 | G98: 14 | H98: 125771062 | I98: 2023-05-12T10:18:11Z | K98: 0.707 | L98: 0.681 | M98: 0 | N98: -4.325 | O98: 1 | P98: 0.0668 | Q98: 0.0632 | R98: 5.15e-06 | S98: 0.0322 | T98: 0.646 | U98: 117.999 | V98: 4
A99: 1PVTvvxpSkyJWemW1CwVVk | B99: Fly Me To The Moon | C99: A Man And His Music | D99: Frank Sinatra | E99: 1965-12 | F99: 148866 | G99: 58 | H99: 125771062 | I99: 2022-09-20T14:38:58Z | J99: christmas,big band,adult standards,swing music,jazz,vocal jazz | K99: 0.623 | L99: 0.274 | M99: 5 | N99: -14.929 | O99: 1 | P99: 0.07 | Q99: 0.343 | R99: 3.16e-06 | S99: 0.0404 | T99: 0.427 | U99: 118.052 | V99: 4
A100: 4KoecuyOpZaNFZ0UqVsllc | B100: Follow Me | C100: Double Wide | D100: Uncle Kracker | E100: 36690 | F100: 218439 | G100: 75 | H100: 125771062 | I100: 2023-12-14T08:09:12Z | K100: 0.817 | L100: 0.585 | M100: 5 | N100: -4.688 | O100: 1 | P100: 0.0301 | Q100: 0.439 | R100: 0 | S100: 0.147 | T100: 0.916 | U100: 105.014 | V100: 4
A101: 1qRA5BS78u3gME0loMl9AA | B101: For What It's Worth | C101: Buffalo Springfield | D101: Buffalo Springfield | E101: 24446 | F101: 153693 | G101: 81 | H101: 125771062 | I101: 2022-09-20T14:38:58Z | J101: folk rock,country rock | K101: 0.653 | L101: 0.519 | M101: 2 | N101: -10.164 | O101: 1 | P101: 0.0497 | Q101: 0.406 | R101: 0.0209 | S101: 0.101 | T101: 0.822 | U101: 98.883 | V101: 4
...

Sheet Solo list
A1: # | B1: WIP | C1: Key | D1: Title | E1: Artist | F1: Cover? | G1: Year | H1: Genre 1 | I1: Genre 2 | J1: Listen
A3: =RAND() -> 0.58125853 | C3: Em | D3: 1973 | E3: James Blunt | G3: 2007 | H3: Rock | I3: Pop | J3: 1973
A4: =RAND() -> 0.10614696 | C4: F | D4: A Little More | E4: Eric Hutchinson | G4: 2014 | H4: Rock | I4: Pop | J4: A Little More
A5: =RAND() -> 0.45825664 | C5: Dm | D5: A Man For All Seasons | E5: Robbie Williams | G5: 2003 | H5: Soundtrack
A6: =RAND() -> 0.9818509 | C6: E | D6: A Thousand Miles | E6: Vanessa Carlton | G6: 2002 | H6: Pop | J6: A Thousand Miles
A7: =RAND() -> 0.44477797 | B7: WIP | C7: G# | D7: Africa | E7: Toto | G7: 2002 | H7: Rock | I7: Soft Rock | J7: Africa
A8: =RAND() -> 0.69016479 | C8: C# | D8: All About You | E8: McFly | G8: 2005 | H8: Rock | I8: Pop | J8: All About You
A9: =RAND() -> 0.86322065 | C9: D | D9: All I Have To Do Is Dream | E9: Everly Brothers | G9: 1958 | H9: Rock 'n' roll | J9: All I Have To Do Is Dream
A10: =RAND() -> 0.72426757 | D10: All I Want | E10: Kodaline | G10: 2013 | H10: Pop | I10: Indie | J10: All I Want
A11: =RAND() -> 0.63620216 | C11: F | D11: All Star | E11: Smash Mouth | G11: 1999 | H11: Rock | I11: Alternative | J11: All Star
A12: =RAND() -> 0.53939548 | C12: G | D12: Angel Of The Morning | E12: Juice Newton | G12: 1981 | H12: Country | J12: Angel Of The Morning
A13: =RAND() -> 0.48874262 | D13: Angels | E13: Robbie Williams | G13: 1997 | H13: Rock | I13: Pop / Gospel | J13: Angels
A14: =RAND() -> 0.25430003 | C14: D | D14: Annie's Song | E14: John Denver | G14: 1974 | H14: Rock | I14: Folk / Country | J14: Annie's Song
A15: =RAND() -> 0.047026725 | B15: WIP | C15: Bm | D15: Baby One More Time | E15: Britney Spears | G15: 1998 | H15: Pop
A16: =RAND() -> 0.14167386 | C16: Em | D16: Bistro Fada | E16: Stephane Wrembel | G16: 2011 | H16: Instrumental | I16: Gypsy Jazz | J16: Bistro Fada
A17: =RAND() -> 0.63873656 | C17: G | D17: Blackbird | E17: Beatles | G17: 1968 | H17: Folk | J17: Blackbird
A18: =RAND() -> 0.89719329 | C18: D | D18: Blowin' In The Wind | E18: Bob Dylan | G18: 1962 | H18: Folk
A19: =RAND() -> 0.95854732 | C19: D | D19: Breakfast At Tiffany's | E19: Deep Blue Something | G19: 1995 | H19: Rock | I19: Alternative | J19: Breakfast At Tiffany's
A20: =RAND() -> 0.25786772 | C20: G | D20: Brown Eyed Girl | E20: Van Morrison | G20: 1967 | H20: Rock
A21: =RAND() -> 0.97569984 | C21: F | D21: Budapest | E21: George Ezra | G21: 2013 | H21: Rock | I21: Folk
A22: =RAND() -> 0.75749022 | C22: D | D22: Bye Bye Love | E22: Everly Brothers | G22: 1957 | H22: Country | I22: Rock | J22: Bye Bye Love
A23: =RAND() -> 0.23643874 | C23: D | D23: Can't Help Falling In Love | E23: Elvis Presley | G23: 1961 | H23: Rock | I23: Soft Rock
A24: =RAND() -> 0.90598264 | D24: Carry You Home | E24: James Blunt | G24: 2008 | H24: Rock | I24: Folk | J24: Carry You Home
A25: =RAND() -> 0.91251057 | C25: F | D25: Closing Time | E25: Semisonic | G25: 1998 | H25: Rock | J25: Closing Time
A26: =RAND() -> 0.9025835 | D26: Cloud Number Nine | E26: Bryan Adams | G26: 1999 | H26: Pop | J26: Cloud Number Nine
A27: =RAND() -> 0.075947448 | D27: Count On Me | E27: Bruno Mars | G27: 2010 | H27: Pop
A28: =RAND() -> 0.76574598 | D28: Country Roads | E28: John Denver | G28: 1971 | H28: Country
A29: =RAND() -> 0.71377286 | C29: Cm | D29: Crazy | E29: Gnarles Barkley | G29: 2006 | H29: Soul | J29: Crazy
A30: =RAND() -> 0.90758171 | C30: D | D30: Crazy Little Thing Called Love | E30: Queen | G30: 1979 | H30: Rock | J30: Crazy Little Thing Called Love
A31: =RAND() -> 0.25475242 | B31: WIP | D31: Dance With Me Tonight | E31: Olly Murs | G31: 2011 | H31: Pop | J31: Dance With Me Tonight
A32: =RAND() -> 0.25626997 | D32: Dancing In The Moonlight | E32: Toploader | G32: 1999 | H32: Pop | J32: Dancing In The Moonlight
D33: Daughters | E33: John Mayer | G33: 2004 | H33: Rock | I33: Acoustic / Blues | J33: Daughters
A34: =RAND() -> 0.51333565 | C34: G | D34: Die, Die, Die | E34: Avett Brothers | G34: 2007 | H34: Folk | I34: Rock | J34: Die, Die, Die
A35: =RAND() -> 0.43458533 | B35: WIP | C35: F# | D35: Don't It Make My Brown Eyes Blue | E35: Crystal Gayle | G35: 1977 | H35: Jazz | I35: Country | J35: Don't It Make My Brown Eyes Blue
A36: =RAND() -> 0.073103616 | B36: WIP | C36: Bb | D36: Don't Know Why | E36: Norah Jones | F36: Jesse Harris | G36: 2002 | H36: Pop | I36: Jazz | J36: Don't Know Why
D37: Don't Look Back In Anger | E37: Oasis | G37: 1995 | H37: Pop | I37: Britpop
A38: =RAND() -> 0.41517025 | D38: Dream A Little Dream Of Me | E38: Various | F38: Laura Fygi | G38: 2002 | H38: Jazz | J38: Dream A Little Dream Of Me
A39: =RAND() -> 0.19578557 | D39: Earth Angel | E39: Death Cab for Cutie | F39: The Penguins | G39: 1954 | J39: Earth Angel
A40: =RAND() -> 0.18277667 | C40: G | D40: Eight Days A Week | E40: Beatles | G40: 1964 | H40: Rock | J40: Eight Days A Week
A41: =RAND() -> 0.8171083 | C41: F | D41: Escape (Pina Colada) | E41: Rupert Holmes | G41: 1979 | H41: Rock | J41: Escape (Pina Colada)
A42: =RAND() -> 0.51258669 | C42: F | D42: Every Little Thing She Does Is Magic | E42: Eric Hutchinson | F42: The Police | G42: 1981 | H42: Pop | J42: Every Little Thing She Does Is Magic
A43: =RAND() -> 0.95445733 | B43: WIP | C43: D | D43: Everything | E43: Michael Buble | G43: 2006 | H43: Pop | J43: Everything
A44: =RAND() -> 0.50360495 | C44: F | D44: Everything I Own | E44: Bread | G44: 1972 | H44: Rock | I44: Soft Rock | J44: Everything I Own
A45: =RAND() -> 0.84033744 | C45: G | D45: Faith | E45: George Michael | G45: 1987 | H45: Rock | I45: Pop | J45: Faith
A46: =RAND() -> 0.32459811 | D46: Fare Thee Well (Dink's Song) | E46: Various | G46: 2002 | H46: Folk | J46: Fare Thee Well (Dink's Song)
A47: =RAND() -> 0.60958514 | B47: WIP | D47: Fireflies | E47: Owl City | G47: 2009 | H47: Pop | I47: Synthpop | J47: Fireflies
A48: =RAND() -> 0.2886905 | D48: First Day Of My Life | E48: Bright Eyes | G48: 2005 | H48: Folk | I48: Indie | J48: First Day Of My Life
A49: =RAND() -> 0.51965415 | D49: Five Hundred Miles | E49: Peter, Paul, & Mary | G49: 1962 | H49: Folk | I49: Country
A50: =RAND() -> 0.83174368 | D50: Fix You | E50: Coldplay | G50: 2005 | H50: Rock | I50: Alternative | J50: Fix You
A51: =RAND() -> 0.41525784 | C51: Am | D51: Fly Me To The Moon | E51: Frank Sinatra | F51: Bart Howard | G51: 1954 | H51: Pop | I51: Traditional | J51: Fly Me To The Moon
A52: =RAND() -> 0.71075312 | D52: Free Falling | E52: John Mayer | F52: Tom Petty | G52: 1989 | H52: Rock | I52: Classic
A53: =RAND() -> 0.72852613 | B53: WIP | C53: Dm | D53: Give A Little More | E53: Maroon 5 | G53: 2010 | H53: Disco | J53: Give A Little More
A54: =RAND() -> 0.12810557 | B54: WIP | C54: F | D54: Goodnight, Goodbye | E54: Eric Hutchinson | G54: 2014 | H54: Rock | I54: Folk | J54: Goodnight, Goodbye
A55: =RAND() -> 0.040137961 | C55: G | D55: Grayscale | E55: Skye Zentz | G55: 2012 | H55: Folk | J55: Grayscale
A56: =RAND() -> 0.97730634 | B56: WIP | C56: Dm | D56: Grenade | E56: Bruno Mars | G56: 2010 | H56: RnB | I56: Pop | J56: Grenade
A57: =RAND() -> 0.73050809 | C57: G | D57: Guitar Man | E57: Bread | G57: 1972 | H57: Rock | J57: Guitar Man
A58: =RAND() -> 0.22952382 | D58: Hallelujah | E58: Jeff Buckley | F58: Leonard Cohen | G58: 1984 | H58: Rock | I58: Folk / Gospel | J58: Hallelujah
A59: =RAND() -> 0.038656426 | C59: C | D59: Have You Ever Seen The Rain | E59: CCR | G59: 1971 | H59: Rock | I59: Roots | J59: Have You Ever Seen The Rain
A60: =RAND() -> 0.32919749 | C60: Am | D60: Here Without You | E60: 3 Doors Down | G60: 2002 | H60: Rock | J60: Here Without You
A61: =RAND() -> 0.51615496 | C61: D | D61: Hey Jude | E61: Beatles | G61: 1968 | H61: Rock | I61: Pop | J61: Hey Jude
A62: =RAND() -> 0.15551626 | C62: D | D62: Hey There Delilah | E62: Plain White T's | G62: 2004 | H62: Pop | I62: Acoustic | J62: Hey There Delilah
A63: =RAND() -> 0.48684761 | C63: D | D63: Hey, Soul Sister | E63: Train | G63: 2002 | H63: Rock | I63: Folk / Pop | J63: Hey, Soul Sister
A64: =RAND() -> 0.22456251 | B64: WIP | C64: Am | D64: Hotel California | E64: Eagles | G64: 1976 | H64: Rock | J64: Hotel California
A65: =RAND() -> 0.32923836 | D65: Hymn For The Weekend | E65: Coldplay | G65: 2015 | H65: Pop | I65: Alternative | J65: Hymn For The Weekend
A66: =RAND() -> 0.54163363 | C66: D | D66: I Wanna Hold Your Hand | E66: Beatles | G66: 1963 | H66: Rock | I66: Pop
A67: =RAND() -> 0.18452135 | C67: D | D67: I Will Follow You Into The Dark | E67: Death Cab for Cutie | G67: 2006 | H67: Rock | I67: Acoustic / Indie | J67: I Will Follow You Into The Dark
A68: =RAND() -> 0.21277763 | C68: G# | D68: I'll Be There For You | E68: Rembrandts | G68: 1995 | H68: Rock | I68: Alternative / Pop | J68: I'll Be There For You
A69: =RAND() -> 0.34459609 | B69: WIP | C69: G | D69: I'm A Believer | E69: Monkees | G69: 1967 | H69: Pop | I69: 60s | J69: I'm A Believer
A70: =RAND() -> 0.82884617 | C70: Am | D70: Killing Me Softly | E70: Lori Lieberman | G70: 1972 | H70: Folk | J70: Killing Me Softly
A71: =RAND() -> 0.022031222 | B71: WIP | C71: D | D71: Kiss Me | E71: Sixpence None The Richer | G71: 2002 | H71: Rock | I71: Pop | J71: Kiss Me
A72: =RAND() -> 0.39652951 | D72: Leaving On A Jet Plane | E72: John Denver | G72: 1966 | H72: Folk | J72: Leaving On A Jet Plane
A73: =RAND() -> 0.63058889 | D73: Lemon Tree | E73: Fool's Garden | G73: 1995 | H73: Pop | J73: Lemon Tree
A74: =RAND() -> 0.017349505 | D74: Let Her Go | E74: Passenger | G74: 2012 | H74: Rock | I74: Folk / Indie | J74: Let Her Go
A75: =RAND() -> 0.81962496 | D75: Lonely Stranger | E75: Eric Clapton | G75: 1992 | H75: Rock | I75: Blues | J75: Lonely Stranger
A76: =RAND() -> 0.17509953 | C76: D | D76: Long Goodbyes | E76: Kurt Hunter | G76: 2009 | H76: Jazz | I76: Contemporary | J76: Long Goodbyes
A77: =RAND() -> 0.2207604 | D77: Lucky | E77: Jason Mraz | G77: 2009 | H77: Rock | I77: Acoustic / Pop | J77: Lucky
A78: =RAND() -> 0.43844682 | B78: WIP | D78: Make You Feel My Love | E78: Adele | F78: Bob Dylan | G78: 1997 | H78: Rock | I78: Blues | J78: Make You Feel My Love
A79: =RAND() -> 0.2304653 | B79: WIP | C79: Am | D79: Mary Jane's Last Dance | E79: Tom Petty & The Heartbreakers | G79: 1993 | H79: Rock | I79: Classic | J79: Mary Jane's Last Dance
A80: =RAND() -> 0.49524537 | B80: WIP | D80: Michelle | E80: Beatles | G80: 1965 | H80: Pop | J80: Michelle
A81: =RAND() -> 0.61850898 | B81: WIP | D81: Moon River | E81: Various | F81: Audrey Hepburn | G81: 1961 | H81: Easy Listening | J81: Moon River
A82: =RAND() -> 0.74874559 | B82: WIP | D82: More Than A Friend | E82: MLTR | G82: 2000 | H82: Pop | J82: More Than A Friend
A83: =RAND() -> 0.7448153 | C83: C | D83: Mr Blue Sky | E83: Electric Light Orchestra | G83: 1977 | H83: Rock | I83: Pop | J83: Mr Blue Sky
A84: =RAND() -> 0.34528397 | D84: My Love | E84: Westlife | G84: 2000 | H84: Pop | J84: My Love
A85: =RAND() -> 0.49171089 | D85: Norwegian Wood | E85: Beatles | G85: 1965 | H85: Folk Rock | J85: Norwegian Wood
A86: =RAND() -> 0.82443434 | D86: Numb | E86: Linkin Park | G86: 2003 | H86: Metal | I86: Alternative | J86: Numb
A87: =RAND() -> 0.38649663 | D87: Oh, Carol | E87: Neil Sedaka | G87: 1995 | H87: Rock
A88: =RAND() -> 0.1327755 | C88: Em | D88: One Love | E88: Blue | G88: 2002 | H88: Pop | J88: One Love
A89: =RAND() -> 0.12233329 | B89: WIP | C89: C | D89: Open Book | E89: Mikey McCleary | G89: 2015 | H89: Pop | J89: Open Book
A90: =RAND() -> 0.14221891 | C90: G | D90: Paradise | E90: Coldplay | G90: 2011 | H90: Rock | I90: Alternative | J90: Paradise
A91: =RAND() -> 0.14586576 | B91: WIP | C91: Gm | D91: Part-Time Lover | E91: Stevie Wonder | G91: 1985 | H91: RnB
A92: =RAND() -> 0.36152007 | C92: F | D92: Photograph | E92: Ed Sheeran | G92: 2014 | H92: Pop | J92: Photograph
A93: =RAND() -> 0.015420929 | C93: C | D93: Piano Man | E93: Billy Joel | G93: 1973 | H93: Pop | J93: Piano Man
A94: =RAND() -> 0.97747241 | C94: G | D94: Poetry In Motion | E94: Johnny Tillotson | F94: Paul Kaufman; Mike Anthony | G94: 1960 | H94: Doo-wop | I94: Pop | J94: Poetry In Motion
A95: =RAND() -> 0.054168208 | D95: Price Tag | E95: Jessie J | G95: 2011 | H95: Pop
A96: =RAND() -> 0.86218767 | B96: WIP | C96: G | D96: Quando Quando Quando | E96: Engelbert Humperdinck | G96: 1962 | H96: Bossa nova
A97: =RAND() -> 0.21316366 | C97: G | D97: Rhythm Of Love | E97: Plain White T's | G97: 2010 | H97: Rock | I97: Indie / Pop | J97: Rhythm Of Love
D98: Ring Of Fire | E98: Johnny Cash | F98: Anita Carter | G98: 1962 | H98: Folk
A99: =RAND() -> 0.85994947 | C99: A | D99: Rock 'n' Roll | E99: Eric Hutchinson | G99: 2008 | H99: Rock | I99: Pop | J99: Rock 'n' Roll
A100: =RAND() -> 0.11238083 | C100: F#m | D100: Rocket Man | E100: Elton John | G100: 1972 | H100: Rock | I100: Soft
A101: =RAND() -> 0.61769749 | B101: WIP | D101: Skyfall | E101: Adele | G101: 2012 | H101: Pop
...
